Workbook

Sheet Summary
A1: ARCHEGON CAPITAL — PoC financial model. One page, then the evidence behind it.
A3: A pure venture opportunity starting from zero: buy the land, buy or contract the power, buy the compute, build the infrastructure, obtain the legals. Proof of concept in Australia and/or New Zealand.
A5: AT THE CURRENT CONTROL SETTINGS
A6: Route | B6: =Control!$B$4 | C6: Control switch.
A7: Compute model | B7: =Control!$B$5 | C7: Control switch.
A8: PoC capacity (MW critical IT) | B8: =Raise!$B$22 | C8: Control input, multiplied by sites funded. BOTH delivers two PoC sites.
A9: TOTAL RAISE (AUD) | B9: =Raise!$B$14 | C9: Derived on the Raise tab. A FLOOR — every RATE_MISSING line sits at zero.
A10: Total raise (USD) | B10: =Raise!$B$15 | C10: At the Rates FX.
A11: Raise per kW of critical IT (AUD) | B11: =Raise!$B$23
A12: Annual contribution once built and full (AUD) | B12: ='Compute-Revenue'!$B$31 | C12: Revenue less opex. Not EBITDA, not a return.
A13: Contribution as a share of the raise (3.3% at base: below any cost of capital) | B13: =IF('Compute-Revenue'!$B$31<=0,"n/a — contribution is not positive",B12/B9) | C13: The first ratio a VC computes. Against a raise that is itself a FLOOR — six RATE_MISSING lines sit at zero — and an opex line that is also a floor.
A14: Years of contribution to return the ask | B14: =Raise!$B$24 | C14: Not a payback period and not an IRR — no discounting, no ramp, no terminal value. State this number yourself before it is computed for you.
A16: THE TWO ROUTES, SIDE BY SIDE
A17: Australia — total capex (AUD) | B17: ='AU-Route'!$B$43 | C17: A DRILLING play. Cooper Basin EGS. Archegon owns the reservoir.
A18: Australia — wells in the programme | B18: ='AU-Route'!$B$10 | C18: Producers plus injectors, at the selected productivity case.
A19: New Zealand — total capex (NZD) | B19: ='NZ-Route'!$B$38 | C19: A CONTRACTING play. TVZ. Archegon owns a contract, not a reservoir.
A20: AU drilling spread, cheapest corner to dearest | B20: =Sensitivity!$B$15 | C20: Drilling alone, before a single server. The number to show first.
A22: HOW TO READ THIS WORKBOOK
A23: • Control is the only tab with switches. Change one and every number in the workbook moves.
A24: • Rates holds every sourced constant. The only unsourced figures are the Control inputs — capacity, contingency, runway, burn, capacity factor and PUE — each labelled ASSUMPTION where no finding exists.
A25: • Traceability maps each rate to the finding id in facts/ that produced it.
A26: • AU-Route and NZ-Route each carry four blocks: land, infrastructure, compute, legals.
A28: EVIDENCE QUALITY — stated up front, not buried
A29: Rates by status
A30: DERIVED | B30: =COUNTIF(Rates!$E$4:$E$90,$A30) | C30: Computed here from sourced inputs. The arithmetic is shown.
A31: INDICATIVE | B31: =COUNTIF(Rates!$E$4:$E$90,$A31) | C31: A single source, or a vendor figure, not independently confirmed.
A32: RATE_MISSING | B32: =COUNTIF(Rates!$E$4:$E$90,$A32) | C32: NO SOURCE EXISTS. Ships at zero. A gap in the evidence, not a zero-cost item.
A33: VERIFIED | B33: =COUNTIF(Rates!$E$4:$E$90,$A33) | C33: Traced to a primary source and checked by an independent verifier.
A34: VERIFIED-ESTIMATE | B34: =COUNTIF(Rates!$E$4:$E$90,$A34) | C34: Sourced, but the source is itself an estimate or a range.
A36: • v3: RATE_MISSING is counted by LINE on the route tabs (AU: 7 capex + 2 opex; NZ: 10), plus the new firm-power lines (BESS, standby, black start, hot-day derate, stimulation/test facilities). The rate-key tally above counts keys, not lines.
A37: • No rate in this workbook depends on a CONTESTED finding. That was checked at build time, not asserted.
A38: • This model produces no IRR and no NPV. An IRR built on RATE_MISSING blocks would be fiction with a decimal point on it — so the honest headline is the contribution-to-raise ratio above, stated plainly rather than omitted.
A40: • v2 (10 Oct 2026): added Funding-Tiers (A$50m-A$500m sizing from the same unit economics) and Deck-Check (deck figures vs live model). No input, rate or formula on the original nine tabs was changed.
A41: • v3 (12 Oct 2026): every point in the v3 review is tracked in CRITIQUE-TRACKER.md. New tabs: Definitions, Flow-Basis, Power-Economics, DC-Economics, Route-Compare, Firm-Power, Gated-Plan; Funding-Tiers rebuilt (whole modules, value optimiser). Headline reference raise unchanged at Control settings (Control BOTH now carries two teams).
A42: • Read first: contribution is 3.3% of the raise; the power system costs about what the hall earns; the first capital that retires the key risk is a ~A$52m reservoir test (Gated-Plan).
A44: RENTAL (colo) vs SELL COMPUTE (GPU-as-a-service), AU 5 MW reference: see Sell-Compute tab. PUBLIC PROXY inputs.
A45: Colo: total capital, A$ | B45: ='Sell-Compute'!$I$36
A46: Colo: annual contribution, A$ | B46: ='Sell-Compute'!$I$46
A47: Colo: 25-yr IRR | B47: ='Sell-Compute'!$I$51
A48: Compute: total capital incl. GPUs, A$ | B48: ='Sell-Compute'!$B$36
A49: Compute: EBITDA yr 1, A$ | B49: ='Sell-Compute'!$B$46
A50: Compute: 25-yr IRR, prices decay ~25%/yr | B50: ='Sell-Compute'!$B$51
A51: Compute: 25-yr IRR, flat prices | B51: ='Sell-Compute'!$C$51
A52: Compute downside (47% util, remote discount, decay): IRR | B52: ='Sell-Compute'!$F$51
A53: NZ compute: IRR decay / flat | B53: ='Sell-Compute'!$D$51
B54: ='Sell-Compute'!$E$51

Sheet Control
A1: ARCHEGON CAPITAL · CONTROL — every switch that drives the model lives here
A3: Switch | B3: Setting | C3: What it does | D3: Allowed values
A4: Route | B4: AU | C4: Which route the Summary and Raise tabs report. Both route tabs always compute; this picks what rolls up. | D4: AU / NZ / BOTH
A5: Compute model | B5: COLO | C5: Revenue basis. COLO = sell space+power per kW. ANCHOR = long take-or-pay lease. BAREMETAL = own the GPUs, sell compute. | D5: COLO / ANCHOR / BAREMETAL
A6: Well productivity | B6: BASE | C6: MWe per production well. LOW = GeoExpro bear case (2 MWe). BASE = 4-6 MWe midpoint. HIGH = Fervo claim (10-16), unproven at scale. v3: all cases are NET MWe per producer at the plant fence (see Definitions); HIGH is a gross source figure used as an upper bound. | D6: LOW / BASE / HIGH
A7: Well cost case | B7: BASE | C7: AU drilling cost. LOW = best-case learning. BASE = engineered 5-well campaign. HIGH = single well, no campaign learning. ACTUAL = Habanero 4 as drilled. | D7: LOW / BASE / HIGH / ACTUAL
A8: Cooling | B8: LIQUID | C8: LIQUID applies the liquid-cooling premium. AIR does not. GB200-class density requires LIQUID. | D8: AIR / LIQUID
A9: Remote loading | B9: ON | C9: Applies the remote-site construction loading to the AU facility build. NZ sites are near existing infrastructure. | D9: ON / OFF
A11: Sizing and scenario inputs
A12: PoC capacity (MW critical IT) | B12: 5 | C12: Target compute load for the proof of concept.
A13: Contingency % | B13: 0.25 | C13: Applied to every capex block. A first-of-a-kind project.
A14: Operating runway (months) | B14: 24 | C14: Pre-revenue months the raise must fund.
A15: Team + overhead (AUD/month) | B15: 250000 | C15: Burn rate during the PoC. ASSUMPTION.
A16: Capacity factor | B16: 0.9 | C16: Average availability. Used to size NAMEPLATE (net) so ANNUAL energy matches the load. It is NOT a firm-power guarantee: see Firm-Power.
A17: Facility PUE (total facility power ÷ critical IT) | B17: 1.25 | C17: ASSUMPTION — no sourced finding exists for this in the evidence base. Liquid-cooled AI halls typically run 1.15-1.35. Critical IT is what is SOLD; PUE grosses it up to what the site must generate or buy. Set to 1.00 to reproduce the pre-review model. | D17: typically 1.15 - 1.35
A18: Sites funded (derived from Route) | B18: =IF($B$4="BOTH",2,1) | C18: Derived, not an input. BOTH builds a PoC on each route, so capacity, capex, revenue and opex all count twice. This cell is what keeps them consistent.
A21: Reading this model
A22: • Blue cells are inputs. Everything else is a formula — change an input and the whole model moves.
A23: • Every rate on the Rates tab names the finding it comes from and carries a status label.
A24: • RATE_MISSING rows ship at zero. They are gaps in the evidence base, not zero-cost items.
A25: • No figure in this workbook was typed from memory. Traceability maps every rate to a finding id.
A26: • Google Sheets: upload this .xlsx to Drive and Open with Google Sheets. Dropdowns and formulas transfer. Do not convert to a Google-native sheet that rewrites formulas. Blue cells stay the only inputs.

Sheet Definitions
A1: ARCHEGON · DEFINITIONS (v3): one meaning per word, used on every tab, slide, diagram and web page
A3: Gross (MW) | B3: Electrical output at the generator terminals, before the plant's own load.
A4: Parasitic load (MW) | B4: Power the plant uses itself: injection/reinjection pumps, ORC feed pumps, air-cooled condenser fans, plant services. For EGS, injection pumping dominates.
A5: Net (MW) | B5: Gross minus parasitic load = what the plant delivers to the site switchboard ("at the fence"). EVERY MWe-per-producer figure in this model is NET.
A6: Nameplate (MW, net) | B6: The net capacity the plant is built to deliver when running. AU-Route!B7 = IT x PUE / capacity factor = 6.94 MW.
A7: Average (MW) | B7: Nameplate x capacity factor (0.90) = 6.25 MW. This is an ANNUAL-ENERGY figure. It is what v2 wrongly called "firm".
A8: Firm (MW) | B8: Power guaranteed in every hour, including with the largest single element out (N-1: one producer, one ORC unit or one transformer). Today the design has NO firm figure above 5.0 MW (one producer out) and no backup: see Firm-Power.
A9: Facility load (MW) | B9: Critical IT x PUE. 5.0 MW IT x 1.25 = 6.25 MW.
A10: Critical IT (MW) | B10: Power to the racks. Sold in whole 1.25 MW modules (Rates module_mw_it).
A11: Contribution | B11: Revenue minus the opex lines in this model. NOT EBITDA, not a return, not a cash yield; excludes RATE_MISSING opex, financing, tax, ramp.
A12: Operating break-even hall | B12: The smallest build whose contribution is zero. v2 called this "minimum viable PoC"; it is NOT viable, it never returns capital.
A13: Reservoir-test tranche | B13: One doublet + rig mobilisation + contingency + runway, with no plant and no hall. Buys a 90-180 day circulation test (Gated-Plan).
A14: Transfer price | B14: The price at which PowerCo (wells + ORC) sells energy to DCCo (the hall). Set equal to PowerCo's levelised cost (Power-Economics) so each business stands on its own.
... A16: RATE_MISSING | B16: No source exists yet. Ships at A$0. The total is understated by that line.

Sheet Rates
A1: ARCHEGON CAPITAL · RATES — every constant, with its source finding and status label
A3: Key | B3: Rate | C3: Unit | D3: Value | E3: Status | F3: Finding id | G3: Note / what the status means
A4: fx_aud_usd | B4: AUD -> USD | C4: USD per AUD | D4: 0.7122 | E4: VERIFIED | F4: geothermal-capex-71 | G4: Restates USD benchmarks into AUD. Point-in-time rate.
A5: fx_aud_nzd | B5: AUD -> NZD | C5: NZD per AUD | D5: 1.2365 | E5: VERIFIED | F5: geothermal-capex-71 | G5: Implies 1 USD = 1.404 AUD and 1 USD = 1.736 NZD.
A6: au_well_cost_base | B6: Cooper Basin EGS well, engineered forward cost | C6: AUD/well | D6: 16500000 | E6: VERIFIED-ESTIMATE | F6: geothermal-capex-30 | G6: Geodynamics optimised slim-bore 5-well campaign average.
A7: au_well_cost_low | B7: Cooper Basin well, best case with high learning | C7: AUD/well | D7: 14000000 | E7: VERIFIED-ESTIMATE | F7: geothermal-capex-30 | G7: Best case in the same engineered estimate.
A8: au_well_cost_high | B8: Cooper Basin well, single-well (no campaign learning) | C8: AUD/well | D8: 22700000 | E8: VERIFIED-ESTIMATE | F8: geothermal-capex-30 | G8: One-off well; the cost if no campaign is assembled.
A9: au_well_actual_h4 | B9: Habanero 4 actual drilled cost | C9: AUD/well | D9: 50850000 | E9: VERIFIED | F9: geothermal-capex-29 | G9: The ANTI-learning curve: last well cost 4.5x the first.
A10: au_rig_day_rate | B10: Australian onshore rig day rate | C10: AUD/day | D10: 50000 | E10: VERIFIED | F10: geothermal-capex-31 | G10: Habanero field development plan assumption.
A11: au_rig_mob | B11: Rig mobilisation / demobilisation | C11: AUD | D11: 4000000 | E11: VERIFIED | F11: geothermal-capex-31 | G11: Single mob/demob for a Cooper Basin campaign.
A12: mwe_per_well_base | B12: MWe per producer - BASE (NET: at the plant fence, after plant parasitics; see Definitions) | C12: MWe | D12: 5 | E12: DERIVED | F12: geothermal-capex-15 | G12: DERIVED base case 4-6 MWe; midpoint used.
A13: mwe_per_well_low | B13: MWe per producer - LOW (NET: at the plant fence, after plant parasitics) | C13: MWe | D13: 2 | E13: DERIVED | F13: geothermal-capex-15 | G13: GeoExpro triplet-implied bear case.
A14: mwe_per_well_high | B14: MWe per producer - HIGH (source figure is GROSS; treated as NET here = optimistic upper bound) | C14: MWe | D14: 13 | E14: DERIVED | F14: geothermal-capex-15 | G14: Fervo claim 10-16 MWe per producer, quoted GROSS by the source. v3: the model has ONE convention (net at the fence). Using a gross figure as net overstates HIGH by the parasitic fraction (13.8%-29%, see rows 62-63). Kept only as an upper-bound sensitivity.
A15: plant_usd_per_kw | B15: 50 MW binary ORC plant, brownfield (wells already drilled) | C15: USD/kW | D15: 3963 | E15: VERIFIED | F15: geothermal-capex-16 | G15: EIA 2023 USD, USD 198.1m for 50 MW net.
... A43: dc_opex_usd_mw_yr | B43: Data centre non-energy opex (maintenance, insurance, security, connectivity, rates) | C43: USD/MW/yr | D43: 0 | E43: RATE_MISSING | F43: NO FINDING — gap raised in model review | G43: RATE_MISSING. Applies to BOTH routes. The evidence base covers data centre CAPEX benchmarks but carries no operating cost benchmark. Ships at zero, so the contribution line is an overstatement by exactly this amount.
A45: Status labels
A46: VERIFIED | B46: The figure appears in the cited source and an independent verifier confirmed it.
A47: VERIFIED-ESTIMATE | B47: Sourced, but the source itself presents it as an estimate or a range.
A48: DERIVED | B48: Arithmetic on sourced figures. The inputs are sourced; this number is not published.
A49: INDICATIVE | B49: A trade or market figure without a primary source behind it. Directionally useful only.
A50: CONTESTED | B50: An independent verifier raised a MAJOR against this figure. Do NOT present it as sourced.
A51: RATE_MISSING | B51: No published figure exists. Ships at zero. A gap in the evidence, not a zero cost.
A52: V3 ADDITIONS (12 Oct 2026): rates added to answer the v3 review
A53: hab_closed_loop_kg_s | B53: Habanero best sustained closed-loop circulation (2013, 160-day pilot) | C53: kg/s | D53: 19 | E53: INDICATIVE | F53: ThinkGeoEnergy 8 Oct 2013 | G53: Verify against the Geodynamics final reports before external use.
A54: hab_open_flow_kg_s | B54: Habanero 4 stabilised open-flow rate | C54: kg/s | D54: 39 | E54: INDICATIVE | F54: ThinkGeoEnergy | G54: 40-50 kg/s claimed at full drawdown.
A55: hab_wellhead_c | B55: Habanero 4 wellhead temperature, maximum | C55: degC | D55: 215 | E55: INDICATIVE | F55: ThinkGeoEnergy 2013
A56: red_flow_kg_s | B56: Fervo Project Red peak flow (63 L/s ~ 63 kg/s) | C56: kg/s | D56: 63 | E56: VERIFIED | F56: Norbeck & Latimer 2023 (EarthArXiv) | G56: Peak test, not sustained.
A57: red_peak_mwe | B57: Fervo Project Red peak electric equivalent | C57: MWe | D57: 3.5 | E57: VERIFIED | F57: Norbeck & Latimer 2023 | G57: Calculated electric equivalent, assumes supercritical ORC; not metered.
A58: red_temp_c | B58: Fervo Project Red production temperature (336 F) | C58: degC | D58: 169 | E58: VERIFIED | F58: Norbeck & Latimer 2023
A59: fervo_sust_flow_kg_s | B59: Fervo Project Red sustained average circulation (614+ days) | C59: kg/s | D59: 36 | E59: INDICATIVE | F59: Fervo operating update Apr 2026 | G59: Verify page reference.
A60: fervo_sust_gross_mw | B60: Fervo Project Red sustained average gross output | C60: MW | D60: 2.1 | E60: INDICATIVE | F60: Fervo operating update Apr 2026
A61: fervo_sust_net_mw | B61: Fervo Project Red sustained average net output | C61: MW | D61: 1.4 | E61: INDICATIVE | F61: Fervo operating update Apr 2026; deck slide 5
A62: parasitic_eia | B62: Parasitic load, conventional binary plant (EIA Case 11: ~58 MW gross for 50 MW net) | C62: share of gross | D62: 0.138 | E62: VERIFIED | F62: EIA capital cost study (geothermal-capex-16)
A63: geoexpro_pump_mw | B63: Cape Station test: injection pumping estimate | C63: MW | D63: 2.5 | E63: INDICATIVE | F63: GeoExpro, Yearsley & Kombrink, 1 Oct 2025 | G63: Critic estimate, not company data.
A64: geoexpro_gross_mw | B64: Cape Station test: gross output estimate | C64: MW | D64: 8.7 | E64: INDICATIVE | F64: GeoExpro, 1 Oct 2025
A65: parasitic_egs_stress | B65: EGS parasitic stress case = pumping / gross | C65: share of gross | D65: =D63/D64 | E65: DERIVED | F65: Arithmetic on rows 63-64 | G65: Replaces the unsourced "Fervo ~33%" used in v2. Use as stress, not as a Cooper Basin prediction.
A66: cp_water | B66: Specific heat of hot water (constant-cp approximation) | C66: kJ/kg.K | D66: 4.2 | E66: ASSUMPTION | F66: Physics approximation | G66: Used only on Flow-Basis.
A67: dead_state_c | B67: Dead-state (ambient) temperature for exergy | C67: degC | D67: 25 | E67: ASSUMPTION | F67: Archegon screening method
A68: exergy_util_low | B68: Share of brine exergy converted to gross power - low | C68: share | D68: 0.4 | E68: ASSUMPTION | F68: Archegon screening method | G68: Project Red back-calculates to ~50% (Flow-Basis).
A69: exergy_util_high | B69: Share of brine exergy converted to gross power - high | C69: share | D69: 0.5 | E69: ASSUMPTION | F69: Archegon screening method
A70: wacc_base | B70: Discount rate for levelised cost (base) | C70: % | D70: 0.08 | E70: ASSUMPTION | F70: Sensitivity range 6/8/10% | G70: Not a sourced cost of capital. Sensitivity on Power-Economics.
A71: asset_life_yrs | B71: Asset life for levelised cost | C71: years | D71: 25 | E71: ASSUMPTION | F71: Archegon assumption
A72: px_sa_aud_mwh | B72: SA wholesale average price | C72: AUD/MWh | D72: 88 | E72: VERIFIED | F72: Same source as D34 (note G34) | G72: Wholesale only; a grid-connected load also pays network and retail charges.
A73: diesel_l_per_kwh | B73: Diesel genset fuel rate | C73: L/kWh | D73: 0.26 | E73: ASSUMPTION | F73: Range 0.25-0.27 | G73: Illustrative only; diesel price RATE_MISSING.
A74: bess_cost | B74: Grid-forming BESS for islanded frequency control | C74: AUD | D74: 0 | E74: PUBLIC PROXY (see Proxies tab) | F74: No finding | G74: Needs a power-systems study and vendor quote.
A75: standby_gen_cost | B75: Standby generation (gensets or local gas) for N-1 cover | C75: AUD | D75: 0 | E75: PUBLIC PROXY (see Proxies tab) | F75: No finding | G75: Cooper Basin is a gas province: local gas is an option to price.
A76: black_start_cost | B76: Black-start source for ORC auxiliaries | C76: AUD | D76: 0 | E76: PUBLIC PROXY (see Proxies tab) | F76: No finding | G76: Mandatory for an islanded ORC.
A77: orc_hot_day_derate | B77: Air-cooled ORC output loss on a 40+ degC day | C77: share | D77: 0 | E77: RATE_MISSING | F77: Vendor derate curve needed | G77: Sensitivities on Firm-Power are illustrative, not vendor data.
A78: stim_test_facility_cost | B78: Stimulation, completion and well-test facilities (if not inside the well cost) | C78: AUD | D78: =Rates!$D$89*'AU-Route'!$B$10 | E78: DERIVED | F78: v4: stimulation per well (D89) x all wells; in AU capex
A79: makeup_interval_yrs | B79: One make-up well every N years (decline provision) | C79: years | D79: 5 | E79: ASSUMPTION | F79: Illustration | G79: Sensitivity only; D42 stays RATE_MISSING until a decline case exists.
A80: km_innamincka_adelaide | B80: Innamincka to Adelaide, straight line | C80: km | D80: 820 | E80: DERIVED | F80: Great-circle from coordinates (box calc 823 km; 820 km) | G80: Road distance is longer. Replaces "~1,000 km" (AU-Route C28) and "750 km" (NZ-Route C21).
A81: orc_scale_exponent | B81: Generic plant cost scale exponent (scale penalty sensitivity) | C81: x | D81: 0.6 | E81: ASSUMPTION | F81: Archegon assumption | G81: Sensitivity only. Replace with two ORC supplier quotes.
A82: module_mw_it | B82: Data-centre module step | C82: MW IT | D82: 1.25 | E82: ASSUMPTION | F82: Design choice shown in Diagram E | G82: v3 enforces whole modules in Funding-Tiers.
A83: colo_remote_discount | B83: Remote / islanded colo price discount (illustrative) | C83: share | D83: 0.2 | E83: ASSUMPTION | F83: Illustration | G83: Sensitivity only. Replace with broker view and tenant LOIs.
A84: fervo_kw_s1a | B84: Fervo first Cape Station project, overnight capital cost | C84: USD/kW | D84: 7000 | E84: VERIFIED-ESTIMATE | F84: Fervo S-1/A filed 4 May 2026 | G84: Basis: OVERNIGHT, first project. Deck v2 mis-dated this as 31 Dec 2025.
A85: fervo_kw_phase2 | B85: Fervo Phase II expected cost | C85: USD/kW | D85: 5500 | E85: VERIFIED-ESTIMATE | F85: Fervo Q2 2026 results, 12 Aug 2026 | G85: Basis: ALL-IN expected. Not as-built.
A86: fervo_kw_target | B86: Fervo long-term target cost | C86: USD/kW | D86: 3000 | E86: VERIFIED-ESTIMATE | F86: Fervo S-1/A, 4 May 2026 | G86: Basis: Nth-of-a-kind target.
A87: v4 INPUTS (14 Oct 2026): stimulation, bores, grid comparator, N-1, monitoring
A88: stim_share | B88: Stimulation + completion per well, share of drilled well cost | C88: share | D88: 0.5 | E88: ASSUMPTION | F88: EIA Trends in U.S. Oil and Natural Gas Upstream Costs (2016): completion 55-70% of onshore well cost; frac pumps, proppant and fluids ~50%. https://www.eia.gov/analysis/studies/drilling/pdf/upstream.pdf | G88: Shale analogue; a granite EGS stimulation may cost more. Replace with an AFE.
A89: stim_well | B89: Stimulation + completion per well, A$ | C89: AUD/well | D89: =D88*'AU-Route'!$B$18 | E89: DERIVED | F89: Share above x scenario well cost
A90: bore_low | B90: GAB replacement bore (redrill and plug), average | C90: AUD/bore | D90: 72420 | E90: PUBLIC PROXY | F90: Queensland GABSI implementation plan 2013-14. https://federalfinancialrelations.gov.au/sites/federalfinancialrelations.gov.au/files/2021-07/GAB_QLD_13-14_Impl_Plan.pdf | G90: Mostly shallow stock bores; deep Cooper-area GAB bores cost more.
A91: bore_high | B91: GAB bore, capped and piped, upper report | C91: AUD/bore | D91: 300000 | E91: PUBLIC PROXY | F91: Queensland Country Life (grazier quote, 2015). https://www.queenslandcountrylife.com.au/story/3573472/plug-pulled-on-basin-funding/ | G91: Used as the base for a deep bore at site; quote needed.
A92: stim_water_ml | B92: Water for one multistage stimulation | C92: ML | D92: 18.76 | E92: PUBLIC PROXY | F92: Utah FORGE 2024: 118,000 bbl across 12 stages (AAPG Explorer). https://www.aapg.org/news-and-media/explorer/utah-forge-completes-stimulation-circulation-tests/ | G92: Habanero 2003 injected ~20,000 m3 (Asanuma et al. 2006).
A93: seis_station_usd | B93: Permanent seismic station, installed | C93: USD/station | D93: 37075 | E93: PUBLIC PROXY | F93: USArray Transportable Array adopt-a-station cost. http://www.usarray.org/files/docs/pubs/TA_AdoptStn_L48.pdf | G93: Surface station; borehole sensors cost more.
A94: seis_stations | B94: Stations for a baseline network | C94: stations | D94: 8 | E94: PUBLIC PROXY | F94: DOE induced-seismicity protocol for EGS (min. 8 three-component stations, 1-6 months baseline). https://geocom.geonardo.com/assets/elearning/8.33.geothermal_seismicity_protocol_012012.pdf
A95: seis_om_usd | B95: Seismic station support | C95: USD/station/yr | D95: 5000 | E95: PUBLIC PROXY | F95: USArray (as above)
A96: grid_fee_mw | B96: Grid connection fee, metro (proposed NSW framework) | C96: AUD/MW | D96: 200000 | E96: PUBLIC PROXY | F96: King & Wood Mallesons on the NSW data-centre connection framework. https://www.mallesons.com/au/en/insights/latest-thinking/another-big-day-for-data-centres-in-nsw-a-new-framework-for-connection.html | G96: Before project-specific augmentation; SA has no published equivalent.
A97: grid_lead_mo | B97: Metro grid connection lead time | C97: months | D97: 15 | E97: PUBLIC PROXY | F97: Developers guide to SAPN connections: typically 12-18 months. https://www.adelaidepds.com.au/_files/ugd/b145bb_873f7589396b4d529f71288f06a6b354.pdf | G97: Midpoint.
A98: sapn_hv_peak | B98: SAPN HV business energy, peak | C98: AUD/kWh | D98: 0.073 | E98: PUBLIC PROXY | F98: SA Power Networks 2026-27 tariff (HVAD). https://www.aer.gov.au/system/files/2026-04/SA%20Power%20Networks%20%E2%80%93%202026%E2%80%9327%20%E2%80%93%20Customer%20Overview%20Document%20%E2%80%93%2010%20April%202026.pdf | G98: Peak 7am-9pm workdays.
A99: sapn_hv_off | B99: SAPN HV business energy, off-peak | C99: AUD/kWh | D99: 0.0456 | E99: PUBLIC PROXY | F99: Same
A100: sapn_hv_dem | B100: SAPN HV annual demand charge | C100: AUD/kVA/day | D100: 0.2696 | E100: PUBLIC PROXY | F100: Same (column read as annual demand; confirm with SAPN)
A101: peak_share | B101: Share of hours in the SAPN peak window (14 h x 5 days / 168 h) | C101: share | D101: =14*5/168 | E101: DERIVED | F101: Tariff definition
A102: retail_margin | B102: Retail, metering and green-scheme margin on wholesale + network | C102: share | D102: 0.1 | E102: ASSUMPTION | F102: Archegon assumption | G102: Replace with a retail quote.
A103: orc_trains | B103: ORC N-1: two 50% trains instead of one (cost multiple) | C103: x | D103: =2*0.5^D81 | E103: DERIVED | F103: Rates D81 scale exponent
A104: hurdle | B104: Investor hurdle IRR for the G4 commercial kill test | C104: share | D104: 0.1 | E104: ASSUMPTION | F104: Round-3 reviewers tested 10% | G104: Set by the lead investor.

Sheet AU-Route
A1: ARCHEGON CAPITAL · AUSTRALIA — Cooper Basin EGS. Buy the land, drill the wells, build the plant, build the hall.
A3: Australia is a drilling play. The heat is there and measured; the permeability is not. That is what the capital buys.
A5: RESOURCE SIZING | F5: drives well count
A6: Net MWe per producer (scenario; NET at the plant fence) | B6: =IF(Control!$B$6="LOW",Rates!$D$13,IF(Control!$B$6="HIGH",Rates!$D$14,Rates!$D$12)) | C6: LOW = GeoExpro bear case. HIGH = Fervo claim, unproven at fleet scale.
A7: Net generation nameplate required (MW, after parasitics) | B7: =Control!$B$12*Control!$B$17/Control!$B$16 | C7: Critical IT x PUE / capacity factor. NET nameplate: what the plant must deliver to the site board after its own parasitic load (injection pumps, ORC feed pumps, condenser fans, plant services). Matches the EIA per-NET-kW plant rate. Delivers 6.25 MW on AVERAGE, not firm (see Firm-Power).
A8: Production wells required | B8: =ROUNDUP(B7/B6,0) | C8: Rounded up — you cannot drill a partial well.
A9: Injection wells required | B9: =B8 | C9: Doublet architecture: one injector per producer. Fervo runs this pattern.
A10: TOTAL wells | B10: =B8+B9
A12: BLOCK 1 — LAND | F12: AUD
A13: Surface land / pastoral lease access | B13: 0 | C13: RATE_MISSING. Pastoral lease over the Cooper Basin footprint. Lessee and compensation regime not yet established — see legals-land open questions.
A14: Site preparation and access roads | B14: 0 | C14: RATE_MISSING. Remote site; no public benchmark located.
A15: Land subtotal | B15: =SUM(B13:B14) | C15: Both lines are RATE_MISSING. This block is UNDERSTATED, not cheap.
A17: BLOCK 2 — INFRASTRUCTURE (subsurface + surface plant) | F17: AUD
A18: Cost per well (scenario) | B18: =IF(Control!$B$7="LOW",Rates!$D$7,IF(Control!$B$7="HIGH",Rates!$D$8,IF(Control!$B$7="ACTUAL",Rates!$D$9,Rates!$D$6))) | C18: BASE is Geodynamics' engineered forward estimate, never realised. ACTUAL is Habanero 4 as drilled — 4.5x the first well. Run ACTUAL before believing BASE.
A19: Drilling programme | B19: =B18*B10 | C19: The single largest line in the Australian route.
A20: Rig mobilisation / demobilisation | B20: =Rates!$D$11 | C20: One mob/demob per campaign. Fixed regardless of well count.
A21: Binary ORC surface plant | B21: =Rates!$D$15/Rates!$D$4*B7*1000 | C21: EIA 50 MW brownfield cost, converted at the Rates FX. Brownfield = wells already drilled, which is why drilling sits on its own line above.
A22: Brine gathering, heat exchange, pipework | B22: 0 | C22: RATE_MISSING. Geodynamics' AUD 182m stack had this at ~14% of non-well cost; not carried forward as a rate because the scope differs.
A23: Infrastructure subtotal (incl. stimulation, Rates D78) | B23: =SUM(B19:B22)+Rates!$D$78
A25: BLOCK 3 — COMPUTE (the hall and the silicon) | F25: AUD
A26: Data centre shell and core | B26: =Rates!$D$21/Rates!$D$4*Control!$B$12 | C26: Per MW of critical IT load.
A27: Liquid cooling premium | B27: =IF(Control!$B$8="LIQUID",Rates!$D$22/Rates!$D$4*Control!$B$12,0) | C27: GB200-class density requires liquid. AIR is modelled only for contrast.
A28: Remote-site loading | B28: =IF(Control!$B$9="ON",(B26+B27)*(Rates!$D$24-1),0) | C28: Innamincka is ~820 km straight-line from Adelaide (Rates km_innamincka_adelaide); road distance is longer. Prefab assumed.
A29: Long-haul fibre / connectivity | B29: 0 | C29: RATE_MISSING. No public per-km figure for a Moomba-Adelaide route was located. Carrier availability is itself an open question, not just a price.
A30: IT fit-out incl. GPUs (BAREMETAL only) | B30: =IF(Control!$B$5="BAREMETAL",Rates!$D$28/Rates!$D$4*Control!$B$12,0) | C30: JLL's US$25m/MW covers GPUs, networking AND racks in one figure — so there is no separate GPU line to add. In COLO and ANCHOR the TENANT pays this, not Archegon. This single toggle decides what kind of company Archegon is: landlord or owner-operator. VCs price those as different companies.
A31: Compute subtotal | B31: =SUM(B26:B30)
A32: cross-check: racks x rack price (NOT added) | B32: =ROUNDDOWN(Control!$B$12*1000/Rates!$D$27,0)*Rates!$D$26/Rates!$D$4 | C32: v3: racks ROUNDED DOWN (power-limited hall: 5,000 kW / 130 kW = 38 complete racks). Bottom-up cross-check, NOT added.
A34: BLOCK 4 — LEGALS | F34: AUD
A35: Native title agreement | B35: =Rates!$D$38 | C35: RATE_MISSING. Determination SCD2015/003 already exists and names the RNTBC, so the counterparty is known. The open question is whether a geothermal licence can enjoin the existing petroleum conjunctive ILUA (SI2006/008).
A36: Aboriginal heritage clearance | B36: =Rates!$D$39 | C36: RATE_MISSING. A SEPARATE statute from native title (Aboriginal Heritage Act 1988 SA). Routinely collapsed into native title in pitch material; it is not.
A37: Tenement, environmental and EPBC | B37: =Rates!$D$40 | C37: RATE_MISSING. Energy Resources Act 2000 (SA) licence plus any EPBC referral.
A38: Legals subtotal | B38: =SUM(B35:B37) | C38: ENTIRE BLOCK IS RATE_MISSING. No published cost exists for concluding an SA native title agreement (legals-08). Requires a counsel quote before use.
A40: AUSTRALIAN ROUTE — TOTAL CAPEX | F40: AUD
A41: Sum of the four blocks | B41: =B15+B23+B31+B38 | C41: Land + infrastructure + compute + legals.
A42: Contingency | B42: =B41*Control!$B$13 | C42: First-of-a-kind in this basin. Habanero's own history argues for more, not less.
A43: TOTAL AU CAPEX | B43: =B41+B42
A44: Implied AUD/kW — GENERATION only | B44: =(B15+B23)*(1+Control!$B$13)/(B7*1000) | C44: Wells and plant over gross generation capacity. THIS is the line to compare against Habanero actual AUD 23,600/kW. The comparator excludes the data centre, so this figure must too.
A45: Implied AUD/kW — ALL-IN over critical IT | B45: =B43/(Control!$B$12*1000) | C45: Everything, over the MW of compute actually sold. A data centre metric, not a geothermal one — do not compare it to a per-kW generation benchmark.
A47: What this total does NOT include
A48: • Every RATE_MISSING line above — land, fibre, brine gathering and the whole legals block.
A49: • Parasitic load: the well ratings are NET by definition (Definitions). If a producer only delivers its rating GROSS, Flow-Basis shows the extra producers needed.
A50: • Any allowance for a dry or under-performing well. EGS fails continuously, not discretely.
A51: • Transmission. The model assumes behind-the-meter co-location — that is the entire thesis.

Sheet NZ-Route
A1: ARCHEGON CAPITAL · NEW ZEALAND — Taupo Volcanic Zone. Contract the power, build the hall. No drilling risk.
A3: New Zealand is a contracting play. The TVZ is conventional hydrothermal and already in commercial production — Contact, Mercury, Eastland and Top Energy own it. Archegon does not drill here; it contracts.
A5: RESOURCE — CONTRACTED, NOT DRILLED
A6: Gross generation required (MW) | B6: =Control!$B$12*Control!$B$17/Control!$B$16 | C6: Same grossing-up as Australia — PUE then capacity factor. The difference is who owns the wells.
A7: Wells drilled by Archegon | B7: 0 | C7: Zero. This is the whole point of the NZ route: the drilling risk sits with an incumbent who has already taken it.
A8: Reference NZ greenfield cost NOT incurred (NZD) | B8: =Rates!$D$17*B6*1000 | C8: Shown to size what contracting avoids — it is NOT a cost in this route. It is the capital an incumbent already sank.
A10: BLOCK 1 — LAND | F10: NZD
A11: Site lease / land acquisition | B11: 0 | C11: RATE_MISSING. TVZ land is frequently Maori freehold or under iwi/hapu interest. The counterparty on every TVZ project is an iwi or hapu entity.
A12: Site preparation | B12: 0 | C12: RATE_MISSING.
A13: Land subtotal | B13: =SUM(B11:B12)
A15: BLOCK 2 — INFRASTRUCTURE (connection, not drilling) | F15: NZD
A16: Behind-the-meter connection and substation | B16: 0 | C16: RATE_MISSING. A data centre is a LOAD connection — expressly handled outside Transpower's generation Connection Management Framework, so the CMF fee is NOT the entry ticket here.
A17: Fibre and connectivity | B17: 0 | C17: RATE_MISSING. Materially easier than Cooper Basin — TVZ sites sit near existing routes — but no figure is carried.
A18: Infrastructure subtotal | B18: =SUM(B16:B17)
A20: BLOCK 3 — COMPUTE (the hall and what goes in it) | F20: NZD
A21: Data centre shell and power train | B21: =Rates!$D$21*Control!$B$12*(Rates!$D$5/Rates!$D$4) | C21: USD/MW benchmark converted at Rates FX. No remote loading: TVZ sites are 1-3 hours from Auckland/Tauranga, not ~820 km straight-line (Rates) from Adelaide.
A22: Liquid cooling premium | B22: =IF(Control!$B$8="LIQUID",Rates!$D$22*Control!$B$12*(Rates!$D$5/Rates!$D$4),0) | C22: Toggled on Control!Cooling. INDICATIVE rate.
A23: Fibre and connectivity | B23: 0 | C23: RATE_MISSING.
A24: IT fit-out incl. GPUs (BAREMETAL only) | B24: =IF(Control!$B$5="BAREMETAL",Rates!$D$28*Control!$B$12*(Rates!$D$5/Rates!$D$4),0) | C24: One figure covering GPUs, networking and racks - there is no separate GPU line to add. Zero under COLO and ANCHOR: the tenant brings the silicon.
A25: Compute subtotal | B25: =SUM(B21:B24)
A26: cross-check: racks x rack price (NOT added) | B26: =ROUNDDOWN(Control!$B$12*1000/Rates!$D$27,0)*Rates!$D$26*(Rates!$D$5/Rates!$D$4) | C26: Bottom-up from GB200 rack economics. Outside the subtotal on purpose.
A28: BLOCK 4 — LEGALS AND CONSENTING | F28: NZD
A29: Resource consents (RMA) and planning | B29: =Rates!$D$41 | C29: RATE_MISSING (v3: now LINKED to Rates!D41, so pricing NZ consenting on Rates flows through).
A30: Iwi / hapu engagement and agreements | B30: 0 | C30: RATE_MISSING. Not a box to tick. On TVZ land the iwi entity is frequently the landowner, the Treaty partner and a potential equity party at once.
A31: Overseas Investment Act screening | B31: 0 | C31: RATE_MISSING. An offshore-funded acquirer of sensitive land triggers OIO consent; source page for decision timelines returns 404 (nz-route-44).
A32: Power purchase agreement negotiation | B32: 0 | C32: RATE_MISSING. This is the NZ route's real gate - a firm, long-dated, behind-the-meter PPA with an incumbent generator.
A33: Legals subtotal | B33: =SUM(B29:B32) | C33: ENTIRE BLOCK IS RATE_MISSING. Requires NZ counsel quotes before use.
A35: NEW ZEALAND ROUTE — TOTAL CAPEX | F35: NZD
A36: Sum of the four blocks | B36: =B13+B18+B25+B33 | C36: Land + infrastructure + compute + legals. Note what is absent: wells.
A37: Contingency | B37: =B36*Control!$B$13 | C37: Lower subsurface risk than AU, but the same first-of-a-kind build risk.
A38: TOTAL NZ CAPEX | B38: =B36+B37
A39: Implied NZD/kW — ALL-IN over critical IT | B39: =B38/(Control!$B$12*1000) | C39: There is no generation-only figure on this route because Archegon builds no generation. Do NOT compare this to a per-kW geothermal benchmark — it is a data centre number.
A41: CONTRACTED POWER — the cost that replaces the wells | F41: NZD/yr
A42: Annual energy consumed (MWh) | B42: =Control!$B$12*Control!$B$17*8760 | C42: Total facility load (critical IT x PUE) running continuously. The hall draws 8,760 hours a year regardless of generator availability, so the capacity factor does NOT belong in this line — it sizes plant, not consumption.
A43: Indicative annual power cost | B43: =B42*Rates!$D$35 | C43: At the NZ wholesale benchmark. A real behind-the-meter geothermal PPA is negotiated, not screen-priced - this line sizes the opex, it does not quote it.
A45: Why the NZ route is the faster PoC, and why it is also the weaker moat
A46: • FASTER: the resource already exists and is in commercial production. No drilling risk, no dry hole, no stimulation programme, no 6-month native title minimum.
A47: • WEAKER: what Archegon owns is a contract, not a reservoir. The incumbent can decline to renew, or price the renewal against the tenant's switching cost.
A48: • The AU route is the reverse trade: worse schedule, harder capital, an owned asset.

Sheet Compute-Revenue
A1: ARCHEGON CAPITAL · COMPUTE AND REVENUE — three ways to sell the same megawatt. Reported in AUD.
A3: v3: Slide 11's "energy is ~7% of AI-DC TCO" describes a GPU OWNER. Under COLO Archegon owns the shell and the power system, and the power system costs about as much as the hall earns (Power-Economics). The premium for firm, carbon-free power is UNPROVEN until tenant LOIs price it.
A5: SOLD CAPACITY
A6: Critical IT sold (kW) | B6: =Control!$B$12*1000 | C6: Assumes the PoC sells out. A ramp belongs in a later version.
A7: Energy delivered (MWh/yr) | B7: =Control!$B$12*Control!$B$17*8760 | C7: Total facility energy: critical IT x PUE, running continuously. The capacity factor sizes generation, not consumption, so it is deliberately absent here.
A9: MODEL A — COLOCATION (sell space and power per kW/month) | F9: AUD/yr
A10: Colocation revenue | B10: =B6*Rates!$D$29*12*(1/Rates!$D$4) | C10: AU market rate. Sydney trades higher; the Sydney rate is on Rates as the upper reference. VERIFIED-ESTIMATE.
A12: MODEL B — ANCHOR LEASE (one take-or-pay tenant) | F12: AUD/yr
A13: Anchor lease revenue | B13: =Rates!$D$31*Control!$B$12*(1/Rates!$D$4) | C13: DERIVED per-MW lease. The alternative benchmark on Rates is ~23% lower — run both before quoting either.
A15: MODEL C — BARE METAL (own the GPUs, sell compute) | F15: AUD/yr
A16: Bare-metal compute revenue | B16: 0 | C16: RATE_MISSING BY DELIBERATE CHOICE. The GPU-hour rates that would drive this line were demoted to CONTESTED — an independent verifier could not locate them in any cited source. Quoting a GPU-hour price here would be inventing the single number a VC checks first.
A17: Power-only fallback, AU route (islanded: no grid connection) | B17: 0 | C17: v3 FIX: v2 linked Rates!D33, which equals the colo rate, so the "fallback" was colo revenue relabelled. With no grid connection an unsold AU megawatt earns nothing. Real fallback options (grid export, curtailable flexible load) are priced on Power-Economics; the connection cost is RATE_MISSING.
A18: Illustrative grid-export value IF a connection existed (SA wholesale, not contracted) | B18: ='Power-Economics'!$B$33 | C18: Wholesale x net average MWh. Connection capex RATE_MISSING. Not in contribution.
A19: SELECTED REVENUE (follows Control!Compute model) | F19: AUD/yr
A20: Revenue on the selected model | B20: =IF(Control!$B$5="COLO",B10,IF(Control!$B$5="ANCHOR",B13,B16))*Control!$B$18 | C20: Per-site revenue multiplied by Control!Sites funded, so BOTH sells two sites' worth. BAREMETAL resolves to zero on purpose — see Model C.
A22: OPERATING COST — differs by route, because ownership differs | F22: AUD/yr
A23: AU: geothermal plant fixed O&M | B23: =Rates!$D$16*'AU-Route'!$B$7*1000*(1/Rates!$D$4) | C23: Archegon OWNS the plant on the AU route, so it carries the O&M. Applied to GROSS generation capacity, not critical IT.
A24: NZ: contracted power purchase | B24: ='NZ-Route'!$B$42*Rates!$D$35*(1/Rates!$D$5) | C24: Archegon BUYS power on the NZ route, so it carries an energy bill instead of an O&M bill. Screen price, not a negotiated PPA.
A25: AU: make-up / well replacement provision | B25: =IF(Control!$B$4="NZ",0,Rates!$D$42) | C25: RATE_MISSING, ships at zero. The plant O&M rate above EXCLUDES well replacement, so without this line the AU route silently assumes the reservoir never declines. NZ's opex rate already includes make-up drilling — that asymmetry is why this line exists.
A26: Both routes: data centre non-energy opex | B26: =Rates!$D$43*Control!$B$12*Control!$B$18*(1/Rates!$D$4) | C26: RATE_MISSING, ships at zero. Maintenance, insurance, security, connectivity and rates. The evidence base carries data centre capex benchmarks but no opex benchmark, so contribution below is overstated by exactly this amount.
A27: Team and overhead (per site funded) | B27: =Control!$B$15*12*Control!$B$18 | C27: v3: multiplied by sites funded. BOTH no longer assumes one team runs two routes; shared overhead needs a resource-loaded plan first.
A28: Opex on the selected route | B28: =IF(Control!$B$4="NZ",B24,IF(Control!$B$4="BOTH",B23+B24,B23))+B25+B26+B27 | C28: BOTH carries both routes' energy/O&M — running two routes costs two routes. Two of the five lines above are RATE_MISSING, so this is a FLOOR on opex, not an estimate.
A30: CONTRIBUTION | F30: AUD/yr
A31: Revenue less opex | B31: =B20-B28 | C31: Pre-financing, pre-tax, pre-depreciation. This is NOT EBITDA and NOT a return — it is the annual cash the PoC throws off once built and full.
A33: What this tab deliberately does not do
A34: • No ramp. Revenue is shown at full occupancy from year one — a PoC will not do that.
A35: • No escalation, no discounting, no terminal value. There is no IRR in this workbook because an IRR built on RATE_MISSING blocks would be fiction with a decimal point.
A36: • Parasitic load is not netted off saleable capacity. PUE is now applied — that covers cooling and facility overhead — but the generator's own consumption (EIA 13.8% vs Fervo actual ~33%) is a separate, unresolved gross-up that moves the AU well count.
A37: • Opex is a FLOOR. Two of the five cost lines above are RATE_MISSING and ship at zero: AU well replacement and data centre non-energy opex. Contribution is overstated by whatever those two turn out to be.

Sheet Raise
A1: ARCHEGON CAPITAL · THE RAISE — derived from the cost stack, not chosen and back-filled
A3: Nothing on this tab is a round number picked first. The ask is the sum of the four money blocks on the selected route, plus the runway needed to reach them. Change a Control switch and the ask moves.
A5: CAPEX ON THE SELECTED ROUTE | F5: AUD
A6: Australian route capex | B6: ='AU-Route'!$B$43 | C6: From AU-Route. Buy the land, drill the wells, build the plant, build the hall.
A7: New Zealand route capex (converted to AUD) | B7: ='NZ-Route'!$B$38*(1/Rates!$D$5) | C7: From NZ-Route at the Rates cross-rate. No drilling in this figure.
A8: Capex to fund | B8: =IF(Control!$B$4="NZ",B7,IF(Control!$B$4="BOTH",B6+B7,B6)) | C8: BOTH funds two routes in parallel — the optionality is real and so is the bill.
A10: PRE-REVENUE OPERATING RUNWAY | F10: AUD
A11: Team and overhead through the runway | B11: =Control!$B$15*Control!$B$14*Control!$B$18 | C11: v3: x sites funded (BOTH = two teams). ASSUMPTION rate.
A13: THE ASK | F13: AUD
A14: TOTAL RAISE (derived) | B14: =B8+B11 | C14: Capex on the selected route plus the runway to deliver it.
A15: Total raise (USD) | B15: =B14*Rates!$D$4 | C15: At the Rates FX. For a USD-denominated conversation.
A17: USE OF FUNDS (share of the derived ask) | F17: %
A18: Capex share of the ask | B18: =B8/B14 | C18: How much of the raise becomes an asset.
A19: Runway share of the ask | B19: =B11/B14 | C19: How much of the raise is burn. A high number here is a red flag to a VC.
A21: WHAT THE ASK BUYS
A22: Critical IT delivered (MW) | B22: =Control!$B$12*Control!$B$18 | C22: From Control, multiplied by sites funded. BOTH delivers two PoC sites, so the denominator below doubles with the numerator.
A23: Raise per kW of critical IT | B23: =B14/(B22*1000) | C23: The number a data centre investor will compute in their head. Compare against the shell and fit-out benchmarks on Rates. Critical IT sold — the site generates PUE times this.
A24: Years of contribution to equal the ask (undiscounted) | B24: =IF('Compute-Revenue'!$B$31<=0,"n/a — contribution is not positive",B14/'Compute-Revenue'!$B$31) | C24: NOT an IRR and NOT a payback period — no discounting, no ramp, no terminal value. A magnitude check only.
A26: What this ask does NOT cover — say this before a VC finds it
A27: • Every RATE_MISSING line. Land, fibre, brine gathering, the entire AU legals block and the entire NZ legals block ship at zero in capex — and AU well replacement and data centre operating cost ship at zero in opex. The ask is a FLOOR, not an estimate.
A28: • No dry-hole or under-performing-well allowance on the AU route. EGS fails continuously — the failure mode is a reservoir that produces 60% of plan, not a hole with no heat.
A29: • No second tranche. A PoC that works needs production capital that this ask does not raise.
A30: • No allowance for the 6-month statutory minimum on the AU native title path (legals-01) running long. Schedule risk is not costed here.

Sheet Sensitivity
A1: ARCHEGON CAPITAL · SENSITIVITY — the three source conflicts that move the answer most
A3: These are not made-up scenarios. Each row is a live disagreement between sources in facts/ — the model carries both ends rather than picking one and hiding the other.
A5: Driver | B5: Low | C5: Base | D5: High | E5: Actual | F5: Why the sources disagree | G5: Control switch
A6: MWe per production well | B6: =Rates!$D$13 | C6: =Rates!$D$12 | D6: =Rates!$D$14 | E6: n/a | F6: GeoExpro reads ~2 MWe from operating EGS. Fervo claims 10-16. A 6.5x spread on the single input that sets how many wells you drill. | G6: Well productivity
A7: Cost per well (AUD) | B7: =Rates!$D$7 | C7: =Rates!$D$6 | D7: =Rates!$D$8 | E7: =Rates!$D$9 | F7: LOW/BASE/HIGH are all Geodynamics engineered forward estimates — best case, campaign average and single-well. ACTUAL is Habanero 4 as drilled, 4.5x the first well. The learning curve ran backwards. | G7: Well cost case
A9: AU WELL PROGRAMME AT EACH CORNER (live) | G9: Drilling capex only
A10: Productivity \ well cost | B10: LOW cost | C10: BASE cost | D10: HIGH cost | E10: ACTUAL (Habanero 4)
A11: LOW (2 MWe) | B11: =('AU-Route'!$B$10/'AU-Route'!$B$8)*ROUNDUP((Control!$B$12*Control!$B$17/Control!$B$16)/Rates!$D$13,0)*B$7 | C11: =('AU-Route'!$B$10/'AU-Route'!$B$8)*ROUNDUP((Control!$B$12*Control!$B$17/Control!$B$16)/Rates!$D$13,0)*C$7 | D11: =('AU-Route'!$B$10/'AU-Route'!$B$8)*ROUNDUP((Control!$B$12*Control!$B$17/Control!$B$16)/Rates!$D$13,0)*D$7 | E11: =('AU-Route'!$B$10/'AU-Route'!$B$8)*ROUNDUP((Control!$B$12*Control!$B$17/Control!$B$16)/Rates!$D$13,0)*E$7
A12: BASE (5 MWe) | B12: =('AU-Route'!$B$10/'AU-Route'!$B$8)*ROUNDUP((Control!$B$12*Control!$B$17/Control!$B$16)/Rates!$D$12,0)*B$7 | C12: =('AU-Route'!$B$10/'AU-Route'!$B$8)*ROUNDUP((Control!$B$12*Control!$B$17/Control!$B$16)/Rates!$D$12,0)*C$7 | D12: =('AU-Route'!$B$10/'AU-Route'!$B$8)*ROUNDUP((Control!$B$12*Control!$B$17/Control!$B$16)/Rates!$D$12,0)*D$7 | E12: =('AU-Route'!$B$10/'AU-Route'!$B$8)*ROUNDUP((Control!$B$12*Control!$B$17/Control!$B$16)/Rates!$D$12,0)*E$7
A13: HIGH (13 MWe) | B13: =('AU-Route'!$B$10/'AU-Route'!$B$8)*ROUNDUP((Control!$B$12*Control!$B$17/Control!$B$16)/Rates!$D$14,0)*B$7 | C13: =('AU-Route'!$B$10/'AU-Route'!$B$8)*ROUNDUP((Control!$B$12*Control!$B$17/Control!$B$16)/Rates!$D$14,0)*C$7 | D13: =('AU-Route'!$B$10/'AU-Route'!$B$8)*ROUNDUP((Control!$B$12*Control!$B$17/Control!$B$16)/Rates!$D$14,0)*D$7 | E13: =('AU-Route'!$B$10/'AU-Route'!$B$8)*ROUNDUP((Control!$B$12*Control!$B$17/Control!$B$16)/Rates!$D$14,0)*E$7
A15: Spread, cheapest corner to dearest | B15: =MAX(B11:E13)/MIN(B11:E13) | C15: The ratio a VC should be shown first. Drilling alone, before a single server is bought. Now spans all four cost cases including Habanero 4 as drilled.
A17: CONFLICTS THE MODEL CANNOT RESOLVE
A18: Parasitic load: 13.8% (EIA, conventional) vs ~29% (EGS stress, GeoExpro-derived: 2.5 MW pumping / 8.7 MW gross)
A19: v3: well ratings are NET by definition (Definitions), so parasitic is inside the rating. Flow-Basis shows what that requires in kg/s, and how many producers a gross-only rating would need.
A21: Capex per kW (US$): Habanero 16,808 at model FX (23,600 x 0.7122) vs Fervo 7,000 (overnight, first project) -> 5,500 (Phase II all-in, expected) -> 3,000 (target)
A22: v3: Fervo US$7,000/kW is in the S-1/A filed 4 May 2026 as an OVERNIGHT cost for the first Cape Station project: CONTESTED cleared, mis-date (31 Dec 2025) corrected. The three Fervo figures are on different bases and are shown as separate points, not a curve. At model FX Habanero is 2.4x Fervo's first-project figure. The model uses none of them as an input.
A24: Every RATE_MISSING block
A25: Land, fibre, brine gathering, AU legals, NZ legals. Four counsel quotes and two engineering quotes would close most of this. None exists yet.
A27: Plant scale penalty (sensitivity, ASSUMPTION 0.6 exponent from the 50 MW EIA reference)
A28: Per-kW multiplier at net nameplate | B28: =(50/'AU-Route'!$B$7)^(1-Rates!$D$81)
A29: AU raise with scale penalty | B29: =Raise!$B$14+'AU-Route'!$B$21*(B28-1)*(1+Control!$B$13)
A30: AU raise with scale penalty AND remote loading on the plant | B30: =Raise!$B$14+'AU-Route'!$B$21*(B28*Rates!$D$24-1)*(1+Control!$B$13)
A31: AU raise at HIGH (single-well, first-of-a-kind) well cost | B31: =Raise!$B$14+'AU-Route'!$B$10*(Rates!$D$8-'AU-Route'!$B$18)*(1+Control!$B$13)

Sheet Traceability
A1: ARCHEGON CAPITAL · TRACEABILITY — every rate in this workbook, and the finding it came from
A3: No figure in this workbook was typed from memory. Each row below names the finding id in facts/ that a rate came from, the status that finding carries, and the claim as recorded. A rate whose finding is missing stops the build.
A5: Rate key | B5: Rate | C5: Value | D5: Unit | E5: Status | F5: Finding id and claim | G5: Why this rate, and what it does not cover
A6: fx_aud_usd | B6: AUD -> USD | C6: 0.7122 | D6: USD per AUD | E6: VERIFIED | F6: geothermal-capex-71 — Exchange rates for restating USD geothermal capex figures into Australian and New Zealand dollars | G6: Restates USD benchmarks into AUD. Point-in-time rate.
A7: fx_aud_nzd | B7: AUD -> NZD | C7: 1.2365 | D7: NZD per AUD | E7: VERIFIED | F7: geothermal-capex-71 — Exchange rates for restating USD geothermal capex figures into Australian and New Zealand dollars | G7: Implies 1 USD = 1.404 AUD and 1 USD = 1.736 NZD.
A8: au_well_cost_base | B8: Cooper Basin EGS well, engineered forward cost | C8: 16500000 | D8: AUD/well | E8: VERIFIED-ESTIMATE | F8: geothermal-capex-30 — Geodynamics' engineered forward cost estimate for Cooper Basin EGS wells under an optimised slim-bore design and campaign drilling - the Australian 'if we did it again' number | G8: Geodynamics optimised slim-bore 5-well campaign average.
A9: au_well_cost_low | B9: Cooper Basin well, best case with high learning | C9: 14000000 | D9: AUD/well | E9: VERIFIED-ESTIMATE | F9: geothermal-capex-30 — Geodynamics' engineered forward cost estimate for Cooper Basin EGS wells under an optimised slim-bore design and campaign drilling - the Australian 'if we did it again' number | G9: Best case in the same engineered estimate.
A10: au_well_cost_high | B10: Cooper Basin well, single-well (no campaign learning) | C10: 22700000 | D10: AUD/well | E10: VERIFIED-ESTIMATE | F10: geothermal-capex-30 — Geodynamics' engineered forward cost estimate for Cooper Basin EGS wells under an optimised slim-bore design and campaign drilling - the Australian 'if we did it again' number | G10: One-off well; the cost if no campaign is assembled.
A11: au_well_actual_h4 | B11: Habanero 4 actual drilled cost | C11: 50850000 | D11: AUD/well | E11: VERIFIED | F11: geothermal-capex-29 — Actual drilled cost and duration of every deep EGS well in the Cooper Basin, Australia (Geodynamics, Habanero/Jolokia) - the only Australian deep-EGS well cost record that exists | G11: The ANTI-learning curve: last well cost 4.5x the first.
A12: au_rig_day_rate | B12: Australian onshore rig day rate | C12: 50000 | D12: AUD/day | E12: VERIFIED | F12: geothermal-capex-31 — Australian onshore drilling rig day rate and mobilisation cost assumed in the Habanero field development plan for a 750,000 lb rated rig | G12: Habanero field development plan assumption.
A13: au_rig_mob | B13: Rig mobilisation / demobilisation | C13: 4000000 | D13: AUD | E13: VERIFIED | F13: geothermal-capex-31 — Australian onshore drilling rig day rate and mobilisation cost assumed in the Habanero field development plan for a 750,000 lb rated rig | G13: Single mob/demob for a Cooper Basin campaign.
A14: mwe_per_well_base | B14: Net MWe per production well - BASE | C14: 5 | D14: MWe | E14: DERIVED | F14: geothermal-capex-15 — Base case recommended for MWe per production well and per doublet in an Archegon financial model, reconciling company and critic sources | G14: DERIVED base case 4-6 MWe; midpoint used.
A15: mwe_per_well_low | B15: Net MWe per production well - LOW | C15: 2 | D15: MWe | E15: DERIVED | F15: geothermal-capex-15 — Base case recommended for MWe per production well and per doublet in an Archegon financial model, reconciling company and critic sources | G15: GeoExpro triplet-implied bear case.
A16: mwe_per_well_high | B16: Gross MWe per producer - HIGH | C16: 13 | D16: MWe | E16: DERIVED | F16: geothermal-capex-15 — Base case recommended for MWe per production well and per doublet in an Archegon financial model, reconciling company and critic sources | G16: Fervo claim 10-16 MWe; midpoint. Unproven at fleet scale.
A17: plant_usd_per_kw | B17: 50 MW binary ORC plant, brownfield (wells already drilled) | C17: 3963 | D17: USD/kW | E17: VERIFIED | F17: geothermal-capex-16 — All-in capital cost of a 50 MW net binary-cycle (ORC) geothermal power plant on a BROWNFIELD site where production and injection wells are already drilled - i.e. surface plant plus gathering system only, no drilling | G17: EIA 2023 USD, USD 198.1m for 50 MW net.
... A45: dc_opex_usd_mw_yr | B45: Data centre non-energy opex (maintenance, insurance, security, connectivity, rates) | C45: 0 | D45: USD/MW/yr | E45: RATE_MISSING | F45: NO FINDING — gap raised in model review. The evidence base carries data centre capex benchmarks only. | G45: RATE_MISSING. Applies to both routes. Ships at zero, so contribution is overstated by exactly this amount.
A47: Status tally
A48: DERIVED | B48: =COUNTIF($E$6:$E$45,$A48)
A49: INDICATIVE | B49: =COUNTIF($E$6:$E$45,$A49)
A50: RATE_MISSING | B50: =COUNTIF($E$6:$E$45,$A50)
A51: VERIFIED | B51: =COUNTIF($E$6:$E$45,$A51)
A52: VERIFIED-ESTIMATE | B52: =COUNTIF($E$6:$E$45,$A52)

Sheet Deck-Check
A1: ARCHEGON CAPITAL · DECK CHECK: every model-derived figure on the master deck, against the live model
A3: Deck v1 (23 Sep 2026) was built from the model with PUE = 1.00. Setting Control!B17 to 1.00 and recalculating reproduces every v1 figure exactly (column E). Deck v2 shows the model at PUE 1.25 (column D). Column G turns FALSE if a Control change moves the model away from what deck v2 displays.
A5: Slide | B5: Figure | C5: Deck v1 shows | D5: Deck v2 shows | E5: Model at PUE 1.00 (recalculated 10 Oct 2026) | F5: Live model value | G5: Deck v2 = live? (to displayed precision) | H5: Model cell
A6: 12 | B6: Net nameplate MW (plant fence) | C6: 5.56 | D6: 6.94 | E6: 5.5556 | F6: ='AU-Route'!B7 | G6: =ROUND(F6,2)=ROUND(D6,2) | H6: AU-Route!B7
A7: 12 | B7: Total wells | C7: 4 | D7: 4 | E7: 4 | F7: ='AU-Route'!B10 | G7: =ROUND(F7,0)=ROUND(D7,0) | H7: AU-Route!B10
A8: 12 | B8: AU infra (wells+mob+plant), A$m | C8: 100.9 | D8: 108.6 | E8: 100.9136 | F8: ='AU-Route'!B23/1000000 | G8: =ROUND(F8,1)=ROUND(D8,1) | H8: AU-Route!B23
A9: 12 | B9: AU compute, A$m | C9: 132.3 | D9: 132.3 | E9: 132.3364 | F9: ='AU-Route'!B31/1000000 | G9: =ROUND(F9,1)=ROUND(D9,1) | H9: AU-Route!B31
A10: 12 | B10: AU contingency, A$m (chart) | C10: 58.3 | D10: 60.2 | E10: 58.3125 | F10: ='AU-Route'!B42/1000000 | G10: =ROUND(F10,1)=ROUND(D10,1) | H10: AU-Route!B42
A11: 12 | B11: AU floor (total capex), A$m | C11: 291.6 | D11: 301.2 | E11: 291.5625 | F11: ='AU-Route'!B43/1000000 | G11: =ROUND(F11,1)=ROUND(D11,1) | H11: AU-Route!B43
A12: 12 | B12: NZ floor, A$m | C12: 127.3 | D12: 127.2 | E12: 127.2466 | F12: =Raise!B7/1000000 | G12: =ROUND(F12,1)=ROUND(D12,1) | H12: Raise!B7
A13: 12 | B13: NZ stack, NZ$m | C13: 157.3 | D13: 157.3 | E13: 157.3404 | F13: ='NZ-Route'!B38/1000000 | G13: =ROUND(F13,1)=ROUND(D13,1) | H13: NZ-Route!B38
A14: 12 | B14: NZ compute (chart), A$m | C14: 101.8 | D14: 101.8 | E14: 101.7976 | F14: ='NZ-Route'!B25/Rates!D5/1000000 | G14: =ROUND(F14,1)=ROUND(D14,1) | H14: NZ-Route!B25
A15: 12 | B15: NZ contingency (chart), A$m | C15: 25.5 | D15: 25.4 | E15: 25.4493 | F15: ='NZ-Route'!B37/Rates!D5/1000000 | G15: =ROUND(F15,1)=ROUND(D15,1) | H15: NZ-Route!B37
A16: 13 | B16: AU route capex, A$m | C16: 291.6 | D16: 301.2 | E16: 291.5625 | F16: =Raise!B8/1000000 | G16: =ROUND(F16,1)=ROUND(D16,1) | H16: Raise!B8
A17: 13 | B17: Runway, A$m | C17: 6 | D17: 6 | E17: 6 | F17: =Raise!B11/1000000 | G17: =ROUND(F17,1)=ROUND(D17,1) | H17: Raise!B11
A18: 13 | B18: Derived raise, A$m | C18: 297.6 | D18: 307.2 | E18: 297.5625 | F18: =Raise!B14/1000000 | G18: =ROUND(F18,1)=ROUND(D18,1) | H18: Raise!B14
A19: 13 | B19: Derived raise, US$m | C19: 211.9 | D19: 218.8 | E19: 211.924 | F19: =Raise!B15/1000000 | G19: =ROUND(F19,1)=ROUND(D19,1) | H19: Raise!B15
A20: 14 | B20: COLO revenue, A$m/yr | C20: 14.5 | D20: 14.5 | E20: 14.5324 | F20: ='Compute-Revenue'!B10/1000000 | G20: =ROUND(F20,1)=ROUND(D20,1) | H20: Compute-Revenue!B10
A21: 14 | B21: ANCHOR revenue, A$m/yr | C21: 16.6 | D21: 16.6 | E21: 16.6386 | F21: ='Compute-Revenue'!B13/1000000 | G21: =ROUND(F21,1)=ROUND(D21,1) | H21: Compute-Revenue!B13
A22: 14 | B22: Opex (plant O&M + team), A$m/yr | C22: 4.2 | D22: 4.5 | E22: 4.1748 | F22: ='Compute-Revenue'!B28/1000000 | G22: =ROUND(F22,1)=ROUND(D22,1) | H22: Compute-Revenue!B28
A23: 14 | B23: COLO contribution, A$m/yr | C23: 10.4 | D23: 10.1 | E23: 10.3577 | F23: ='Compute-Revenue'!B31/1000000 | G23: =ROUND(F23,1)=ROUND(D23,1) | H23: Compute-Revenue!B31
A25: NZ: v1 showed the NZ floor as A$127.3m and NZ contingency as A$25.5m. The model gives A$127.25m and A$25.45m, which round to A$127.2m and A$25.4m. v1 was a rounding error that does not depend on PUE, and v2 corrects it. Rounding note: slide 12 chart labels sum to A$301.1m (108.6 + 132.3 + 60.2) against a A$301.2m total. Each label is the model value rounded on its own. v1 had the same effect: its chart total read A$291.5m against a A$291.6m header. v2 stores unrounded values, so the chart total now reads A$301.2m.
A26: Slide 14: A$14.5m − A$4.5m appears to give A$10.0m, but the model gives A$10.06m (14.532 − 4.468). The displayed values are each rounded to 0.1.
A30: v3: deck slide numbers follow archegon-deck-v3.pptx; new slides 17-22 draw on Definitions, Flow-Basis, Power-Economics, Route-Compare, Firm-Power, Gated-Plan.

Sheet Flow-Basis
A1: ARCHEGON · FLOW BASIS: what flow per producer does 5 MWe NET need, and what has the Cooper Basin delivered?
A3: Method (ASSUMPTION, Archegon screening): net MW = flow x specific exergy of hot water x utilisation x (1 - parasitic). Specific exergy e = cp[(T-T0) - (T0+273.15) ln((T+273.15)/(T0+273.15))]. This is a screening calculation, NOT a reservoir forecast. It does not replace a reservoir engineer's sustainable rate, temperature and injectivity case, which the founder must supply (status: NEEDS DATA).
A5: Inputs (linked to Rates)
A6: cp (kJ/kg.K) | B6: =Rates!$D$66
A7: Dead state T0 (degC) | B7: =Rates!$D$67
A8: Utilisation low | B8: =Rates!$D$68
A9: Utilisation high | B9: =Rates!$D$69
A10: Parasitic low (EIA) | B10: =Rates!$D$62
A11: Parasitic high (EGS stress, GeoExpro-derived) | B11: =Rates!$D$65
A12: Target NET MWe per producer (scenario) | B12: ='AU-Route'!$B$6
A14: A. Flow needed per producer for the target NET MWe
A15: Production temperature (degC) | B15: Specific exergy (kJ/kg) | C15: Flow needed, optimistic (kg/s): util high, parasitic low | D15: Flow needed, conservative (kg/s): util low, parasitic high | E15: Reference
A16: =Rates!$D$58 | B16: =$B$6*((A16)-$B$7-($B$7+273.15)*LN(((A16)+273.15)/($B$7+273.15))) | C16: =$B$12*1000/(B16*$B$9*(1-$B$10)) | D16: =$B$12*1000/(B16*$B$8*(1-$B$11)) | E16: Fervo Project Red
A17: 200 | B17: =$B$6*((A17)-$B$7-($B$7+273.15)*LN(((A17)+273.15)/($B$7+273.15))) | C17: =$B$12*1000/(B17*$B$9*(1-$B$10)) | D17: =$B$12*1000/(B17*$B$8*(1-$B$11)) | E17: Habanero earlier trial (~200 degC)
A18: =Rates!$D$55 | B18: =$B$6*((A18)-$B$7-($B$7+273.15)*LN(((A18)+273.15)/($B$7+273.15))) | C18: =$B$12*1000/(B18*$B$9*(1-$B$10)) | D18: =$B$12*1000/(B18*$B$8*(1-$B$11)) | E18: Habanero 4 wellhead, 2013
A19: 220 | B19: =$B$6*((A19)-$B$7-($B$7+273.15)*LN(((A19)+273.15)/($B$7+273.15))) | C19: =$B$12*1000/(B19*$B$9*(1-$B$10)) | D19: =$B$12*1000/(B19*$B$8*(1-$B$11))
A20: 240 | B20: =$B$6*((A20)-$B$7-($B$7+273.15)*LN(((A20)+273.15)/($B$7+273.15))) | C20: =$B$12*1000/(B20*$B$9*(1-$B$10)) | D20: =$B$12*1000/(B20*$B$8*(1-$B$11))
A22: B. What measured flows would deliver (NET MWe per producer, at Habanero 215 degC)
A23: Flow (kg/s) | B23: Source | C23: NET MWe, optimistic | D23: NET MWe, conservative | E23: vs target (conservative)
A24: =Rates!$D$53 | B24: Habanero best sustained closed loop (INDICATIVE) | C24: =A24*$B$18*$B$9*(1-$B$10)/1000 | D24: =A24*$B$18*$B$8*(1-$B$11)/1000 | E24: =D24/$B$12
A25: =Rates!$D$54 | B25: Habanero 4 open flow (INDICATIVE) | C25: =A25*$B$18*$B$9*(1-$B$10)/1000 | D25: =A25*$B$18*$B$8*(1-$B$11)/1000 | E25: =D25/$B$12
A26: =Rates!$D$59 | B26: Fervo Red sustained average (INDICATIVE) | C26: =A26*$B$18*$B$9*(1-$B$10)/1000 | D26: =A26*$B$18*$B$8*(1-$B$11)/1000 | E26: =D26/$B$12
A27: =Rates!$D$56 | B27: Fervo Red peak (VERIFIED) | C27: =A27*$B$18*$B$9*(1-$B$10)/1000 | D27: =A27*$B$18*$B$8*(1-$B$11)/1000 | E27: =D27/$B$12
A28: 107 | B28: Fervo Cape 30-day max, Sep 2024 | C28: =A28*$B$18*$B$9*(1-$B$10)/1000 | D28: =A28*$B$18*$B$8*(1-$B$11)/1000 | E28: =D28/$B$12
A30: C. Calibration and slide 5 reconciliation
A31: Project Red implied utilisation (3.5 MWe from 63 kg/s at 169 degC, treated as gross) | B31: =Rates!$D$57*1000/(Rates!$D$56*B16) | C31: ~50% = top of the range: consistent with a calculated, not metered, figure.
A32: Fervo sustained: NET / GROSS | B32: =Rates!$D$61/Rates!$D$60 | C32: 1.4 / 2.1: parasitic ~33% of gross.
A33: Slide 5 step 1: Project Red PEAK (MWe) | B33: =Rates!$D$57 | C33: Peak
A34: Slide 5 step 2: sustained GROSS (MW) | B34: =Rates!$D$60 | C34: Sustained average over 614+ days
A35: Slide 5 step 3: parasitic (MW) | B35: =Rates!$D$60-Rates!$D$61
A36: Slide 5 step 4: sustained NET (MW) | B36: =Rates!$D$61 | C36: v2 implied 3.5 x (1-33%) = 1.4, which is wrong (= 2.35). 1.4 is 2.1 gross less 0.7 parasitic.
A37: Linear scale-up: flow for 5 MWe NET at Fervo sustained ratio (kg/s) | B37: =Rates!$D$59*$B$12/Rates!$D$61 | C37: Illustration (~129 kg/s). Not linear in reality.
A39: D. Sensitivity: MWe per producer -> wells and AU raise (other inputs at Control settings)
A40: NET MWe per producer | B40: Basis | C40: Producers (N+0) | D40: Total wells (doublets) | E40: AU raise, A$ (doublets) | F40: Total wells (triplets: 2 injectors per producer) | G40: AU raise, A$ (triplets) | H40: Contribution / raise (doublets)
A41: =Rates!$D$61 | B41: Fervo sustained net (slide 5 underwriting figure) | C41: =ROUNDUP(ROUND('AU-Route'!$B$7/A41,6),0) | D41: =2*C41 | E41: =(D41*'AU-Route'!$B$18+('AU-Route'!$B$20+'AU-Route'!$B$21+'AU-Route'!$B$22+'AU-Route'!$B$15+'AU-Route'!$B$31+'AU-Route'!$B$38))*(1+Control!$B$13)+Raise!$B$11 | F41: =3*C41 | G41: =(F41*'AU-Route'!$B$18+('AU-Route'!$B$20+'AU-Route'!$B$21+'AU-Route'!$B$22+'AU-Route'!$B$15+'AU-Route'!$B$31+'AU-Route'!$B$38))*(1+Control!$B$13)+Raise!$B$11 | H41: ='Compute-Revenue'!$B$31/E41
A42: =D24 | B42: Habanero 19 kg/s, conservative conversion | C42: =ROUNDUP(ROUND('AU-Route'!$B$7/A42,6),0) | D42: =2*C42 | E42: =(D42*'AU-Route'!$B$18+('AU-Route'!$B$20+'AU-Route'!$B$21+'AU-Route'!$B$22+'AU-Route'!$B$15+'AU-Route'!$B$31+'AU-Route'!$B$38))*(1+Control!$B$13)+Raise!$B$11 | F42: =3*C42 | G42: =(F42*'AU-Route'!$B$18+('AU-Route'!$B$20+'AU-Route'!$B$21+'AU-Route'!$B$22+'AU-Route'!$B$15+'AU-Route'!$B$31+'AU-Route'!$B$38))*(1+Control!$B$13)+Raise!$B$11 | H42: ='Compute-Revenue'!$B$31/E42
A43: =C24 | B43: Habanero 19 kg/s, optimistic conversion | C43: =ROUNDUP(ROUND('AU-Route'!$B$7/A43,6),0) | D43: =2*C43 | E43: =(D43*'AU-Route'!$B$18+('AU-Route'!$B$20+'AU-Route'!$B$21+'AU-Route'!$B$22+'AU-Route'!$B$15+'AU-Route'!$B$31+'AU-Route'!$B$38))*(1+Control!$B$13)+Raise!$B$11 | F43: =3*C43 | G43: =(F43*'AU-Route'!$B$18+('AU-Route'!$B$20+'AU-Route'!$B$21+'AU-Route'!$B$22+'AU-Route'!$B$15+'AU-Route'!$B$31+'AU-Route'!$B$38))*(1+Control!$B$13)+Raise!$B$11 | H43: ='Compute-Revenue'!$B$31/E43
A44: =Rates!$D$13 | B44: Model LOW | C44: =ROUNDUP(ROUND('AU-Route'!$B$7/A44,6),0) | D44: =2*C44 | E44: =(D44*'AU-Route'!$B$18+('AU-Route'!$B$20+'AU-Route'!$B$21+'AU-Route'!$B$22+'AU-Route'!$B$15+'AU-Route'!$B$31+'AU-Route'!$B$38))*(1+Control!$B$13)+Raise!$B$11 | F44: =3*C44 | G44: =(F44*'AU-Route'!$B$18+('AU-Route'!$B$20+'AU-Route'!$B$21+'AU-Route'!$B$22+'AU-Route'!$B$15+'AU-Route'!$B$31+'AU-Route'!$B$38))*(1+Control!$B$13)+Raise!$B$11 | H44: ='Compute-Revenue'!$B$31/E44
A45: ='AU-Route'!$B$7/2 | B45: Threshold where 2 producers just cover nameplate | C45: =ROUNDUP(ROUND('AU-Route'!$B$7/A45,6),0) | D45: =2*C45 | E45: =(D45*'AU-Route'!$B$18+('AU-Route'!$B$20+'AU-Route'!$B$21+'AU-Route'!$B$22+'AU-Route'!$B$15+'AU-Route'!$B$31+'AU-Route'!$B$38))*(1+Control!$B$13)+Raise!$B$11 | F45: =3*C45 | G45: =(F45*'AU-Route'!$B$18+('AU-Route'!$B$20+'AU-Route'!$B$21+'AU-Route'!$B$22+'AU-Route'!$B$15+'AU-Route'!$B$31+'AU-Route'!$B$38))*(1+Control!$B$13)+Raise!$B$11 | H45: ='Compute-Revenue'!$B$31/E45
A46: =Rates!$D$12 | B46: Model BASE | C46: =ROUNDUP(ROUND('AU-Route'!$B$7/A46,6),0) | D46: =2*C46 | E46: =(D46*'AU-Route'!$B$18+('AU-Route'!$B$20+'AU-Route'!$B$21+'AU-Route'!$B$22+'AU-Route'!$B$15+'AU-Route'!$B$31+'AU-Route'!$B$38))*(1+Control!$B$13)+Raise!$B$11 | F46: =3*C46 | G46: =(F46*'AU-Route'!$B$18+('AU-Route'!$B$20+'AU-Route'!$B$21+'AU-Route'!$B$22+'AU-Route'!$B$15+'AU-Route'!$B$31+'AU-Route'!$B$38))*(1+Control!$B$13)+Raise!$B$11 | H46: ='Compute-Revenue'!$B$31/E46
A47: =Rates!$D$14 | B47: Model HIGH (gross source figure) | C47: =ROUNDUP(ROUND('AU-Route'!$B$7/A47,6),0) | D47: =2*C47 | E47: =(D47*'AU-Route'!$B$18+('AU-Route'!$B$20+'AU-Route'!$B$21+'AU-Route'!$B$22+'AU-Route'!$B$15+'AU-Route'!$B$31+'AU-Route'!$B$38))*(1+Control!$B$13)+Raise!$B$11 | F47: =3*C47 | G47: =(F47*'AU-Route'!$B$18+('AU-Route'!$B$20+'AU-Route'!$B$21+'AU-Route'!$B$22+'AU-Route'!$B$15+'AU-Route'!$B$31+'AU-Route'!$B$38))*(1+Control!$B$13)+Raise!$B$11 | H47: ='Compute-Revenue'!$B$31/E47
A49: Status: NEEDS FOUNDER DATA. The only figures that close this tab are a site flow/temperature/injectivity test and an ORC vendor curve. Until then BASE 5 MWe NET is an ASSUMPTION 3.4-5.4x Habanero's best sustained circulation.

Sheet Power-Economics
A1: ARCHEGON · POWER ECONOMICS (PowerCo: wells + ORC, AU route), priced as electricity, separate from the hall
A3: Both reviews asked for two businesses with two P&Ls. PowerCo owns wells and plant and sells energy to DCCo at a TRANSFER PRICE = its levelised cost. WACC and life are ASSUMPTIONS (Rates).
A5: Generation asset
A6: Generation capex pre-contingency (wells + mob + ORC + brine gathering), A$ | B6: ='AU-Route'!$B$23 | C6: AU-Route B23
A7: Generation capex incl. contingency, A$ | B7: =B6*(1+Control!$B$13)
A8: Net nameplate (MW) | B8: ='AU-Route'!$B$7 | C8: NET (Definitions)
A9: Average net delivered (MW) | B9: =B8*Control!$B$16 | C9: Average, NOT firm
A10: Annual energy (MWh) | B10: =B9*8760 | C10: Facility load x 8760 h
A11: Plant fixed O&M, A$/yr | B11: ='Compute-Revenue'!$B$23 | C11: Excludes well replacement (RATE_MISSING)
A13: Levelised cost of energy (LCOE) = (capex x CRF + O&M) / MWh
A14: Case | B14: Discount rate | C14: Life (yrs) | D14: CRF | E14: LCOE A$/MWh | F14: Capital + O&M, A$/yr
A15: Low | B15: =0.06 | C15: =Rates!$D$71 | D15: =B15/(1-(1+B15)^(-C15)) | E15: =F15/$B$10 | F15: =$B$7*D15+$B$11
A16: BASE (Rates wacc_base) | B16: =Rates!$D$70 | C16: =Rates!$D$71 | D16: =B16/(1-(1+B16)^(-C16)) | E16: =F16/$B$10 | F16: =$B$7*D16+$B$11
A17: High | B17: =0.10 | C17: =Rates!$D$71 | D17: =B17/(1-(1+B17)^(-C17)) | E17: =F17/$B$10 | F17: =$B$7*D17+$B$11
A18: Stress check | B18: =0.10 | C18: =20 | D18: =B18/(1-(1+B18)^(-C18)) | E18: =F18/$B$10 | F18: =$B$7*D18+$B$11
A20: LCOE at ACTUAL (Habanero 4) well cost, BASE rate, A$/MWh | B20: =((('AU-Route'!$B$10*Rates!$D$9)+'AU-Route'!$B$20+'AU-Route'!$B$21+'AU-Route'!$B$22)*(1+Control!$B$13)*D16+B11)/B10 | C20: Check: ~A$553
A21: Make-up well provision (1 well / N yrs), A$/yr | B21: ='AU-Route'!$B$18/Rates!$D$79 | C21: ASSUMPTION interval; sensitivity only
A22: LCOE incl. make-up wells, BASE rate, A$/MWh | B22: =(F16+B21)/B10
A24: Transfer price and market comparison
A25: TRANSFER PRICE to DCCo (= BASE LCOE), A$/MWh | B25: =E16 | C25: Power system recovers its capital at the BASE rate, no profit
A26: NEM average wholesale, A$/MWh | B26: =Rates!$D$34 | C26: VERIFIED
A27: SA wholesale, A$/MWh | B27: =Rates!$D$72 | C27: VERIFIED
A28: Premium over SA wholesale, A$/yr | B28: =(B25-B27)*B10 | C28: What the hall pays for islanded geothermal vs grid wholesale (network/retail charges excluded, so overstated)
A29: Generation capital + O&M as share of colo revenue | B29: =F16/'Compute-Revenue'!$B$10 | C29: Check: 83% / 98% / 113% at 6 / 8 / 10%
A31: Power-only fallback (replaces v2 Compute-Revenue!B17)
A32: AU islanded: revenue if no compute contract lands, A$/yr | B32: =0 | C32: No grid connection = no buyer
A33: IF a grid connection were built: export at SA wholesale, A$/yr | B33: =B10*Rates!$D$72 | C33: Connection capex RATE_MISSING; not contracted
A34: Curtailable flexible load (e.g. interruptible compute), A$/yr | B34: =0 | C34: RATE_MISSING: needs a tenant price

Sheet DC-Economics
A1: ARCHEGON · DATA-CENTRE ECONOMICS (DCCo: the hall), buying power at the transfer price
A3: The hall is a colocation landlord: tenants own the GPUs. It buys energy from PowerCo at the transfer price. Consolidated contribution (bottom) still reconciles to Compute-Revenue!B31.
A5: DC capex incl. contingency, A$ | B5: ='AU-Route'!$B$31*(1+Control!$B$13) | C5: Shell + liquid + remote loading
A6: Colo revenue, A$/yr | B6: ='Compute-Revenue'!$B$10 | C6: US$172.5/kW/mo, US 10 MW+ benchmark, full from day one
A7: Power bought from PowerCo at transfer price, A$/yr | B7: ='Power-Economics'!$B$10*'Power-Economics'!$B$25
A8: DC non-energy opex, A$/yr | B8: ='Compute-Revenue'!$B$26 | C8: RATE_MISSING (A$0)
A9: DCCo contribution before team, A$/yr | B9: =B6-B7-B8 | C9: What the hall earns once it pays for its power
A10: DCCo yield on DC capex | B10: =B9/B5
A11: Hall yield on DC capex with FREE power (gross, before DC opex) | B11: =B6/B5 | C11: Check: 8.8% ceiling at this site
A12: PowerCo margin over its levelised cost, A$/yr | B12: =0 | C12: By construction (transfer = LCOE)
A13: Team + overhead, A$/yr | B13: ='Compute-Revenue'!$B$27
A14: Consolidated contribution (accounting view, capital not charged), A$/yr | B14: ='Compute-Revenue'!$B$31 | C14: Reconciles to v2: A$10.06m
A15: Contribution / raise | B15: ='Compute-Revenue'!$B$31/Raise!$B$14 | C15: 3.3% - stated openly on slide 13 v3
A16: Undiscounted contribution over asset life vs raise | B16: ='Compute-Revenue'!$B$31*Rates!$D$71-Raise!$B$14 | C16: Negative = the ask is not repaid in 25 years
A17: Colo rate needed for a 10% contribution yield on the raise, US$/kW/month | B17: =(0.1*Raise!$B$14+'Compute-Revenue'!$B$28)/('Compute-Revenue'!$B$6*12)*Rates!$D$4 | C17: Check: ~US$418 = 2.4x benchmark
A18: Contribution with an illustrative remote discount on colo price, A$/yr | B18: ='Compute-Revenue'!$B$10*(1-Rates!$D$83)-'Compute-Revenue'!$B$28 | C18: ASSUMPTION 20% (Rates colo_remote_discount)
A20: Colo benchmark fit (both reviews): the rate is a US primary-market 10 MW+ asking rate. Its energy basis (included vs pass-through) is UNCONFIRMED. NEEDS DATA: an Australian broker view for an islanded remote site and tenant LOIs with price and energy terms.
A21: ANCHOR comparables (Rates D31:D32) are ~400 MW, 15-20 yr hyperscale leases: they do not transfer to a 5 MW unproven site. Shown for reference only.

Sheet Route-Compare
A1: ARCHEGON · NZ vs AU on the model's own numbers (stated honestly)
A3: Metric | B3: Australia (drill) | C3: New Zealand (contract) | D3: Note
A4: Capex, A$ | B4: ='AU-Route'!$B$43 | C4: =Raise!$B$7
A5: Runway, A$ | B5: =Control!$B$15*Control!$B$14 | C5: =Control!$B$15*Control!$B$14 | D5: One team per route
A6: Raise, A$ | B6: =B4+B5 | C6: =C4+C5
A7: Revenue (colo), A$/yr | B7: ='Compute-Revenue'!$B$10 | C7: ='Compute-Revenue'!$B$10 | D7: Same hall
A8: Energy / plant cost, A$/yr | B8: ='Compute-Revenue'!$B$23 | C8: ='Compute-Revenue'!$B$24 | D8: AU: plant O&M only (capital not charged). NZ: bought at one week of spot.
A9: Team, A$/yr | B9: =Control!$B$15*12 | C9: =Control!$B$15*12
A10: Contribution, A$/yr | B10: =B7-B8-B9 | C10: =C7-C8-C9
A11: Contribution / raise | B11: =B10/B6 | C11: =C10/C6 | D11: NZ beats AU on these numbers (Check: 5.2% vs 3.3%)
A12: Drilling risk carried | B12: Yes (4 wells) | C12: None
A13: What Archegon owns | B13: A reservoir (option value) | C13: A contract | D13: The AU case is an OPTION on a resource; it must be argued with a probability and payoff, not by slide order.
A14: NZ power price at which NZ contribution/raise = AU, NZ$/MWh | C14: =(C7-C9-B11*C6)/('NZ-Route'!$B$42)*Rates!$D$5 | D14: NZ wins unless contracted power costs more than this
A16: NZ power price basis (both reviews): NZ$105/MWh is ONE week of spot (17-23 May 2026). NZ prices move with hydrology. NEEDS DATA: an indicative 15-20 yr PPA quote from Contact/Mercury, cross-checked to ASX NZ electricity futures.

Sheet Firm-Power
A1: ARCHEGON · FIRM vs AVERAGE POWER, redundancy, hot day, black start (AU route)
A3: v2 labelled average power "firm". Islanded, with no storage or grid, the 10% of hours not covered by a 0.90 capacity factor are outages. This tab states what is firm today and lists the unpriced cover.
A5: Facility load (MW) | B5: =Control!$B$12*Control!$B$17
A6: Net nameplate (MW) | B6: ='AU-Route'!$B$7
A7: Average net (MW) = nameplate x CF | B7: =B6*Control!$B$16 | C7: Average, NOT firm
A8: Producers x NET MWe (MW) | B8: ='AU-Route'!$B$8*'AU-Route'!$B$6 | C8: Well capacity
A9: Margin of well capacity over nameplate (MW) | B9: =B8-B6 | C9: Decline buffer only once a role is chosen
A10: FIRM supply with one producer out (N-1), MW | B10: =MIN(B6,('AU-Route'!$B$8-1)*'AU-Route'!$B$6) | C10: No plant, ORC or transformer redundancy assumed
A11: Firm critical IT under N-1 (MW) | B11: =B10/Control!$B$17 | C11: Check: 4.0 MW
A12: Firm IT in whole modules (MW) | B12: =FLOOR(B11,Rates!$D$82) | C12: 3 modules
A13: Hours/yr not covered at the capacity factor | B13: =(1-Control!$B$16)*8760 | C13: If outage rather than uniform derate
A14: Energy to cover those hours (MWh) | B14: =B13*B5
A15: Diesel to cover them (litres, illustrative) | B15: =B14*1000*Rates!$D$73 | C15: ASSUMPTION fuel rate; diesel price RATE_MISSING; ends carbon-free for those hours
A17: N-1 on producers: cost to make the wells firm
A18: Producers for N-1 | B18: ='AU-Route'!$B$8+1
A19: Extra wells (one producer + one injector) | B19: =2
A20: Extra cost incl. contingency, A$ | B20: =2*'AU-Route'!$B$18*(1+Control!$B$13) | C20: Check: +A$41.25m
A21: AU raise with N-1 producers, A$ | B21: =Raise!$B$14+B20 | C21: Check: A$348.5m
A23: Firm-power items priced at PUBLIC PROXIES (not in headline Raise; see Proxies for the adjusted raise)
A24: Grid-forming BESS (frequency control, ride-through) | B24: =Proxies!$B$35*(1+Control!$B$13) | C24: PUBLIC PROXY: GenCost 2025-26 2 h BESS, incl. contingency
A25: Standby generation / local gas for N-1 | B25: =Proxies!$B$36*(1+Control!$B$13) | C25: PUBLIC PROXY: GenCost 2025-26 gas recip, incl. contingency
A26: Black-start source for ORC auxiliaries | B26: 0 | C26: PUBLIC PROXY: no separate figure; covered by BESS + recips
A27: Hot-day ORC derate (vendor curve) | B27: =Rates!$D$77
A29: Hot day (ILLUSTRATIVE derates, NOT vendor data): how many 1.25 MW modules stay lit at PUE 1.25?
A30: ORC output loss (illustrative) | B30: Net available (MW) | C30: Lit modules, both producers | D30: Lit modules, one producer out
A31: 0 | B31: =$B$6*(1-A31) | C31: =MIN(4,INT(B31/Control!$B$17/Rates!$D$82+1E-9)) | D31: =MIN(4,INT(MIN(B31,('AU-Route'!$B$8-1)*'AU-Route'!$B$6*(1-A31))/Control!$B$17/Rates!$D$82+1E-9))
A32: 0.1 | B32: =$B$6*(1-A32) | C32: =MIN(4,INT(B32/Control!$B$17/Rates!$D$82+1E-9)) | D32: =MIN(4,INT(MIN(B32,('AU-Route'!$B$8-1)*'AU-Route'!$B$6*(1-A32))/Control!$B$17/Rates!$D$82+1E-9))
A33: 0.2 | B33: =$B$6*(1-A33) | C33: =MIN(4,INT(B33/Control!$B$17/Rates!$D$82+1E-9)) | D33: =MIN(4,INT(MIN(B33,('AU-Route'!$B$8-1)*'AU-Route'!$B$6*(1-A33))/Control!$B$17/Rates!$D$82+1E-9))
A34: 0.3 | B34: =$B$6*(1-A34) | C34: =MIN(4,INT(B34/Control!$B$17/Rates!$D$82+1E-9)) | D34: =MIN(4,INT(MIN(B34,('AU-Route'!$B$8-1)*'AU-Route'!$B$6*(1-A34))/Control!$B$17/Rates!$D$82+1E-9))
A36: Peak PUE on a 40+ degC day is also higher than the 1.25 annual average (ASSUMPTION) - not modelled. NEEDS DATA: hourly simulation with site weather, ORC derate curve and peak PUE; power-systems study (load steps, frequency control).
A38: Diagram E, corrected cases
A39: Wells 20% low: well capacity (MW) | B39: =B8*0.8 | C39: 8.0 MW still covers 6.94 MW: NO change at the fence
A40: Per-producer rating below which supply falls (MW) | B40: ='AU-Route'!$B$7/'AU-Route'!$B$8 | C40: 3.47 MWe = 31% low
A41: Shortfall threshold vs BASE | B41: =1-B40/'AU-Route'!$B$6
A42: One producer lost: supply (MW) | B42: =B10 | C42: 4.0 MW IT -> 3 modules: the case Diagram E actually draws
A43: Base-case margin: 4 modules draw vs average supply (MW) | B43: =B7-4*Rates!$D$82*Control!$B$17 | C43: Zero: any derate sheds a module

Sheet Gated-Plan
A1: ARCHEGON · GATED, RESERVOIR-FIRST PLAN with pass/fail criteria (replaces the single A$307m PoC)
A3: Gate | B3: What it buys | C3: Capital, A$ (derived) | D3: Cumulative, A$ | E3: Pass / fail criteria | F3: Status
A4: Gate 0 - SEED (US$10m) | B4: Tranched seed: engineers/viability, lawyers/government, DC procurement, financing, itemised runway, buffer; Tranche 3 pre-buys Gate 1 long-lead items. See Seed tab. | C4: =Seed!$C$7 | D4: =C4 | E4: Signed reservoir-engineer case for flow, temperature, injectivity; AFE in 2027 A$; principal named; LOI with price and energy terms | F4: NEEDS FOUNDER INPUT: amount = sum of quotes (RATE_MISSING). Not modelled.
A5: Gate 1a - appraisal well (option) | B5: One deep well: temperature, stress, image logs, injectivity. Cheaper than a doublet. | C5: =('AU-Route'!$B$18+Rates!$D$11)*(1+Control!$B$13)+Raise!$B$11 | D5: n/a (alternative to Gate 1) | E5: Temperature >= target; stress regime and fracture orientation compatible with the lateral design | F5: Derived from model rates
A6: Gate 1 - RESERVOIR TEST | B6: One doublet + 90-180 day circulation test. No plant, no hall. | C6: =((2*('AU-Route'!$B$18+Rates!$D$89)+Rates!$D$11)*(1+Control!$B$13)+Raise!$B$11-SUMIF(Seed!$H$31:$H$63,"T3",Seed!$E$31:$E$63))/(1-Seed!$C$15) | D6: =C6 | E6: v4: incl. stimulation of both wells; less seed Tranche 3 pre-buys; grossed up for the 6% success fee so the test is fully funded. | F6: Derived. Stimulation/test facilities RATE_MISSING (Rates D78)
A7: Gate 2 - first whole module | B7: Plant sized to MEASURED flow + one 1.25 MW module, signed tenant | C7: ='Funding-Tiers'!$B$28 | D7: =C7 | E7: Metered net power; PUE; tenant paying; N-1 design costed | F7: Derived (Funding-Tiers B28) incl. the Gate 1 doublet
A8: Gate 3 - 5 MW reference | B8: Scale to 4 modules | C8: =Raise!$B$14 | D8: =C8 | E8: Gate 2 performance holds; firm-power cover priced | F8: Model reference raise
A10: Seed (C4) is the A$10m shoestring budget on the Seed tab, above comparable geothermal seed rounds (US$3-6m, Proxies B51:B52). The next round is the Gate 1 reservoir test (C6, ~A$52m model estimate), raised only if the Seed go/no-go gates pass.
A11: Each gate is a separate decision. Later capital is conditional on the previous gate passing; an unproven EGS PoC is not debt-financeable. Capital stack (equity / ARENA / strategic) NEEDS FOUNDER INPUT.
A14: GATE 1 RESERVOIR TEST: GO / NO-GO LIMITS, checked by an investor-appointed independent engineer. Gate 2 adds a 12-month circulation record before plant capital.
A15: Metric | B15: GO (pass) | C15: REVIEW (re-scope before Gate 2) | D15: NO-GO (stop) | E15: Basis and sources
A16: Net capability per producer at measured temperature, sustained 90+ days | B16: =">= "&ROUND('Flow-Basis'!$C$18,0)&"-"&ROUND('Flow-Basis'!$D$18,0)&" kg/s at 215 degC, i.e. >= 5 MWe net per producer" | C16: 3.47-5 MWe: two producers still cover the plant but the 3.06 MW decline margin shrinks; re-price make-up | D16: < 3.47 MWe net per producer | E16: Flow-Basis tab; Firm-Power B8:B9; Habanero best sustained 19 kg/s (2013, ARENA)
A17: Thermal decline (degC/yr), from tracer test + calibrated reservoir model, not from the 60-day trend | B17: ="Forecast <= "&TEXT(Decline!$C$28,"0.0")&" degC/yr (keeps 4 modules lit 25 yrs on 2 producers)" | C17: Above that: price make-up drilling (Headroom) before Gate 2 | D17: Forecast >= 5 degC/yr (Project Red reading) or early tracer breakthrough | E17: Decline tab threshold; GeoExPro Apr 2026; tracer practice (round-3 review)
A18: Long-run monitoring after Gate 1 | B18: 12-month circulation record before Gate 2 plant capital; annual tracer + temperature logs | C18: Trend above forecast: make-up campaign triggered (Headroom b) | D18: Trend above 5 degC/yr after 12 months | E18: Staged commitment: plant and hall capital released only after the 12-month record
A19: Fluid loss (injected minus produced, % of injected) | B19: <= 1% | C19: 1-5%: licence and bores sized for it (Water tab) | D19: > 5% sustained | E19: Argonne ANL-EVS-14-2; Fenton Hill 7%, Rosemanowes ~20%
A20: Flow impedance / pumping parasitic | B20: Pumping power <= 10% of gross at target flow (ASSUMPTION) | C20: 10-20%: re-price parasitic | D20: > 20%: flow bought with pressure, not permeability | E20: Round-3 review: impedance sets the economics
A21: Induced seismicity | B21: Traffic light agreed with the SA regulator, receptor-based (PGV at nearest receptor), Utah FORGE structure as a template | C21: Amber: pause and flow back, independent review | D21: Red set by the regulator below the basin record (Habanero 2003 reached ~ML 3.7); two Ambers = no-go | E21: Utah FORGE TLS v2; Basel 2006; Pohang 2017; Habanero 2003 (Asanuma et al. 2006)
A22: Data release | B22: Flow, temperature, injection, tracer and seismic data verified by the independent engineer and released to investors within 60 days | C22: - | D22: Data withheld or unverified | E22: Lesson from the 2026 disclosure dispute
A24: Any NO-GO stops the project before plant or hall capital. REVIEW results go back to investors with a re-scoped plan before Gate 2 is raised.
A26: FULL PROGRAMME COST: what the 5 MW reference costs once N-1, firm cover, stimulation, the success fee and the seed are priced
A27: Headline raise (now includes stimulation of all wells, Rates D78) | C27: =Raise!$B$14
A28: N-1 producers: third doublet incl. stimulation and contingency | C28: =2*('AU-Route'!$B$18+Rates!$D$89)*(1+Control!$B$13)
A29: N-1 plant: two 50% ORC trains instead of one, incl. contingency | C29: ='AU-Route'!$B$21*(Rates!$D$103-1)*(1+Control!$B$13)
A30: Transformer and switchgear N-1 | C30: 0 | D30: RATE_MISSING: needs a single-line design
A31: Firm cover: battery + standby engines (Proxies B38) | C31: =Proxies!$B$38
A32: Success fee on the Gate 1 round | C32: ='Gated-Plan'!$C$6*Seed!$C$15
A33: Seed (US$10m) | C33: ='Gated-Plan'!$C$4
A34: FULL PROGRAMME, A$ | C34: =SUM(C27:C33)
A35: Extra capital over the headline raise, A$ | C35: =C34-C27
A38: Year | C38: 0 | D38: 1 | E38: 2 | F38: 3 | G38: 4 | H38: 5 | I38: 6 | J38: 7 | K38: 8 | L38: 9 | M38: 10 | N38: 11 | O38: 12 | P38: 13 | Q38: 14 | R38: 15 | S38: 16 | T38: 17 | U38: 18 | V38: 19 | W38: 20 | X38: 21 | Y38: 22 | Z38: 23 | AA38: 24 | AB38: 25
A39: Colo, full programme | B39: =IF(SUM(C39:AB39)<0,"never repays",IFERROR(IRR(C39:AB39),"no IRR")) | C39: ='Sell-Compute'!C64-$C$35 | D39: ='Sell-Compute'!D64 | E39: ='Sell-Compute'!E64 | F39: ='Sell-Compute'!F64 | G39: ='Sell-Compute'!G64 | H39: ='Sell-Compute'!H64 | I39: ='Sell-Compute'!I64 | J39: ='Sell-Compute'!J64 | K39: ='Sell-Compute'!K64 | ... AB39: ='Sell-Compute'!AB64
A40: Compute flat, full programme | B40: =IF(SUM(C40:AB40)<0,"never repays",IFERROR(IRR(C40:AB40),"no IRR")) | C40: ='Sell-Compute'!C58-$C$35 | D40: ='Sell-Compute'!D58 | E40: ='Sell-Compute'!E58 | F40: ='Sell-Compute'!F58 | G40: ='Sell-Compute'!G58 | H40: ='Sell-Compute'!H58 | I40: ='Sell-Compute'!I58 | J40: ='Sell-Compute'!J58 | K40: ='Sell-Compute'!K58 | ... AB40: ='Sell-Compute'!AB58
A41: Compute falling, full programme | B41: =IF(SUM(C41:AB41)<0,"never repays",IFERROR(IRR(C41:AB41),"no IRR")) | C41: ='Sell-Compute'!C57-$C$35 | D41: ='Sell-Compute'!D57 | E41: ='Sell-Compute'!E57 | F41: ='Sell-Compute'!F57 | G41: ='Sell-Compute'!G57 | H41: ='Sell-Compute'!H57 | I41: ='Sell-Compute'!I57 | J41: ='Sell-Compute'!J57 | K41: ='Sell-Compute'!K57 | ... AB41: ='Sell-Compute'!AB57

Sheet Funding-Tiers
A1: ARCHEGON · FUNDING TIERS v3: what A$50m to A$500m buys (AU route), WHOLE 1.25 MW modules, value-optimised
A3: v3 fixes: (1) IT is built in whole 1.25 MW modules; (2) for each tier the optimiser picks the producer count with the best contribution per dollar COMMITTED, and leaves the rest undrawn instead of buying a doublet for a sliver of MW; (3) "firm" relabelled AVERAGE; (4) "minimum viable PoC" relabelled OPERATING BREAK-EVEN; (5) land+legals link now includes brine gathering and fibre; opex includes well replacement and DC opex lines (RATE_MISSING, A$0). ILLUSTRATIVE, NOT AN OFFER.
A6: FX AUD->USD | B6: =Rates!$D$4
A7: NET MWe per producer (scenario) | B7: ='AU-Route'!$B$6
A8: Cost per well, A$ | B8: ='AU-Route'!$B$18
A9: Rig mobilisation, A$ | B9: =Rates!$D$11
A10: ORC plant, A$ per kW NET | B10: =Rates!$D$15/Rates!$D$4
A11: DC modules, A$ per MW IT | B11: =(Rates!$D$21+IF(Control!$B$8="LIQUID",Rates!$D$22,0))/Rates!$D$4*IF(Control!$B$9="ON",Rates!$D$24,1)
A12: IT fit-out, A$ per MW IT (BAREMETAL only) | B12: =IF(Control!$B$5="BAREMETAL",Rates!$D$28/Rates!$D$4,0)
A13: PUE | B13: =Control!$B$17
A14: Capacity factor | B14: =Control!$B$16
A15: Contingency | B15: =Control!$B$13
A16: Runway, A$ | B16: =Control!$B$15*Control!$B$14
A17: Capex per MW IT excl. wells, pre-contingency, A$ | B17: =B10*1000*B13/B14+B11+B12
A18: Revenue per MW IT per year, A$ (COLO / ANCHOR / BAREMETAL=0) | B18: =IF(Control!$B$5="COLO",Rates!$D$29*12*1000,IF(Control!$B$5="ANCHOR",Rates!$D$31,0))/Rates!$D$4
A19: Plant O&M + DC opex per MW IT per year, A$ | B19: =Rates!$D$16*1000*B13/B14/Rates!$D$4+Rates!$D$43/Rates!$D$4
A20: Fixed opex per year (team + well replacement), A$ | B20: =Control!$B$15*12+Rates!$D$42
A21: Module step, MW IT | B21: =Rates!$D$82
A22: Land + legals + brine gathering + fibre (RATE_MISSING), A$ | B22: ='AU-Route'!$B$15+'AU-Route'!$B$38+'AU-Route'!$B$22+'AU-Route'!$B$29
A23: OPERATING BREAK-EVEN IT, continuous (MW) - theoretical | B23: =IF(B18-B19<=0,"n/a",B20/(B18-B19))
A24: Producers at break-even | B24: =IF(ISNUMBER(B23),ROUNDUP(ROUND(B23*B13/B14/B7,6),0),"n/a")
A25: OPERATING BREAK-EVEN HALL, A$ (v2 "minimum viable PoC": NOT viable) | B25: =IF(ISNUMBER(B23),(2*B24*B8+B9+B17*B23+B22)*(1+B15)+B16,"n/a")
A26: Modules needed to break even (whole) | B26: =IF(ISNUMBER(B23),ROUNDUP(B23/B21,0),"n/a")
A27: Producers for one whole module | B27: =ROUNDUP(ROUND(B21*B13/B14/B7,6),0)
A28: SMALLEST WHOLE-MODULE BUILD (1 x 1.25 MW), A$ | B28: =(2*B27*B8+B9+B17*B21+B22)*(1+B15)+B16
A29: RESERVOIR-TEST TRANCHE (doublet, no plant/hall), A$ | B29: ='Gated-Plan'!$C$6
A31: Funding A$ | B31: Funding US$ | C31: Budget pre-contingency | D31: IT n=1 | E31: IT n=2 | F31: IT n=3 | G31: IT n=4 | H31: IT n=5 | I31: IT n=6 | J31: IT n=7 | K31: IT n=8 | L31: IT n=9 | M31: IT n=10 | N31: Committed n=1 | O31: Committed n=2 | P31: Committed n=3 | Q31: Committed n=4 | R31: Committed n=5 | S31: Committed n=6 | T31: Committed n=7 | U31: Committed n=8 | V31: Committed n=9 | W31: Committed n=10 | X31: Contrib n=1 | Y31: Contrib n=2 | Z31: Contrib n=3 | AA31: Contrib n=4 | AB31: Contrib n=5 | AC31: Contrib n=6 | AD31: Contrib n=7 | AE31: Contrib n=8 | AF31: Contrib n=9 | AG31: Contrib n=10 | AH31: Ratio n=1 | AI31: Ratio n=2 | AJ31: Ratio n=3 | AK31: Ratio n=4 | AL31: Ratio n=5 | AM31: Ratio n=6 | AN31: Ratio n=7 | AO31: Ratio n=8 | AP31: Ratio n=9 | AQ31: Ratio n=10 | AR31: Best ratio | AS31: Producers (chosen) | AT31: IT MW (whole modules) | AU31: Modules | AV31: Total wells | AW31: Net nameplate MW | AX31: AVERAGE MW at fence (not firm) | AY31: Well capacity MW | AZ31: GB200 racks (complete) | BA31: Wells + mob | BB31: ORC plant | BC31: DC modules | BD31: IT fit-out | BE31: Unpriced lines (A$0) | BF31: Contingency | BG31: Runway | BH31: Committed | BI31: Undrawn | BJ31: Revenue/yr | BK31: Opex/yr | BL31: Contribution/yr | BM31: Contribution / committed | BN31: Status
A32: 50000000 | B32: =A32*$B$6 | C32: =MAX(0,(A32-$B$16)/(1+$B$15)) | D32: =MAX(0,FLOOR(MIN(1*$B$7*$B$14/$B$13,(C32-2*1*$B$8-$B$9-$B$22)/$B$17)+1E-9,$B$21)) | E32: =MAX(0,FLOOR(MIN(2*$B$7*$B$14/$B$13,(C32-2*2*$B$8-$B$9-$B$22)/$B$17)+1E-9,$B$21)) | F32: =MAX(0,FLOOR(MIN(3*$B$7*$B$14/$B$13,(C32-2*3*$B$8-$B$9-$B$22)/$B$17)+1E-9,$B$21)) | G32: =MAX(0,FLOOR(MIN(4*$B$7*$B$14/$B$13,(C32-2*4*$B$8-$B$9-$B$22)/$B$17)+1E-9,$B$21)) | H32: =MAX(0,FLOOR(MIN(5*$B$7*$B$14/$B$13,(C32-2*5*$B$8-$B$9-$B$22)/$B$17)+1E-9,$B$21)) | I32: =MAX(0,FLOOR(MIN(6*$B$7*$B$14/$B$13,(C32-2*6*$B$8-$B$9-$B$22)/$B$17)+1E-9,$B$21)) | J32: =MAX(0,FLOOR(MIN(7*$B$7*$B$14/$B$13,(C32-2*7*$B$8-$B$9-$B$22)/$B$17)+1E-9,$B$21)) | K32: =MAX(0,FLOOR(MIN(8*$B$7*$B$14/$B$13,(C32-2*8*$B$8-$B$9-$B$22)/$B$17)+1E-9,$B$21)) | L32: =MAX(0,FLOOR(MIN(9*$B$7*$B$14/$B$13,(C32-2*9*$B$8-$B$9-$B$22)/$B$17)+1E-9,$B$21)) | M32: =MAX(0,FLOOR(MIN(10*$B$7*$B$14/$B$13,(C32-2*10*$B$8-$B$9-$B$22)/$B$17)+1E-9,$B$21)) | N32: =IF(D32>0,(2*1*$B$8+$B$9+$B$22+$B$17*D32)*(1+$B$15)+$B$16,0) | O32: =IF(E32>0,(2*2*$B$8+$B$9+$B$22+$B$17*E32)*(1+$B$15)+$B$16,0) | P32: =IF(F32>0,(2*3*$B$8+$B$9+$B$22+$B$17*F32)*(1+$B$15)+$B$16,0) | Q32: =IF(G32>0,(2*4*$B$8+$B$9+$B$22+$B$17*G32)*(1+$B$15)+$B$16,0) | R32: =IF(H32>0,(2*5*$B$8+$B$9+$B$22+$B$17*H32)*(1+$B$15)+$B$16,0) | S32: =IF(I32>0,(2*6*$B$8+$B$9+$B$22+$B$17*I32)*(1+$B$15)+$B$16,0) | T32: =IF(J32>0,(2*7*$B$8+$B$9+$B$22+$B$17*J32)*(1+$B$15)+$B$16,0) | U32: =IF(K32>0,(2*8*$B$8+$B$9+$B$22+$B$17*K32)*(1+$B$15)+$B$16,0) | V32: =IF(L32>0,(2*9*$B$8+$B$9+$B$22+$B$17*L32)*(1+$B$15)+$B$16,0) | W32: =IF(M32>0,(2*10*$B$8+$B$9+$B$22+$B$17*M32)*(1+$B$15)+$B$16,0) | X32: =IF(D32>0,D32*($B$18-$B$19)-$B$20,0) | Y32: =IF(E32>0,E32*($B$18-$B$19)-$B$20,0) | Z32: =IF(F32>0,F32*($B$18-$B$19)-$B$20,0) | AA32: =IF(G32>0,G32*($B$18-$B$19)-$B$20,0) | AB32: =IF(H32>0,H32*($B$18-$B$19)-$B$20,0) | AC32: =IF(I32>0,I32*($B$18-$B$19)-$B$20,0) | AD32: =IF(J32>0,J32*($B$18-$B$19)-$B$20,0) | AE32: =IF(K32>0,K32*($B$18-$B$19)-$B$20,0) | ... AG32: =IF(M32>0,M32*($B$18-$B$19)-$B$20,0) | AH32: =IF(D32>0,X32/N32,-99) | AI32: =IF(E32>0,Y32/O32,-99) | AJ32: =IF(F32>0,Z32/P32,-99) | AK32: =IF(G32>0,AA32/Q32,-99) | AL32: =IF(H32>0,AB32/R32,-99) | AM32: =IF(I32>0,AC32/S32,-99) | AN32: =IF(J32>0,AD32/T32,-99) | AO32: =IF(K32>0,AE32/U32,-99) | ... AQ32: =IF(M32>0,AG32/W32,-99) | AR32: =MAX(AH32:AQ32) | AS32: =IF(AR32=-99,0,MATCH(AR32,AH32:AQ32,0)) | AT32: =IF(AS32=0,0,INDEX(D32:M32,AS32)) | AU32: =ROUND(AT32/$B$21,0) | AV32: =2*AS32 | AW32: =AT32*$B$13/$B$14 | AX32: =AW32*$B$14 | AY32: =AS32*$B$7 | AZ32: =ROUNDDOWN(AT32*1000/Rates!$D$27,0) | BA32: =IF(AS32=0,0,2*AS32*$B$8+$B$9) | BB32: =AW32*1000*$B$10 | BC32: =AT32*$B$11 | BD32: =AT32*$B$12 | BE32: =IF(AS32=0,0,$B$22) | BF32: =(BA32+BB32+BC32+BD32+BE32)*$B$15 | BG32: =IF(AS32=0,0,$B$16) | BH32: =BA32+BB32+BC32+BD32+BE32+BF32+BG32 | BI32: =A32-BH32 | BJ32: =AT32*$B$18 | BK32: =IF(AS32=0,0,AT32*$B$19+$B$20) | BL32: =BJ32-BK32 | BM32: =IF(BH32>0,BL32/BH32,0) | BN32: =IF(AS32=0,IF(A32>=$B$29,"RESERVOIR TEST ONLY: funds a doublet test, not a powered module","BELOW A DOUBLET: appraisal well at most"),IF(BL32<0,"Builds whole modules but contribution is negative",IF(AT32<Control!$B$12,"Operating break-even or better, below the 5 MW reference (not a return)","At/above the 5 MW reference (not a return)")))
A33: 100000000 | B33: =A33*$B$6 | C33: =MAX(0,(A33-$B$16)/(1+$B$15)) | D33: =MAX(0,FLOOR(MIN(1*$B$7*$B$14/$B$13,(C33-2*1*$B$8-$B$9-$B$22)/$B$17)+1E-9,$B$21)) | E33: =MAX(0,FLOOR(MIN(2*$B$7*$B$14/$B$13,(C33-2*2*$B$8-$B$9-$B$22)/$B$17)+1E-9,$B$21)) | F33: =MAX(0,FLOOR(MIN(3*$B$7*$B$14/$B$13,(C33-2*3*$B$8-$B$9-$B$22)/$B$17)+1E-9,$B$21)) | G33: =MAX(0,FLOOR(MIN(4*$B$7*$B$14/$B$13,(C33-2*4*$B$8-$B$9-$B$22)/$B$17)+1E-9,$B$21)) | H33: =MAX(0,FLOOR(MIN(5*$B$7*$B$14/$B$13,(C33-2*5*$B$8-$B$9-$B$22)/$B$17)+1E-9,$B$21)) | I33: =MAX(0,FLOOR(MIN(6*$B$7*$B$14/$B$13,(C33-2*6*$B$8-$B$9-$B$22)/$B$17)+1E-9,$B$21)) | J33: =MAX(0,FLOOR(MIN(7*$B$7*$B$14/$B$13,(C33-2*7*$B$8-$B$9-$B$22)/$B$17)+1E-9,$B$21)) | K33: =MAX(0,FLOOR(MIN(8*$B$7*$B$14/$B$13,(C33-2*8*$B$8-$B$9-$B$22)/$B$17)+1E-9,$B$21)) | L33: =MAX(0,FLOOR(MIN(9*$B$7*$B$14/$B$13,(C33-2*9*$B$8-$B$9-$B$22)/$B$17)+1E-9,$B$21)) | M33: =MAX(0,FLOOR(MIN(10*$B$7*$B$14/$B$13,(C33-2*10*$B$8-$B$9-$B$22)/$B$17)+1E-9,$B$21)) | N33: =IF(D33>0,(2*1*$B$8+$B$9+$B$22+$B$17*D33)*(1+$B$15)+$B$16,0) | O33: =IF(E33>0,(2*2*$B$8+$B$9+$B$22+$B$17*E33)*(1+$B$15)+$B$16,0) | P33: =IF(F33>0,(2*3*$B$8+$B$9+$B$22+$B$17*F33)*(1+$B$15)+$B$16,0) | Q33: =IF(G33>0,(2*4*$B$8+$B$9+$B$22+$B$17*G33)*(1+$B$15)+$B$16,0) | R33: =IF(H33>0,(2*5*$B$8+$B$9+$B$22+$B$17*H33)*(1+$B$15)+$B$16,0) | S33: =IF(I33>0,(2*6*$B$8+$B$9+$B$22+$B$17*I33)*(1+$B$15)+$B$16,0) | T33: =IF(J33>0,(2*7*$B$8+$B$9+$B$22+$B$17*J33)*(1+$B$15)+$B$16,0) | U33: =IF(K33>0,(2*8*$B$8+$B$9+$B$22+$B$17*K33)*(1+$B$15)+$B$16,0) | V33: =IF(L33>0,(2*9*$B$8+$B$9+$B$22+$B$17*L33)*(1+$B$15)+$B$16,0) | W33: =IF(M33>0,(2*10*$B$8+$B$9+$B$22+$B$17*M33)*(1+$B$15)+$B$16,0) | X33: =IF(D33>0,D33*($B$18-$B$19)-$B$20,0) | Y33: =IF(E33>0,E33*($B$18-$B$19)-$B$20,0) | Z33: =IF(F33>0,F33*($B$18-$B$19)-$B$20,0) | AA33: =IF(G33>0,G33*($B$18-$B$19)-$B$20,0) | AB33: =IF(H33>0,H33*($B$18-$B$19)-$B$20,0) | AC33: =IF(I33>0,I33*($B$18-$B$19)-$B$20,0) | AD33: =IF(J33>0,J33*($B$18-$B$19)-$B$20,0) | AE33: =IF(K33>0,K33*($B$18-$B$19)-$B$20,0) | ... AG33: =IF(M33>0,M33*($B$18-$B$19)-$B$20,0) | AH33: =IF(D33>0,X33/N33,-99) | AI33: =IF(E33>0,Y33/O33,-99) | AJ33: =IF(F33>0,Z33/P33,-99) | AK33: =IF(G33>0,AA33/Q33,-99) | AL33: =IF(H33>0,AB33/R33,-99) | AM33: =IF(I33>0,AC33/S33,-99) | AN33: =IF(J33>0,AD33/T33,-99) | AO33: =IF(K33>0,AE33/U33,-99) | ... AQ33: =IF(M33>0,AG33/W33,-99) | AR33: =MAX(AH33:AQ33) | AS33: =IF(AR33=-99,0,MATCH(AR33,AH33:AQ33,0)) | AT33: =IF(AS33=0,0,INDEX(D33:M33,AS33)) | AU33: =ROUND(AT33/$B$21,0) | AV33: =2*AS33 | AW33: =AT33*$B$13/$B$14 | AX33: =AW33*$B$14 | AY33: =AS33*$B$7 | AZ33: =ROUNDDOWN(AT33*1000/Rates!$D$27,0) | BA33: =IF(AS33=0,0,2*AS33*$B$8+$B$9) | BB33: =AW33*1000*$B$10 | BC33: =AT33*$B$11 | BD33: =AT33*$B$12 | BE33: =IF(AS33=0,0,$B$22) | BF33: =(BA33+BB33+BC33+BD33+BE33)*$B$15 | BG33: =IF(AS33=0,0,$B$16) | BH33: =BA33+BB33+BC33+BD33+BE33+BF33+BG33 | BI33: =A33-BH33 | BJ33: =AT33*$B$18 | BK33: =IF(AS33=0,0,AT33*$B$19+$B$20) | BL33: =BJ33-BK33 | BM33: =IF(BH33>0,BL33/BH33,0) | BN33: =IF(AS33=0,IF(A33>=$B$29,"RESERVOIR TEST ONLY: funds a doublet test, not a powered module","BELOW A DOUBLET: appraisal well at most"),IF(BL33<0,"Builds whole modules but contribution is negative",IF(AT33<Control!$B$12,"Operating break-even or better, below the 5 MW reference (not a return)","At/above the 5 MW reference (not a return)")))
A34: 150000000 | B34: =A34*$B$6 | C34: =MAX(0,(A34-$B$16)/(1+$B$15)) | D34: =MAX(0,FLOOR(MIN(1*$B$7*$B$14/$B$13,(C34-2*1*$B$8-$B$9-$B$22)/$B$17)+1E-9,$B$21)) | E34: =MAX(0,FLOOR(MIN(2*$B$7*$B$14/$B$13,(C34-2*2*$B$8-$B$9-$B$22)/$B$17)+1E-9,$B$21)) | F34: =MAX(0,FLOOR(MIN(3*$B$7*$B$14/$B$13,(C34-2*3*$B$8-$B$9-$B$22)/$B$17)+1E-9,$B$21)) | G34: =MAX(0,FLOOR(MIN(4*$B$7*$B$14/$B$13,(C34-2*4*$B$8-$B$9-$B$22)/$B$17)+1E-9,$B$21)) | H34: =MAX(0,FLOOR(MIN(5*$B$7*$B$14/$B$13,(C34-2*5*$B$8-$B$9-$B$22)/$B$17)+1E-9,$B$21)) | I34: =MAX(0,FLOOR(MIN(6*$B$7*$B$14/$B$13,(C34-2*6*$B$8-$B$9-$B$22)/$B$17)+1E-9,$B$21)) | J34: =MAX(0,FLOOR(MIN(7*$B$7*$B$14/$B$13,(C34-2*7*$B$8-$B$9-$B$22)/$B$17)+1E-9,$B$21)) | K34: =MAX(0,FLOOR(MIN(8*$B$7*$B$14/$B$13,(C34-2*8*$B$8-$B$9-$B$22)/$B$17)+1E-9,$B$21)) | L34: =MAX(0,FLOOR(MIN(9*$B$7*$B$14/$B$13,(C34-2*9*$B$8-$B$9-$B$22)/$B$17)+1E-9,$B$21)) | M34: =MAX(0,FLOOR(MIN(10*$B$7*$B$14/$B$13,(C34-2*10*$B$8-$B$9-$B$22)/$B$17)+1E-9,$B$21)) | N34: =IF(D34>0,(2*1*$B$8+$B$9+$B$22+$B$17*D34)*(1+$B$15)+$B$16,0) | O34: =IF(E34>0,(2*2*$B$8+$B$9+$B$22+$B$17*E34)*(1+$B$15)+$B$16,0) | P34: =IF(F34>0,(2*3*$B$8+$B$9+$B$22+$B$17*F34)*(1+$B$15)+$B$16,0) | Q34: =IF(G34>0,(2*4*$B$8+$B$9+$B$22+$B$17*G34)*(1+$B$15)+$B$16,0) | R34: =IF(H34>0,(2*5*$B$8+$B$9+$B$22+$B$17*H34)*(1+$B$15)+$B$16,0) | S34: =IF(I34>0,(2*6*$B$8+$B$9+$B$22+$B$17*I34)*(1+$B$15)+$B$16,0) | T34: =IF(J34>0,(2*7*$B$8+$B$9+$B$22+$B$17*J34)*(1+$B$15)+$B$16,0) | U34: =IF(K34>0,(2*8*$B$8+$B$9+$B$22+$B$17*K34)*(1+$B$15)+$B$16,0) | V34: =IF(L34>0,(2*9*$B$8+$B$9+$B$22+$B$17*L34)*(1+$B$15)+$B$16,0) | W34: =IF(M34>0,(2*10*$B$8+$B$9+$B$22+$B$17*M34)*(1+$B$15)+$B$16,0) | X34: =IF(D34>0,D34*($B$18-$B$19)-$B$20,0) | Y34: =IF(E34>0,E34*($B$18-$B$19)-$B$20,0) | Z34: =IF(F34>0,F34*($B$18-$B$19)-$B$20,0) | AA34: =IF(G34>0,G34*($B$18-$B$19)-$B$20,0) | AB34: =IF(H34>0,H34*($B$18-$B$19)-$B$20,0) | AC34: =IF(I34>0,I34*($B$18-$B$19)-$B$20,0) | AD34: =IF(J34>0,J34*($B$18-$B$19)-$B$20,0) | AE34: =IF(K34>0,K34*($B$18-$B$19)-$B$20,0) | ... AG34: =IF(M34>0,M34*($B$18-$B$19)-$B$20,0) | AH34: =IF(D34>0,X34/N34,-99) | AI34: =IF(E34>0,Y34/O34,-99) | AJ34: =IF(F34>0,Z34/P34,-99) | AK34: =IF(G34>0,AA34/Q34,-99) | AL34: =IF(H34>0,AB34/R34,-99) | AM34: =IF(I34>0,AC34/S34,-99) | AN34: =IF(J34>0,AD34/T34,-99) | AO34: =IF(K34>0,AE34/U34,-99) | ... AQ34: =IF(M34>0,AG34/W34,-99) | AR34: =MAX(AH34:AQ34) | AS34: =IF(AR34=-99,0,MATCH(AR34,AH34:AQ34,0)) | AT34: =IF(AS34=0,0,INDEX(D34:M34,AS34)) | AU34: =ROUND(AT34/$B$21,0) | AV34: =2*AS34 | AW34: =AT34*$B$13/$B$14 | AX34: =AW34*$B$14 | AY34: =AS34*$B$7 | AZ34: =ROUNDDOWN(AT34*1000/Rates!$D$27,0) | BA34: =IF(AS34=0,0,2*AS34*$B$8+$B$9) | BB34: =AW34*1000*$B$10 | BC34: =AT34*$B$11 | BD34: =AT34*$B$12 | BE34: =IF(AS34=0,0,$B$22) | BF34: =(BA34+BB34+BC34+BD34+BE34)*$B$15 | BG34: =IF(AS34=0,0,$B$16) | BH34: =BA34+BB34+BC34+BD34+BE34+BF34+BG34 | BI34: =A34-BH34 | BJ34: =AT34*$B$18 | BK34: =IF(AS34=0,0,AT34*$B$19+$B$20) | BL34: =BJ34-BK34 | BM34: =IF(BH34>0,BL34/BH34,0) | BN34: =IF(AS34=0,IF(A34>=$B$29,"RESERVOIR TEST ONLY: funds a doublet test, not a powered module","BELOW A DOUBLET: appraisal well at most"),IF(BL34<0,"Builds whole modules but contribution is negative",IF(AT34<Control!$B$12,"Operating break-even or better, below the 5 MW reference (not a return)","At/above the 5 MW reference (not a return)")))
A35: 200000000 | B35: =A35*$B$6 | C35: =MAX(0,(A35-$B$16)/(1+$B$15)) | D35: =MAX(0,FLOOR(MIN(1*$B$7*$B$14/$B$13,(C35-2*1*$B$8-$B$9-$B$22)/$B$17)+1E-9,$B$21)) | E35: =MAX(0,FLOOR(MIN(2*$B$7*$B$14/$B$13,(C35-2*2*$B$8-$B$9-$B$22)/$B$17)+1E-9,$B$21)) | F35: =MAX(0,FLOOR(MIN(3*$B$7*$B$14/$B$13,(C35-2*3*$B$8-$B$9-$B$22)/$B$17)+1E-9,$B$21)) | G35: =MAX(0,FLOOR(MIN(4*$B$7*$B$14/$B$13,(C35-2*4*$B$8-$B$9-$B$22)/$B$17)+1E-9,$B$21)) | H35: =MAX(0,FLOOR(MIN(5*$B$7*$B$14/$B$13,(C35-2*5*$B$8-$B$9-$B$22)/$B$17)+1E-9,$B$21)) | I35: =MAX(0,FLOOR(MIN(6*$B$7*$B$14/$B$13,(C35-2*6*$B$8-$B$9-$B$22)/$B$17)+1E-9,$B$21)) | J35: =MAX(0,FLOOR(MIN(7*$B$7*$B$14/$B$13,(C35-2*7*$B$8-$B$9-$B$22)/$B$17)+1E-9,$B$21)) | K35: =MAX(0,FLOOR(MIN(8*$B$7*$B$14/$B$13,(C35-2*8*$B$8-$B$9-$B$22)/$B$17)+1E-9,$B$21)) | L35: =MAX(0,FLOOR(MIN(9*$B$7*$B$14/$B$13,(C35-2*9*$B$8-$B$9-$B$22)/$B$17)+1E-9,$B$21)) | M35: =MAX(0,FLOOR(MIN(10*$B$7*$B$14/$B$13,(C35-2*10*$B$8-$B$9-$B$22)/$B$17)+1E-9,$B$21)) | N35: =IF(D35>0,(2*1*$B$8+$B$9+$B$22+$B$17*D35)*(1+$B$15)+$B$16,0) | O35: =IF(E35>0,(2*2*$B$8+$B$9+$B$22+$B$17*E35)*(1+$B$15)+$B$16,0) | P35: =IF(F35>0,(2*3*$B$8+$B$9+$B$22+$B$17*F35)*(1+$B$15)+$B$16,0) | Q35: =IF(G35>0,(2*4*$B$8+$B$9+$B$22+$B$17*G35)*(1+$B$15)+$B$16,0) | R35: =IF(H35>0,(2*5*$B$8+$B$9+$B$22+$B$17*H35)*(1+$B$15)+$B$16,0) | S35: =IF(I35>0,(2*6*$B$8+$B$9+$B$22+$B$17*I35)*(1+$B$15)+$B$16,0) | T35: =IF(J35>0,(2*7*$B$8+$B$9+$B$22+$B$17*J35)*(1+$B$15)+$B$16,0) | U35: =IF(K35>0,(2*8*$B$8+$B$9+$B$22+$B$17*K35)*(1+$B$15)+$B$16,0) | V35: =IF(L35>0,(2*9*$B$8+$B$9+$B$22+$B$17*L35)*(1+$B$15)+$B$16,0) | W35: =IF(M35>0,(2*10*$B$8+$B$9+$B$22+$B$17*M35)*(1+$B$15)+$B$16,0) | X35: =IF(D35>0,D35*($B$18-$B$19)-$B$20,0) | Y35: =IF(E35>0,E35*($B$18-$B$19)-$B$20,0) | Z35: =IF(F35>0,F35*($B$18-$B$19)-$B$20,0) | AA35: =IF(G35>0,G35*($B$18-$B$19)-$B$20,0) | AB35: =IF(H35>0,H35*($B$18-$B$19)-$B$20,0) | AC35: =IF(I35>0,I35*($B$18-$B$19)-$B$20,0) | AD35: =IF(J35>0,J35*($B$18-$B$19)-$B$20,0) | AE35: =IF(K35>0,K35*($B$18-$B$19)-$B$20,0) | ... AG35: =IF(M35>0,M35*($B$18-$B$19)-$B$20,0) | AH35: =IF(D35>0,X35/N35,-99) | AI35: =IF(E35>0,Y35/O35,-99) | AJ35: =IF(F35>0,Z35/P35,-99) | AK35: =IF(G35>0,AA35/Q35,-99) | AL35: =IF(H35>0,AB35/R35,-99) | AM35: =IF(I35>0,AC35/S35,-99) | AN35: =IF(J35>0,AD35/T35,-99) | AO35: =IF(K35>0,AE35/U35,-99) | ... AQ35: =IF(M35>0,AG35/W35,-99) | AR35: =MAX(AH35:AQ35) | AS35: =IF(AR35=-99,0,MATCH(AR35,AH35:AQ35,0)) | AT35: =IF(AS35=0,0,INDEX(D35:M35,AS35)) | AU35: =ROUND(AT35/$B$21,0) | AV35: =2*AS35 | AW35: =AT35*$B$13/$B$14 | AX35: =AW35*$B$14 | AY35: =AS35*$B$7 | AZ35: =ROUNDDOWN(AT35*1000/Rates!$D$27,0) | BA35: =IF(AS35=0,0,2*AS35*$B$8+$B$9) | BB35: =AW35*1000*$B$10 | BC35: =AT35*$B$11 | BD35: =AT35*$B$12 | BE35: =IF(AS35=0,0,$B$22) | BF35: =(BA35+BB35+BC35+BD35+BE35)*$B$15 | BG35: =IF(AS35=0,0,$B$16) | BH35: =BA35+BB35+BC35+BD35+BE35+BF35+BG35 | BI35: =A35-BH35 | BJ35: =AT35*$B$18 | BK35: =IF(AS35=0,0,AT35*$B$19+$B$20) | BL35: =BJ35-BK35 | BM35: =IF(BH35>0,BL35/BH35,0) | BN35: =IF(AS35=0,IF(A35>=$B$29,"RESERVOIR TEST ONLY: funds a doublet test, not a powered module","BELOW A DOUBLET: appraisal well at most"),IF(BL35<0,"Builds whole modules but contribution is negative",IF(AT35<Control!$B$12,"Operating break-even or better, below the 5 MW reference (not a return)","At/above the 5 MW reference (not a return)")))
A36: 250000000 | B36: =A36*$B$6 | C36: =MAX(0,(A36-$B$16)/(1+$B$15)) | D36: =MAX(0,FLOOR(MIN(1*$B$7*$B$14/$B$13,(C36-2*1*$B$8-$B$9-$B$22)/$B$17)+1E-9,$B$21)) | E36: =MAX(0,FLOOR(MIN(2*$B$7*$B$14/$B$13,(C36-2*2*$B$8-$B$9-$B$22)/$B$17)+1E-9,$B$21)) | F36: =MAX(0,FLOOR(MIN(3*$B$7*$B$14/$B$13,(C36-2*3*$B$8-$B$9-$B$22)/$B$17)+1E-9,$B$21)) | G36: =MAX(0,FLOOR(MIN(4*$B$7*$B$14/$B$13,(C36-2*4*$B$8-$B$9-$B$22)/$B$17)+1E-9,$B$21)) | H36: =MAX(0,FLOOR(MIN(5*$B$7*$B$14/$B$13,(C36-2*5*$B$8-$B$9-$B$22)/$B$17)+1E-9,$B$21)) | I36: =MAX(0,FLOOR(MIN(6*$B$7*$B$14/$B$13,(C36-2*6*$B$8-$B$9-$B$22)/$B$17)+1E-9,$B$21)) | J36: =MAX(0,FLOOR(MIN(7*$B$7*$B$14/$B$13,(C36-2*7*$B$8-$B$9-$B$22)/$B$17)+1E-9,$B$21)) | K36: =MAX(0,FLOOR(MIN(8*$B$7*$B$14/$B$13,(C36-2*8*$B$8-$B$9-$B$22)/$B$17)+1E-9,$B$21)) | L36: =MAX(0,FLOOR(MIN(9*$B$7*$B$14/$B$13,(C36-2*9*$B$8-$B$9-$B$22)/$B$17)+1E-9,$B$21)) | M36: =MAX(0,FLOOR(MIN(10*$B$7*$B$14/$B$13,(C36-2*10*$B$8-$B$9-$B$22)/$B$17)+1E-9,$B$21)) | N36: =IF(D36>0,(2*1*$B$8+$B$9+$B$22+$B$17*D36)*(1+$B$15)+$B$16,0) | O36: =IF(E36>0,(2*2*$B$8+$B$9+$B$22+$B$17*E36)*(1+$B$15)+$B$16,0) | P36: =IF(F36>0,(2*3*$B$8+$B$9+$B$22+$B$17*F36)*(1+$B$15)+$B$16,0) | Q36: =IF(G36>0,(2*4*$B$8+$B$9+$B$22+$B$17*G36)*(1+$B$15)+$B$16,0) | R36: =IF(H36>0,(2*5*$B$8+$B$9+$B$22+$B$17*H36)*(1+$B$15)+$B$16,0) | S36: =IF(I36>0,(2*6*$B$8+$B$9+$B$22+$B$17*I36)*(1+$B$15)+$B$16,0) | T36: =IF(J36>0,(2*7*$B$8+$B$9+$B$22+$B$17*J36)*(1+$B$15)+$B$16,0) | U36: =IF(K36>0,(2*8*$B$8+$B$9+$B$22+$B$17*K36)*(1+$B$15)+$B$16,0) | V36: =IF(L36>0,(2*9*$B$8+$B$9+$B$22+$B$17*L36)*(1+$B$15)+$B$16,0) | W36: =IF(M36>0,(2*10*$B$8+$B$9+$B$22+$B$17*M36)*(1+$B$15)+$B$16,0) | X36: =IF(D36>0,D36*($B$18-$B$19)-$B$20,0) | Y36: =IF(E36>0,E36*($B$18-$B$19)-$B$20,0) | Z36: =IF(F36>0,F36*($B$18-$B$19)-$B$20,0) | AA36: =IF(G36>0,G36*($B$18-$B$19)-$B$20,0) | AB36: =IF(H36>0,H36*($B$18-$B$19)-$B$20,0) | AC36: =IF(I36>0,I36*($B$18-$B$19)-$B$20,0) | AD36: =IF(J36>0,J36*($B$18-$B$19)-$B$20,0) | AE36: =IF(K36>0,K36*($B$18-$B$19)-$B$20,0) | ... AG36: =IF(M36>0,M36*($B$18-$B$19)-$B$20,0) | AH36: =IF(D36>0,X36/N36,-99) | AI36: =IF(E36>0,Y36/O36,-99) | AJ36: =IF(F36>0,Z36/P36,-99) | AK36: =IF(G36>0,AA36/Q36,-99) | AL36: =IF(H36>0,AB36/R36,-99) | AM36: =IF(I36>0,AC36/S36,-99) | AN36: =IF(J36>0,AD36/T36,-99) | AO36: =IF(K36>0,AE36/U36,-99) | ... AQ36: =IF(M36>0,AG36/W36,-99) | AR36: =MAX(AH36:AQ36) | AS36: =IF(AR36=-99,0,MATCH(AR36,AH36:AQ36,0)) | AT36: =IF(AS36=0,0,INDEX(D36:M36,AS36)) | AU36: =ROUND(AT36/$B$21,0) | AV36: =2*AS36 | AW36: =AT36*$B$13/$B$14 | AX36: =AW36*$B$14 | AY36: =AS36*$B$7 | AZ36: =ROUNDDOWN(AT36*1000/Rates!$D$27,0) | BA36: =IF(AS36=0,0,2*AS36*$B$8+$B$9) | BB36: =AW36*1000*$B$10 | BC36: =AT36*$B$11 | BD36: =AT36*$B$12 | BE36: =IF(AS36=0,0,$B$22) | BF36: =(BA36+BB36+BC36+BD36+BE36)*$B$15 | BG36: =IF(AS36=0,0,$B$16) | BH36: =BA36+BB36+BC36+BD36+BE36+BF36+BG36 | BI36: =A36-BH36 | BJ36: =AT36*$B$18 | BK36: =IF(AS36=0,0,AT36*$B$19+$B$20) | BL36: =BJ36-BK36 | BM36: =IF(BH36>0,BL36/BH36,0) | BN36: =IF(AS36=0,IF(A36>=$B$29,"RESERVOIR TEST ONLY: funds a doublet test, not a powered module","BELOW A DOUBLET: appraisal well at most"),IF(BL36<0,"Builds whole modules but contribution is negative",IF(AT36<Control!$B$12,"Operating break-even or better, below the 5 MW reference (not a return)","At/above the 5 MW reference (not a return)")))
A37: 300000000 | B37: =A37*$B$6 | C37: =MAX(0,(A37-$B$16)/(1+$B$15)) | D37: =MAX(0,FLOOR(MIN(1*$B$7*$B$14/$B$13,(C37-2*1*$B$8-$B$9-$B$22)/$B$17)+1E-9,$B$21)) | E37: =MAX(0,FLOOR(MIN(2*$B$7*$B$14/$B$13,(C37-2*2*$B$8-$B$9-$B$22)/$B$17)+1E-9,$B$21)) | F37: =MAX(0,FLOOR(MIN(3*$B$7*$B$14/$B$13,(C37-2*3*$B$8-$B$9-$B$22)/$B$17)+1E-9,$B$21)) | G37: =MAX(0,FLOOR(MIN(4*$B$7*$B$14/$B$13,(C37-2*4*$B$8-$B$9-$B$22)/$B$17)+1E-9,$B$21)) | H37: =MAX(0,FLOOR(MIN(5*$B$7*$B$14/$B$13,(C37-2*5*$B$8-$B$9-$B$22)/$B$17)+1E-9,$B$21)) | I37: =MAX(0,FLOOR(MIN(6*$B$7*$B$14/$B$13,(C37-2*6*$B$8-$B$9-$B$22)/$B$17)+1E-9,$B$21)) | J37: =MAX(0,FLOOR(MIN(7*$B$7*$B$14/$B$13,(C37-2*7*$B$8-$B$9-$B$22)/$B$17)+1E-9,$B$21)) | K37: =MAX(0,FLOOR(MIN(8*$B$7*$B$14/$B$13,(C37-2*8*$B$8-$B$9-$B$22)/$B$17)+1E-9,$B$21)) | L37: =MAX(0,FLOOR(MIN(9*$B$7*$B$14/$B$13,(C37-2*9*$B$8-$B$9-$B$22)/$B$17)+1E-9,$B$21)) | M37: =MAX(0,FLOOR(MIN(10*$B$7*$B$14/$B$13,(C37-2*10*$B$8-$B$9-$B$22)/$B$17)+1E-9,$B$21)) | N37: =IF(D37>0,(2*1*$B$8+$B$9+$B$22+$B$17*D37)*(1+$B$15)+$B$16,0) | O37: =IF(E37>0,(2*2*$B$8+$B$9+$B$22+$B$17*E37)*(1+$B$15)+$B$16,0) | P37: =IF(F37>0,(2*3*$B$8+$B$9+$B$22+$B$17*F37)*(1+$B$15)+$B$16,0) | Q37: =IF(G37>0,(2*4*$B$8+$B$9+$B$22+$B$17*G37)*(1+$B$15)+$B$16,0) | R37: =IF(H37>0,(2*5*$B$8+$B$9+$B$22+$B$17*H37)*(1+$B$15)+$B$16,0) | S37: =IF(I37>0,(2*6*$B$8+$B$9+$B$22+$B$17*I37)*(1+$B$15)+$B$16,0) | T37: =IF(J37>0,(2*7*$B$8+$B$9+$B$22+$B$17*J37)*(1+$B$15)+$B$16,0) | U37: =IF(K37>0,(2*8*$B$8+$B$9+$B$22+$B$17*K37)*(1+$B$15)+$B$16,0) | V37: =IF(L37>0,(2*9*$B$8+$B$9+$B$22+$B$17*L37)*(1+$B$15)+$B$16,0) | W37: =IF(M37>0,(2*10*$B$8+$B$9+$B$22+$B$17*M37)*(1+$B$15)+$B$16,0) | X37: =IF(D37>0,D37*($B$18-$B$19)-$B$20,0) | Y37: =IF(E37>0,E37*($B$18-$B$19)-$B$20,0) | Z37: =IF(F37>0,F37*($B$18-$B$19)-$B$20,0) | AA37: =IF(G37>0,G37*($B$18-$B$19)-$B$20,0) | AB37: =IF(H37>0,H37*($B$18-$B$19)-$B$20,0) | AC37: =IF(I37>0,I37*($B$18-$B$19)-$B$20,0) | AD37: =IF(J37>0,J37*($B$18-$B$19)-$B$20,0) | AE37: =IF(K37>0,K37*($B$18-$B$19)-$B$20,0) | ... AG37: =IF(M37>0,M37*($B$18-$B$19)-$B$20,0) | AH37: =IF(D37>0,X37/N37,-99) | AI37: =IF(E37>0,Y37/O37,-99) | AJ37: =IF(F37>0,Z37/P37,-99) | AK37: =IF(G37>0,AA37/Q37,-99) | AL37: =IF(H37>0,AB37/R37,-99) | AM37: =IF(I37>0,AC37/S37,-99) | AN37: =IF(J37>0,AD37/T37,-99) | AO37: =IF(K37>0,AE37/U37,-99) | ... AQ37: =IF(M37>0,AG37/W37,-99) | AR37: =MAX(AH37:AQ37) | AS37: =IF(AR37=-99,0,MATCH(AR37,AH37:AQ37,0)) | AT37: =IF(AS37=0,0,INDEX(D37:M37,AS37)) | AU37: =ROUND(AT37/$B$21,0) | AV37: =2*AS37 | AW37: =AT37*$B$13/$B$14 | AX37: =AW37*$B$14 | AY37: =AS37*$B$7 | AZ37: =ROUNDDOWN(AT37*1000/Rates!$D$27,0) | BA37: =IF(AS37=0,0,2*AS37*$B$8+$B$9) | BB37: =AW37*1000*$B$10 | BC37: =AT37*$B$11 | BD37: =AT37*$B$12 | BE37: =IF(AS37=0,0,$B$22) | BF37: =(BA37+BB37+BC37+BD37+BE37)*$B$15 | BG37: =IF(AS37=0,0,$B$16) | BH37: =BA37+BB37+BC37+BD37+BE37+BF37+BG37 | BI37: =A37-BH37 | BJ37: =AT37*$B$18 | BK37: =IF(AS37=0,0,AT37*$B$19+$B$20) | BL37: =BJ37-BK37 | BM37: =IF(BH37>0,BL37/BH37,0) | BN37: =IF(AS37=0,IF(A37>=$B$29,"RESERVOIR TEST ONLY: funds a doublet test, not a powered module","BELOW A DOUBLET: appraisal well at most"),IF(BL37<0,"Builds whole modules but contribution is negative",IF(AT37<Control!$B$12,"Operating break-even or better, below the 5 MW reference (not a return)","At/above the 5 MW reference (not a return)")))
A38: 350000000 | B38: =A38*$B$6 | C38: =MAX(0,(A38-$B$16)/(1+$B$15)) | D38: =MAX(0,FLOOR(MIN(1*$B$7*$B$14/$B$13,(C38-2*1*$B$8-$B$9-$B$22)/$B$17)+1E-9,$B$21)) | E38: =MAX(0,FLOOR(MIN(2*$B$7*$B$14/$B$13,(C38-2*2*$B$8-$B$9-$B$22)/$B$17)+1E-9,$B$21)) | F38: =MAX(0,FLOOR(MIN(3*$B$7*$B$14/$B$13,(C38-2*3*$B$8-$B$9-$B$22)/$B$17)+1E-9,$B$21)) | G38: =MAX(0,FLOOR(MIN(4*$B$7*$B$14/$B$13,(C38-2*4*$B$8-$B$9-$B$22)/$B$17)+1E-9,$B$21)) | H38: =MAX(0,FLOOR(MIN(5*$B$7*$B$14/$B$13,(C38-2*5*$B$8-$B$9-$B$22)/$B$17)+1E-9,$B$21)) | I38: =MAX(0,FLOOR(MIN(6*$B$7*$B$14/$B$13,(C38-2*6*$B$8-$B$9-$B$22)/$B$17)+1E-9,$B$21)) | J38: =MAX(0,FLOOR(MIN(7*$B$7*$B$14/$B$13,(C38-2*7*$B$8-$B$9-$B$22)/$B$17)+1E-9,$B$21)) | K38: =MAX(0,FLOOR(MIN(8*$B$7*$B$14/$B$13,(C38-2*8*$B$8-$B$9-$B$22)/$B$17)+1E-9,$B$21)) | L38: =MAX(0,FLOOR(MIN(9*$B$7*$B$14/$B$13,(C38-2*9*$B$8-$B$9-$B$22)/$B$17)+1E-9,$B$21)) | M38: =MAX(0,FLOOR(MIN(10*$B$7*$B$14/$B$13,(C38-2*10*$B$8-$B$9-$B$22)/$B$17)+1E-9,$B$21)) | N38: =IF(D38>0,(2*1*$B$8+$B$9+$B$22+$B$17*D38)*(1+$B$15)+$B$16,0) | O38: =IF(E38>0,(2*2*$B$8+$B$9+$B$22+$B$17*E38)*(1+$B$15)+$B$16,0) | P38: =IF(F38>0,(2*3*$B$8+$B$9+$B$22+$B$17*F38)*(1+$B$15)+$B$16,0) | Q38: =IF(G38>0,(2*4*$B$8+$B$9+$B$22+$B$17*G38)*(1+$B$15)+$B$16,0) | R38: =IF(H38>0,(2*5*$B$8+$B$9+$B$22+$B$17*H38)*(1+$B$15)+$B$16,0) | S38: =IF(I38>0,(2*6*$B$8+$B$9+$B$22+$B$17*I38)*(1+$B$15)+$B$16,0) | T38: =IF(J38>0,(2*7*$B$8+$B$9+$B$22+$B$17*J38)*(1+$B$15)+$B$16,0) | U38: =IF(K38>0,(2*8*$B$8+$B$9+$B$22+$B$17*K38)*(1+$B$15)+$B$16,0) | V38: =IF(L38>0,(2*9*$B$8+$B$9+$B$22+$B$17*L38)*(1+$B$15)+$B$16,0) | W38: =IF(M38>0,(2*10*$B$8+$B$9+$B$22+$B$17*M38)*(1+$B$15)+$B$16,0) | X38: =IF(D38>0,D38*($B$18-$B$19)-$B$20,0) | Y38: =IF(E38>0,E38*($B$18-$B$19)-$B$20,0) | Z38: =IF(F38>0,F38*($B$18-$B$19)-$B$20,0) | AA38: =IF(G38>0,G38*($B$18-$B$19)-$B$20,0) | AB38: =IF(H38>0,H38*($B$18-$B$19)-$B$20,0) | AC38: =IF(I38>0,I38*($B$18-$B$19)-$B$20,0) | AD38: =IF(J38>0,J38*($B$18-$B$19)-$B$20,0) | AE38: =IF(K38>0,K38*($B$18-$B$19)-$B$20,0) | ... AG38: =IF(M38>0,M38*($B$18-$B$19)-$B$20,0) | AH38: =IF(D38>0,X38/N38,-99) | AI38: =IF(E38>0,Y38/O38,-99) | AJ38: =IF(F38>0,Z38/P38,-99) | AK38: =IF(G38>0,AA38/Q38,-99) | AL38: =IF(H38>0,AB38/R38,-99) | AM38: =IF(I38>0,AC38/S38,-99) | AN38: =IF(J38>0,AD38/T38,-99) | AO38: =IF(K38>0,AE38/U38,-99) | ... AQ38: =IF(M38>0,AG38/W38,-99) | AR38: =MAX(AH38:AQ38) | AS38: =IF(AR38=-99,0,MATCH(AR38,AH38:AQ38,0)) | AT38: =IF(AS38=0,0,INDEX(D38:M38,AS38)) | AU38: =ROUND(AT38/$B$21,0) | AV38: =2*AS38 | AW38: =AT38*$B$13/$B$14 | AX38: =AW38*$B$14 | AY38: =AS38*$B$7 | AZ38: =ROUNDDOWN(AT38*1000/Rates!$D$27,0) | BA38: =IF(AS38=0,0,2*AS38*$B$8+$B$9) | BB38: =AW38*1000*$B$10 | BC38: =AT38*$B$11 | BD38: =AT38*$B$12 | BE38: =IF(AS38=0,0,$B$22) | BF38: =(BA38+BB38+BC38+BD38+BE38)*$B$15 | BG38: =IF(AS38=0,0,$B$16) | BH38: =BA38+BB38+BC38+BD38+BE38+BF38+BG38 | BI38: =A38-BH38 | BJ38: =AT38*$B$18 | BK38: =IF(AS38=0,0,AT38*$B$19+$B$20) | BL38: =BJ38-BK38 | BM38: =IF(BH38>0,BL38/BH38,0) | BN38: =IF(AS38=0,IF(A38>=$B$29,"RESERVOIR TEST ONLY: funds a doublet test, not a powered module","BELOW A DOUBLET: appraisal well at most"),IF(BL38<0,"Builds whole modules but contribution is negative",IF(AT38<Control!$B$12,"Operating break-even or better, below the 5 MW reference (not a return)","At/above the 5 MW reference (not a return)")))
A39: 400000000 | B39: =A39*$B$6 | C39: =MAX(0,(A39-$B$16)/(1+$B$15)) | D39: =MAX(0,FLOOR(MIN(1*$B$7*$B$14/$B$13,(C39-2*1*$B$8-$B$9-$B$22)/$B$17)+1E-9,$B$21)) | E39: =MAX(0,FLOOR(MIN(2*$B$7*$B$14/$B$13,(C39-2*2*$B$8-$B$9-$B$22)/$B$17)+1E-9,$B$21)) | F39: =MAX(0,FLOOR(MIN(3*$B$7*$B$14/$B$13,(C39-2*3*$B$8-$B$9-$B$22)/$B$17)+1E-9,$B$21)) | G39: =MAX(0,FLOOR(MIN(4*$B$7*$B$14/$B$13,(C39-2*4*$B$8-$B$9-$B$22)/$B$17)+1E-9,$B$21)) | H39: =MAX(0,FLOOR(MIN(5*$B$7*$B$14/$B$13,(C39-2*5*$B$8-$B$9-$B$22)/$B$17)+1E-9,$B$21)) | I39: =MAX(0,FLOOR(MIN(6*$B$7*$B$14/$B$13,(C39-2*6*$B$8-$B$9-$B$22)/$B$17)+1E-9,$B$21)) | J39: =MAX(0,FLOOR(MIN(7*$B$7*$B$14/$B$13,(C39-2*7*$B$8-$B$9-$B$22)/$B$17)+1E-9,$B$21)) | K39: =MAX(0,FLOOR(MIN(8*$B$7*$B$14/$B$13,(C39-2*8*$B$8-$B$9-$B$22)/$B$17)+1E-9,$B$21)) | L39: =MAX(0,FLOOR(MIN(9*$B$7*$B$14/$B$13,(C39-2*9*$B$8-$B$9-$B$22)/$B$17)+1E-9,$B$21)) | M39: =MAX(0,FLOOR(MIN(10*$B$7*$B$14/$B$13,(C39-2*10*$B$8-$B$9-$B$22)/$B$17)+1E-9,$B$21)) | N39: =IF(D39>0,(2*1*$B$8+$B$9+$B$22+$B$17*D39)*(1+$B$15)+$B$16,0) | O39: =IF(E39>0,(2*2*$B$8+$B$9+$B$22+$B$17*E39)*(1+$B$15)+$B$16,0) | P39: =IF(F39>0,(2*3*$B$8+$B$9+$B$22+$B$17*F39)*(1+$B$15)+$B$16,0) | Q39: =IF(G39>0,(2*4*$B$8+$B$9+$B$22+$B$17*G39)*(1+$B$15)+$B$16,0) | R39: =IF(H39>0,(2*5*$B$8+$B$9+$B$22+$B$17*H39)*(1+$B$15)+$B$16,0) | S39: =IF(I39>0,(2*6*$B$8+$B$9+$B$22+$B$17*I39)*(1+$B$15)+$B$16,0) | T39: =IF(J39>0,(2*7*$B$8+$B$9+$B$22+$B$17*J39)*(1+$B$15)+$B$16,0) | U39: =IF(K39>0,(2*8*$B$8+$B$9+$B$22+$B$17*K39)*(1+$B$15)+$B$16,0) | V39: =IF(L39>0,(2*9*$B$8+$B$9+$B$22+$B$17*L39)*(1+$B$15)+$B$16,0) | W39: =IF(M39>0,(2*10*$B$8+$B$9+$B$22+$B$17*M39)*(1+$B$15)+$B$16,0) | X39: =IF(D39>0,D39*($B$18-$B$19)-$B$20,0) | Y39: =IF(E39>0,E39*($B$18-$B$19)-$B$20,0) | Z39: =IF(F39>0,F39*($B$18-$B$19)-$B$20,0) | AA39: =IF(G39>0,G39*($B$18-$B$19)-$B$20,0) | AB39: =IF(H39>0,H39*($B$18-$B$19)-$B$20,0) | AC39: =IF(I39>0,I39*($B$18-$B$19)-$B$20,0) | AD39: =IF(J39>0,J39*($B$18-$B$19)-$B$20,0) | AE39: =IF(K39>0,K39*($B$18-$B$19)-$B$20,0) | ... AG39: =IF(M39>0,M39*($B$18-$B$19)-$B$20,0) | AH39: =IF(D39>0,X39/N39,-99) | AI39: =IF(E39>0,Y39/O39,-99) | AJ39: =IF(F39>0,Z39/P39,-99) | AK39: =IF(G39>0,AA39/Q39,-99) | AL39: =IF(H39>0,AB39/R39,-99) | AM39: =IF(I39>0,AC39/S39,-99) | AN39: =IF(J39>0,AD39/T39,-99) | AO39: =IF(K39>0,AE39/U39,-99) | ... AQ39: =IF(M39>0,AG39/W39,-99) | AR39: =MAX(AH39:AQ39) | AS39: =IF(AR39=-99,0,MATCH(AR39,AH39:AQ39,0)) | AT39: =IF(AS39=0,0,INDEX(D39:M39,AS39)) | AU39: =ROUND(AT39/$B$21,0) | AV39: =2*AS39 | AW39: =AT39*$B$13/$B$14 | AX39: =AW39*$B$14 | AY39: =AS39*$B$7 | AZ39: =ROUNDDOWN(AT39*1000/Rates!$D$27,0) | BA39: =IF(AS39=0,0,2*AS39*$B$8+$B$9) | BB39: =AW39*1000*$B$10 | BC39: =AT39*$B$11 | BD39: =AT39*$B$12 | BE39: =IF(AS39=0,0,$B$22) | BF39: =(BA39+BB39+BC39+BD39+BE39)*$B$15 | BG39: =IF(AS39=0,0,$B$16) | BH39: =BA39+BB39+BC39+BD39+BE39+BF39+BG39 | BI39: =A39-BH39 | BJ39: =AT39*$B$18 | BK39: =IF(AS39=0,0,AT39*$B$19+$B$20) | BL39: =BJ39-BK39 | BM39: =IF(BH39>0,BL39/BH39,0) | BN39: =IF(AS39=0,IF(A39>=$B$29,"RESERVOIR TEST ONLY: funds a doublet test, not a powered module","BELOW A DOUBLET: appraisal well at most"),IF(BL39<0,"Builds whole modules but contribution is negative",IF(AT39<Control!$B$12,"Operating break-even or better, below the 5 MW reference (not a return)","At/above the 5 MW reference (not a return)")))
A40: 450000000 | B40: =A40*$B$6 | C40: =MAX(0,(A40-$B$16)/(1+$B$15)) | D40: =MAX(0,FLOOR(MIN(1*$B$7*$B$14/$B$13,(C40-2*1*$B$8-$B$9-$B$22)/$B$17)+1E-9,$B$21)) | E40: =MAX(0,FLOOR(MIN(2*$B$7*$B$14/$B$13,(C40-2*2*$B$8-$B$9-$B$22)/$B$17)+1E-9,$B$21)) | F40: =MAX(0,FLOOR(MIN(3*$B$7*$B$14/$B$13,(C40-2*3*$B$8-$B$9-$B$22)/$B$17)+1E-9,$B$21)) | G40: =MAX(0,FLOOR(MIN(4*$B$7*$B$14/$B$13,(C40-2*4*$B$8-$B$9-$B$22)/$B$17)+1E-9,$B$21)) | H40: =MAX(0,FLOOR(MIN(5*$B$7*$B$14/$B$13,(C40-2*5*$B$8-$B$9-$B$22)/$B$17)+1E-9,$B$21)) | I40: =MAX(0,FLOOR(MIN(6*$B$7*$B$14/$B$13,(C40-2*6*$B$8-$B$9-$B$22)/$B$17)+1E-9,$B$21)) | J40: =MAX(0,FLOOR(MIN(7*$B$7*$B$14/$B$13,(C40-2*7*$B$8-$B$9-$B$22)/$B$17)+1E-9,$B$21)) | K40: =MAX(0,FLOOR(MIN(8*$B$7*$B$14/$B$13,(C40-2*8*$B$8-$B$9-$B$22)/$B$17)+1E-9,$B$21)) | L40: =MAX(0,FLOOR(MIN(9*$B$7*$B$14/$B$13,(C40-2*9*$B$8-$B$9-$B$22)/$B$17)+1E-9,$B$21)) | M40: =MAX(0,FLOOR(MIN(10*$B$7*$B$14/$B$13,(C40-2*10*$B$8-$B$9-$B$22)/$B$17)+1E-9,$B$21)) | N40: =IF(D40>0,(2*1*$B$8+$B$9+$B$22+$B$17*D40)*(1+$B$15)+$B$16,0) | O40: =IF(E40>0,(2*2*$B$8+$B$9+$B$22+$B$17*E40)*(1+$B$15)+$B$16,0) | P40: =IF(F40>0,(2*3*$B$8+$B$9+$B$22+$B$17*F40)*(1+$B$15)+$B$16,0) | Q40: =IF(G40>0,(2*4*$B$8+$B$9+$B$22+$B$17*G40)*(1+$B$15)+$B$16,0) | R40: =IF(H40>0,(2*5*$B$8+$B$9+$B$22+$B$17*H40)*(1+$B$15)+$B$16,0) | S40: =IF(I40>0,(2*6*$B$8+$B$9+$B$22+$B$17*I40)*(1+$B$15)+$B$16,0) | T40: =IF(J40>0,(2*7*$B$8+$B$9+$B$22+$B$17*J40)*(1+$B$15)+$B$16,0) | U40: =IF(K40>0,(2*8*$B$8+$B$9+$B$22+$B$17*K40)*(1+$B$15)+$B$16,0) | V40: =IF(L40>0,(2*9*$B$8+$B$9+$B$22+$B$17*L40)*(1+$B$15)+$B$16,0) | W40: =IF(M40>0,(2*10*$B$8+$B$9+$B$22+$B$17*M40)*(1+$B$15)+$B$16,0) | X40: =IF(D40>0,D40*($B$18-$B$19)-$B$20,0) | Y40: =IF(E40>0,E40*($B$18-$B$19)-$B$20,0) | Z40: =IF(F40>0,F40*($B$18-$B$19)-$B$20,0) | AA40: =IF(G40>0,G40*($B$18-$B$19)-$B$20,0) | AB40: =IF(H40>0,H40*($B$18-$B$19)-$B$20,0) | AC40: =IF(I40>0,I40*($B$18-$B$19)-$B$20,0) | AD40: =IF(J40>0,J40*($B$18-$B$19)-$B$20,0) | AE40: =IF(K40>0,K40*($B$18-$B$19)-$B$20,0) | ... AG40: =IF(M40>0,M40*($B$18-$B$19)-$B$20,0) | AH40: =IF(D40>0,X40/N40,-99) | AI40: =IF(E40>0,Y40/O40,-99) | AJ40: =IF(F40>0,Z40/P40,-99) | AK40: =IF(G40>0,AA40/Q40,-99) | AL40: =IF(H40>0,AB40/R40,-99) | AM40: =IF(I40>0,AC40/S40,-99) | AN40: =IF(J40>0,AD40/T40,-99) | AO40: =IF(K40>0,AE40/U40,-99) | ... AQ40: =IF(M40>0,AG40/W40,-99) | AR40: =MAX(AH40:AQ40) | AS40: =IF(AR40=-99,0,MATCH(AR40,AH40:AQ40,0)) | AT40: =IF(AS40=0,0,INDEX(D40:M40,AS40)) | AU40: =ROUND(AT40/$B$21,0) | AV40: =2*AS40 | AW40: =AT40*$B$13/$B$14 | AX40: =AW40*$B$14 | AY40: =AS40*$B$7 | AZ40: =ROUNDDOWN(AT40*1000/Rates!$D$27,0) | BA40: =IF(AS40=0,0,2*AS40*$B$8+$B$9) | BB40: =AW40*1000*$B$10 | BC40: =AT40*$B$11 | BD40: =AT40*$B$12 | BE40: =IF(AS40=0,0,$B$22) | BF40: =(BA40+BB40+BC40+BD40+BE40)*$B$15 | BG40: =IF(AS40=0,0,$B$16) | BH40: =BA40+BB40+BC40+BD40+BE40+BF40+BG40 | BI40: =A40-BH40 | BJ40: =AT40*$B$18 | BK40: =IF(AS40=0,0,AT40*$B$19+$B$20) | BL40: =BJ40-BK40 | BM40: =IF(BH40>0,BL40/BH40,0) | BN40: =IF(AS40=0,IF(A40>=$B$29,"RESERVOIR TEST ONLY: funds a doublet test, not a powered module","BELOW A DOUBLET: appraisal well at most"),IF(BL40<0,"Builds whole modules but contribution is negative",IF(AT40<Control!$B$12,"Operating break-even or better, below the 5 MW reference (not a return)","At/above the 5 MW reference (not a return)")))
A41: 500000000 | B41: =A41*$B$6 | C41: =MAX(0,(A41-$B$16)/(1+$B$15)) | D41: =MAX(0,FLOOR(MIN(1*$B$7*$B$14/$B$13,(C41-2*1*$B$8-$B$9-$B$22)/$B$17)+1E-9,$B$21)) | E41: =MAX(0,FLOOR(MIN(2*$B$7*$B$14/$B$13,(C41-2*2*$B$8-$B$9-$B$22)/$B$17)+1E-9,$B$21)) | F41: =MAX(0,FLOOR(MIN(3*$B$7*$B$14/$B$13,(C41-2*3*$B$8-$B$9-$B$22)/$B$17)+1E-9,$B$21)) | G41: =MAX(0,FLOOR(MIN(4*$B$7*$B$14/$B$13,(C41-2*4*$B$8-$B$9-$B$22)/$B$17)+1E-9,$B$21)) | H41: =MAX(0,FLOOR(MIN(5*$B$7*$B$14/$B$13,(C41-2*5*$B$8-$B$9-$B$22)/$B$17)+1E-9,$B$21)) | I41: =MAX(0,FLOOR(MIN(6*$B$7*$B$14/$B$13,(C41-2*6*$B$8-$B$9-$B$22)/$B$17)+1E-9,$B$21)) | J41: =MAX(0,FLOOR(MIN(7*$B$7*$B$14/$B$13,(C41-2*7*$B$8-$B$9-$B$22)/$B$17)+1E-9,$B$21)) | K41: =MAX(0,FLOOR(MIN(8*$B$7*$B$14/$B$13,(C41-2*8*$B$8-$B$9-$B$22)/$B$17)+1E-9,$B$21)) | L41: =MAX(0,FLOOR(MIN(9*$B$7*$B$14/$B$13,(C41-2*9*$B$8-$B$9-$B$22)/$B$17)+1E-9,$B$21)) | M41: =MAX(0,FLOOR(MIN(10*$B$7*$B$14/$B$13,(C41-2*10*$B$8-$B$9-$B$22)/$B$17)+1E-9,$B$21)) | N41: =IF(D41>0,(2*1*$B$8+$B$9+$B$22+$B$17*D41)*(1+$B$15)+$B$16,0) | O41: =IF(E41>0,(2*2*$B$8+$B$9+$B$22+$B$17*E41)*(1+$B$15)+$B$16,0) | P41: =IF(F41>0,(2*3*$B$8+$B$9+$B$22+$B$17*F41)*(1+$B$15)+$B$16,0) | Q41: =IF(G41>0,(2*4*$B$8+$B$9+$B$22+$B$17*G41)*(1+$B$15)+$B$16,0) | R41: =IF(H41>0,(2*5*$B$8+$B$9+$B$22+$B$17*H41)*(1+$B$15)+$B$16,0) | S41: =IF(I41>0,(2*6*$B$8+$B$9+$B$22+$B$17*I41)*(1+$B$15)+$B$16,0) | T41: =IF(J41>0,(2*7*$B$8+$B$9+$B$22+$B$17*J41)*(1+$B$15)+$B$16,0) | U41: =IF(K41>0,(2*8*$B$8+$B$9+$B$22+$B$17*K41)*(1+$B$15)+$B$16,0) | V41: =IF(L41>0,(2*9*$B$8+$B$9+$B$22+$B$17*L41)*(1+$B$15)+$B$16,0) | W41: =IF(M41>0,(2*10*$B$8+$B$9+$B$22+$B$17*M41)*(1+$B$15)+$B$16,0) | X41: =IF(D41>0,D41*($B$18-$B$19)-$B$20,0) | Y41: =IF(E41>0,E41*($B$18-$B$19)-$B$20,0) | Z41: =IF(F41>0,F41*($B$18-$B$19)-$B$20,0) | AA41: =IF(G41>0,G41*($B$18-$B$19)-$B$20,0) | AB41: =IF(H41>0,H41*($B$18-$B$19)-$B$20,0) | AC41: =IF(I41>0,I41*($B$18-$B$19)-$B$20,0) | AD41: =IF(J41>0,J41*($B$18-$B$19)-$B$20,0) | AE41: =IF(K41>0,K41*($B$18-$B$19)-$B$20,0) | ... AG41: =IF(M41>0,M41*($B$18-$B$19)-$B$20,0) | AH41: =IF(D41>0,X41/N41,-99) | AI41: =IF(E41>0,Y41/O41,-99) | AJ41: =IF(F41>0,Z41/P41,-99) | AK41: =IF(G41>0,AA41/Q41,-99) | AL41: =IF(H41>0,AB41/R41,-99) | AM41: =IF(I41>0,AC41/S41,-99) | AN41: =IF(J41>0,AD41/T41,-99) | AO41: =IF(K41>0,AE41/U41,-99) | ... AQ41: =IF(M41>0,AG41/W41,-99) | AR41: =MAX(AH41:AQ41) | AS41: =IF(AR41=-99,0,MATCH(AR41,AH41:AQ41,0)) | AT41: =IF(AS41=0,0,INDEX(D41:M41,AS41)) | AU41: =ROUND(AT41/$B$21,0) | AV41: =2*AS41 | AW41: =AT41*$B$13/$B$14 | AX41: =AW41*$B$14 | AY41: =AS41*$B$7 | AZ41: =ROUNDDOWN(AT41*1000/Rates!$D$27,0) | BA41: =IF(AS41=0,0,2*AS41*$B$8+$B$9) | BB41: =AW41*1000*$B$10 | BC41: =AT41*$B$11 | BD41: =AT41*$B$12 | BE41: =IF(AS41=0,0,$B$22) | BF41: =(BA41+BB41+BC41+BD41+BE41)*$B$15 | BG41: =IF(AS41=0,0,$B$16) | BH41: =BA41+BB41+BC41+BD41+BE41+BF41+BG41 | BI41: =A41-BH41 | BJ41: =AT41*$B$18 | BK41: =IF(AS41=0,0,AT41*$B$19+$B$20) | BL41: =BJ41-BK41 | BM41: =IF(BH41>0,BL41/BH41,0) | BN41: =IF(AS41=0,IF(A41>=$B$29,"RESERVOIR TEST ONLY: funds a doublet test, not a powered module","BELOW A DOUBLET: appraisal well at most"),IF(BL41<0,"Builds whole modules but contribution is negative",IF(AT41<Control!$B$12,"Operating break-even or better, below the 5 MW reference (not a return)","At/above the 5 MW reference (not a return)")))
A43: Check: model reference raise (Raise!B14) | B43: =Raise!$B$14

Sheet Proxies
A1: ARCHEGON · PUBLIC PROXIES — public benchmarks standing in for Archegon-specific data (ASSUMPTION inputs, sourced)
A2: Every value here is a PUBLIC PROXY: a published figure from another project, market or year. None is an Archegon quote, test or contract. Headline Raise/Summary figures are NOT overwritten; the proxy-adjusted view is computed below so both can be read side by side.
A4: id | B4: Proxy | C4: Value | D4: Unit | E4: Source | F4: URL | G4: Date | H4: Applicability caveat
A5: px_nz_cy27 | B5: ASX NZ baseload futures, Otahuhu CY2027 strip | C5: 126.51 | D5: NZD/MWh | E5: ASX Energy NZ electricity | F5: https://www.asxenergy.com.au/futures/nz_electricity | G5: settle ~1 Oct 2026 | H5: Financial hedge at a grid node, not a physical behind-the-meter PPA; excludes transmission, demand charges, firming premium.
A6: px_nz_cy28 | B6: ASX NZ baseload futures, Otahuhu CY2028 strip | C6: 133.86 | D6: NZD/MWh | E6: ASX Energy NZ electricity | F6: https://www.asxenergy.com.au/futures/nz_electricity | G6: settle ~1 Oct 2026 | H6: As above.
A7: px_nz_contact_avg | B7: Contact Energy average price on electricity sold, FY2026 | C7: 140 | D7: NZD/MWh | E7: interest.co.nz (Contact FY26 result) | F7: https://www.interest.co.nz/business/139744/contact-energys-annual-net-profit-jumps-over-400-million-following-manawa-energy | G7: Aug 2026 | H7: Portfolio average across customers, not a data-centre PPA. Mercury-Datagrid 15-yr 140 MW option (Mar 2026) price undisclosed.
A8: px_colo_azio | B8: AZIO AI Atlas One hosting: capacity reservation charge | C8: 150 | D8: USD/kW/month | E8: AZIO AI press release | F8: https://www.otcmarkets.com/stock/AZIO/news/AZIO-AI-Signs-First-Hosting-Agreement-at-Atlas-One-with-Power-Champion-10-MW-Contracted-with-Expansion-Rights-to-50-MW-R?e=&id=3551446 | G8: 9 Oct 2026 | H8: Texas, grid-connected, 10 MW, 60-month term, 99.9% availability. ENERGY BILLED SEPARATELY (next row). Charged only once energised.
A9: px_energy_azio | B9: AZIO AI Atlas One: fixed energy rate on metered kWh | C9: 0.13 | D9: USD/kWh | E9: AZIO AI press release | F9: https://www.otcmarkets.com/stock/AZIO/news/AZIO-AI-Signs-First-Hosting-Agreement-at-Atlas-One-with-Power-Champion-10-MW-Contracted-with-Expansion-Rights-to-50-MW-R?e=&id=3551446 | G9: 9 Oct 2026 | H9: Plus pass-through utility/transmission charges. One counterparty, one market.
A10: px_colo_sydney | B10: CBRE Sydney average wholesale colo asking rent, Q1 2026 | C10: 188 | D10: USD/kW/month | E10: CBRE Global Data Center Trends 2026 | F10: https://www.cbre.com/insights/reports/global-data-center-trends-2026 | G10: Jun 2026 | H10: Metro asking rent; electricity normally metered separately. Not a remote islanded site.
A11: px_bess_2h | B11: Battery storage 2 h, total cost, 2026, Current policies | C11: 503 | D11: AUD/kWh | E11: CSIRO GenCost 2025-26 Final, Apx Table B.4 | F11: https://www.csiro.au/-/media/Energy/GenCost-2025-26-Final/GenCost_2025-26_Final_Report_20260715.pdf | G11: Jul 2026 | H11: Utility-scale NEM cost; a ~6 MW remote, grid-forming unit will cost more per kWh (no public small-scale figure found).
A12: px_recip_kw | B12: Gas reciprocating engine capital cost, 2026 | C12: 2022 | D12: AUD/kW | E12: CSIRO GenCost 2025-26 Final, Apx Table B.1 | F12: https://www.csiro.au/-/media/Energy/GenCost-2025-26-Final/GenCost_2025-26_Final_Report_20260715.pdf | G12: Jul 2026 | H12: Utility-scale gas recips; GenCost has no diesel genset figure. Gas supply to site is unpriced.
A13: px_blackstart | B13: Separate black-start source | C13: 0 | D13: AUD | E13: No separate public proxy | H13: Assumed covered by grid-forming BESS + recip engines (both black-start capable classes). Needs a power-systems study.
A14: px_fervo_well_hi | B14: Fervo Cape Station horizontal well cost, first well | C14: 9.4 | D14: USD m/well | E14: Fervo Energy (Stanford Workshop release) | F14: https://fervoenergy.com/fervo-energy-drilling-results-show-rapid-advancement-of-geothermal-performance/ | G14: 12 Feb 2024 | H14: Utah granite, mature campaign, US rig market. Excludes stimulation? Not stated.
A15: px_fervo_well_lo | B15: Fervo Cape Station horizontal well cost, 4th well | C15: 4.8 | D15: USD m/well | E15: Fervo Energy | F15: https://fervoenergy.com/fervo-energy-drilling-results-show-rapid-advancement-of-geothermal-performance/ | G15: 12 Feb 2024 | H15: After learning; first Cooper wells would sit near the first-well figure or above (remote AU rig market).
A16: px_forge_flow | B16: Utah FORGE 16B stable production, Aug-Sep 2024 circulation test | C16: 23.5 | D16: kg/s | E16: GeoConvention 2025 abstract (FORGE well test) | F16: https://geoconvention.com/wp-content/uploads/abstracts/2025/114754-egs-well-test-analysis-from-the-perspect | G16: 2025 | H16: 193 degC, 90% recovery; research site, not a commercial design.
A17: px_forge_mwe | B17: Utah FORGE 16B estimated net output at that flow | C17: 1.7 | D17: MWe net | E17: Same abstract (author estimate) | F17: https://geoconvention.com/wp-content/uploads/abstracts/2025/114754-egs-well-test-analysis-from-the-perspect | G17: 2025 | H17: Author calculation, not measured generation.
A18: px_atb_occ_lo | B18: NREL ATB 2024 Deep EGS binary, average OCC, >=200 degC class | C18: 12396 | D18: USD/kW | E18: NREL ATB 2024 Geothermal | F18: https://atb.nrel.gov/electricity/2024/geothermal | G18: 2024 | H18: US 2022$; includes wells + plant; GETEM-modelled, not observed.
A19: px_atb_occ_hi | B19: NREL ATB 2024 Deep EGS binary, average OCC, 150-200 degC class | C19: 22133 | D19: USD/kW | E19: NREL ATB 2024 Geothermal | F19: https://atb.nrel.gov/electricity/2024/geothermal | G19: 2024 | H19: As above.
A20: px_dc_sydney_w | B20: Data-centre construction cost, Sydney (T&T index 2024) | C20: 9.5 | D20: USD/W | E20: Turner & Townsend DCCI, reported via LinkedIn post | F20: https://www.linkedin.com/posts/alistairrobson1_data-centre-cost-index-us-watt-sydney-activity-7223544395164213248-mxRS | G20: 2024 | H20: Secondary report of the index; metro, not AI-liquid specific, not remote.
A21: px_salary_res | B21: Reservoir engineer base salary, Australia | C21: 152459 | D21: AUD/yr | E21: PayScale | F21: https://www.payscale.com/research/AU/Job=Reservoir_Engineer/Salary | G21: 2026 | H21: Average base, excludes super/bonus; principal-level geothermal hires cost more.
A22: px_salary_drill | B22: Drilling engineer base salary, Australia | C22: 203030 | D22: AUD/yr | E22: PayScale | F22: https://www.payscale.com/research/AU/Job=Drilling_Engineer/Salary | G22: 2026 | H22: As above.
A23: px_runway_months | B23: EGS schedule proxy: Cape Station drilling start Jun 2023 to first power targeted 2026 | C23: 36 | D23: months | E23: Fervo Energy / ThinkGeoEnergy | F23: https://www.thinkgeoenergy.com/scientific-approach-to-well-design-powers-fervo-energys-cape-station/ | G23: 2024 | H23: ~36 months for an experienced team with existing permits. Project Red: drilling 2022, grid power 30 Oct 2023.
A24: px_nt_exploration | B24: Native title: earliest arbitration application, exploration/prospecting licence (NTA s35(a)) | C24: 4 | D24: months | E24: Native Title Act 1993 s35 | F24: https://www.legislation.gov.au/C2004A04665/asmade/1993-12-24/text/original/pdf | G24: 1993 as made | H24: Other future acts 6 months (s35(b)); NNTT usually determines within ~6 months of application. ILUA: no set time, plus >=6 months to register.
A25: px_nt_ilua | B25: Yandruwandha Yawarrawarrka conjunctive Cooper Basin ILUA (registered 2007) | C25: 1 | D25: flag | E25: SA Dept for Energy and Mining | F25: https://www.energymining.sa.gov.au/industry/energy-resources/licensing-and-land-access/land-access/aboriginal-interests | G25: current | H25: Petroleum template covering the eastern SA Cooper Basin; whether it can cover a GEOTHERMAL licence needs legal advice. Cost of agreements: no public figure.
... A30: px_habanero_geomech | B30: Habanero/Jolokia lessons: productive zone was one pre-existing critically stressed fault; Jolokia ~1 L/s at 116-122 MPa | C30: 1 | D30: flag | E30: Hogarth & Holl, GRC 2017 "Lessons learned from the Habanero EGS project" | F30: https://publications.mygeoenergynow.org/grc/1033770.pdf | G30: 2017 | H30: Qualitative: argues AGAINST assuming Fervo-style fracture networks transfer to Cooper granite without new stress data.
A33: PROXY-ADJUSTED VIEW (formulas; headline tabs untouched)
A34: Facility load to firm (critical IT x PUE), kW | B34: =Control!$B$12*Control!$B$17*1000*Control!$B$18
A35: Grid-forming BESS, 2 h at facility load, A$ | B35: =B34*2*Proxies!$C$11 | C35: 2 h ride-through/transition at GenCost utility cost
A36: Standby recip engines at full facility load, A$ | B36: =B34*Proxies!$C$12 | C36: Covers a full plant trip (876 h/yr at CF 0.90)
A37: Black start (separate), A$ | B37: =Proxies!$C$13 | C37: Included in BESS + recips
A38: Firm-power package incl. contingency, A$ | B38: =(B35+B36+B37)*(1+Control!$B$13)
A39: Extra runway to proxy schedule, A$ | B39: =MAX(0,Proxies!$C$23-Control!$B$14)*Control!$B$15*Control!$B$18 | C39: 36 vs 24 months
A40: Headline raise (Raise!B14), A$ | B40: =Raise!$B$14
A41: PROXY-ADJUSTED RAISE, A$ | B41: =B40+B38+B39 | C41: Headline + firm package + longer runway
A42: Contribution, headline (colo bundled), A$/yr | B42: ='Compute-Revenue'!$B$31
A43: Contribution / proxy-adjusted raise | B43: =B42/B41
A44: AZIO structure: capacity charge revenue, A$/yr | B44: =Proxies!$C$8*12*'Compute-Revenue'!$B$6/Rates!$D$4 | C44: US$150/kW/mo on critical IT
A45: AZIO structure: energy billed at US$0.13/kWh, A$/yr | B45: ='Compute-Revenue'!$B$7*1000*Proxies!$C$9/Rates!$D$4 | C45: On total facility MWh
A46: AZIO structure: contribution, A$/yr | B46: =B44+B45-'Compute-Revenue'!$B$28 | C46: Same opex floor
A47: AZIO structure: contribution / proxy-adjusted raise | B47: =B46/B41 | C47: Upper case: assumes a tenant pays Texas-style energy on top
A48: NZ energy cost at ASX CY27 strip, A$/yr | B48: ='Compute-Revenue'!$B$24*Proxies!$C$5/Rates!$D$35 | C48: vs NZ$105 one-week spot
A49: NZ contribution at ASX CY27, A$/yr | B49: ='Route-Compare'!$C$10-(B48-'Compute-Revenue'!$B$24)
A50: NZ contribution / NZ raise at ASX CY27 | B50: =B49/'Route-Compare'!$C$6
A51: Gate 0 pre-seed proxy range, low, A$ | B51: =3000000/Rates!$D$4 | C51: US$3m: between Eavor 2018 seed (CA$3.0m) and Quaise seed (US$6m)
A52: Gate 0 pre-seed proxy range, high, A$ | B52: =Proxies!$C$26*1000000/Rates!$D$4 | C52: US$6m = Quaise seed
A53: Team budget implied FTEs at reservoir-engineer base salary | B53: =Control!$B$15*12/Proxies!$C$21 | C53: A$250k/month; excludes on-costs, so real headcount is lower
A54: DC build: shell+cooling at T&T Sydney US$9.5/W vs model, A$ (overlap check, not applied) | B54: =-('AU-Route'!$B$26+'AU-Route'!$B$27+'AU-Route'!$B$28)*(1-Proxies!$C$20*1000000/(Rates!$D$21+Rates!$D$22))*(1+Control!$B$13) | C54: Negative = model may be conservative; remote AI build likely costs more than metro
A55: Cape well cost range in A$ m | B55: =Proxies!$C$15/Rates!$D$4 | C55: to
B56: =Proxies!$C$14/Rates!$D$4 | C56: vs model A$14.0/16.5/22.7m

Sheet Sell-Compute
A1: ARCHEGON · SELL COMPUTE — GPU-as-a-service beside the colocation (rental) case. Inputs are PUBLIC PROXIES with sources; not quotes.
A2: Archegon buys the GPU servers and sells GPU-hours. Revenue = GPUs x 8,760 h x utilisation x price. Every input below is a published figure from another market or a derivation from one (DERIVED). The colocation case on Compute-Revenue is unchanged. No AI-lab customer is assumed.
A4: id | B4: Input | C4: Value | D4: Unit | E4: Status | F4: Source | G4: URL | H4: Date | I4: Caveat
A5: srv_usd | B5: 8-GPU HGX B200 server, OEM integrated, typical | C5: 450000 | D5: USD/server | E5: PUBLIC PROXY | F5: Mercatus: B200 server price 2026 | G5: https://www.mercatus-ai.com/blog/b200-server-price | H5: 2026 | I5: Range US$400-500k; DGX B200 ~US$515k; allocation-constrained.
A6: srv_kw | B6: DGX B200 system max power | C6: 14.3 | D6: kW/server | E6: VERIFIED | F6: NVIDIA DGX B200 User Guide | G6: https://docs.nvidia.com/dgx/dgxb200-user-guide/introduction-to-dgxb200.html | H6: 2026 | I6: Max draw used as design IT load.
A7: gpu_per_srv | B7: GPUs per server | C7: 8 | D7: GPUs | E7: VERIFIED | F7: NVIDIA DGX B200 User Guide | G7: https://docs.nvidia.com/dgx/dgxb200-user-guide/introduction-to-dgxb200.html | H7: 2026
A8: net_share | B8: Networking + storage + racks, share of GPU server capex | C8: 0.3 | D8: share | E8: PUBLIC PROXY | F8: GPUaaS.com TCO (Silicon Analysts example: 64xH100 US$4.0m + 0.4 storage + 0.5 network + 0.3 racks) | G8: https://gpuaas.com/blog/real-tco-gpu-cluster-2026 | H8: 4 Jun 2026 | I8: H100 example; other sources 8-25%.
A9: maint_share | B9: Hardware maintenance, share of capex per year | C9: 0.1 | D9: share/yr | E9: PUBLIC PROXY | F9: GPUaaS.com citing Introl (8-12%) | G9: https://gpuaas.com/blog/real-tco-gpu-cluster-2026 | H9: 4 Jun 2026 | I9: Midpoint of quoted range.
A10: eng_usd | B10: GPU infrastructure engineer, fully loaded | C10: 275000 | D10: USD/yr | E10: PUBLIC PROXY | F10: GPUaaS.com citing Introl | G10: https://gpuaas.com/blog/real-tco-gpu-cluster-2026 | H10: 4 Jun 2026 | I10: US cost; remote-site premium unpriced.
A11: fte_512 | B11: 24x7 ops team per 512 GPUs | C11: 5 | D11: FTE | E11: PUBLIC PROXY | F11: GPUaaS.com citing io.net | G11: https://gpuaas.com/blog/real-tco-gpu-cluster-2026 | H11: 4 Jun 2026 | I11: Linear scaling above 512 GPUs is an ASSUMPTION; minimum 5 FTE.
A12: p_od_median | B12: B200 on-demand median rate card, 33 providers | C12: 6.99 | D12: USD/GPU-h | E12: PUBLIC PROXY | F12: gpueconomy.com | G12: https://gpueconomy.com/providers/lambda/b200 | H12: 12 Oct 2026 | I12: Rate cards, not transacted prices.
A13: disc_1y | B13: B200 1-year reserved discount vs on-demand | C13: 0.21 | D13: share | E13: PUBLIC PROXY | F13: AI Industry Reviews, GPU cloud pricing Sep 2026 | G13: https://ai-industry-reviews.com/research/gpu-cloud-pricing-statistics-september-2026/ | H13: Sep 2026 | I13: Median across providers.
A14: p_low | B14: B200 SemiAnalysis spot-contract composite index | C14: 3.68 | D14: USD/GPU-h | E14: PUBLIC PROXY | F14: SemiAnalysis GPU index | G14: https://gpu-index.semianalysis.com/ | H14: Apr 2026 | I14: Market composite; LOW case.
A15: p_base | B15: B200 1-year reserved (derived = median on-demand x (1 - discount)) | C15: =C12*(1-C13) | D15: USD/GPU-h | E15: DERIVED | F15: From the two rows above
A16: p_high | B16: B200 on-demand, Lambda 8-GPU | C16: 6.69 | D16: USD/GPU-h | E16: PUBLIC PROXY | F16: Lambda instances | G16: https://lambda.ai/instances | H16: 12 Oct 2026 | I16: Also listed for NSW, sold out. HIGH case: on-demand assumes full sell-through.
A17: p_cw | B17: HGX B200 on-demand, CoreWeave | C17: 8.6 | D17: USD/GPU-h | E17: PUBLIC PROXY | F17: CoreWeave pricing | G17: https://coreweave.com/pricing | H17: 12 Oct 2026 | I17: Reference only; most capacity is sold on contract.
A18: u_low | B18: GPU active utilisation, 34-provider panel | C18: 0.47 | D18: share | E18: PUBLIC PROXY | F18: AI Industry Reviews, GPU utilisation 2026 | G18: https://ai-industry-reviews.com/research/gpu-utilization-rate-statistics-2026/ | H18: 2026 | I18: Panel estimate; no provider discloses a consistent KPI.
A19: u_base | B19: Utilisation at which owning beats renting (B200) | C19: 0.7 | D19: share | E19: PUBLIC PROXY | F19: GPUaaS.com citing American Compute | G19: https://gpuaas.com/blog/real-tco-gpu-cluster-2026 | H19: Mar 2026 | I19: Used as BASE.
A20: u_high | B20: Utilisation assumed in owned-cluster TCO example | C20: 0.8 | D20: share | E20: PUBLIC PROXY | F20: GPUaaS.com citing American Compute | G20: https://gpuaas.com/blog/real-tco-gpu-cluster-2026 | H20: Mar 2026
A21: life | B21: GPU server useful life (refresh cycle) | C21: 5 | D21: years | E21: PUBLIC PROXY | F21: Amazon shortened servers to 5 yrs from 2025 (CoreWeave uses 6) | G21: https://www.businessinsider.com/coreweave-ipo-nvidia-gpu-hopper-problem-blackwell-ai-depreciation-2025-3 | H21: 2025 | I21: Economic life may be shorter (resale -50% in 2 yrs per GPUaaS.com).
A22: decay | B22: GPU-hour price change per year within a refresh cycle (H100 >$7 early 2024 -> $3.38 Aug 2026) | C22: =(3.38/7)^(1/2.5)-1 | D22: share/yr | E22: DERIVED | F22: Shattered.io citing AIMultiple index | G22: https://shattered.io/h100-h200-b200-cloud-gpu-pricing-2026/ | H22: Aug 2026 | I22: 2026 counter-signal: H100 on-demand +15% YoY (GPUaaS.com Q4 2026). Flat-price case shown alongside.
A23: decay_flat | B23: Flat-price case (2026 market rose rather than fell) | C23: 0 | D23: share/yr | E23: PUBLIC PROXY | F23: GPUaaS.com State of GPU procurement Q4 2026 | G23: https://gpuaas.com/blog/state-of-gpu-procurement-q4-2026 | H23: Q4 2026 | I23: Upside case.
A24: starlink_ms | B24: Starlink average latency, Australia | C24: 29.8 | D24: ms | E24: PUBLIC PROXY | F24: Off-grid Internet (ACCC data) | G24: https://www.offgridinternet.com.au/starlink-vs-nbn-australia/ | H24: 2026 | I24: Fine for batch training/inference APIs; not for bulk data ingress.
A25: starlink_mbps | B25: Telstra Starlink busy-hour download | C25: 50 | D25: Mbps | E25: PUBLIC PROXY | F25: WhistleOut | G25: https://www.whistleout.com.au/Broadband/Guides/Telstra-Starlink-vs-SpaceX-Starlink | H25: 2026 | I25: ~0.5 TB/day at full rate: far too thin for a 2,800-GPU cluster. AU compute needs fibre (AU-Route B29 is RATE_MISSING, A$0).
A26: au_h200_aud | B26: Only public Australian GPU rate: Micron21 H200 (reference) | C26: 6.08 | D26: AUD/GPU-h | E26: PUBLIC PROXY | F26: Micron21 | G26: https://www.micron21.com/blog/nvidia-h200-cloud-pricing-in-australia-2026-mcloud-vs-aws-azure-google-cloud-and-neoclouds | H26: 2026 | I26: H200, Melbourne Tier IV; not used in calcs.
A29: CASES AT THE 5 MW REFERENCE (one site each). Consolidated = Archegon owns power + hall + GPUs. ComputeCo = buys power at the Power-Economics transfer price (LCOE at 8%).
A30: Case | B30: AU, prices decay | C30: AU, flat prices | D30: NZ, prices decay | E30: NZ, flat prices | F30: AU downside: 47% util, 20% remote discount, decay | G30: AU ComputeCo (transfer price), decay | H30: AU ComputeCo (transfer price), flat | I30: AU colocation (rental), for comparison
A31: IT load (kW) | B31: =Control!$B$12*1000 | C31: =Control!$B$12*1000 | D31: =Control!$B$12*1000 | E31: =Control!$B$12*1000 | F31: =Control!$B$12*1000 | G31: =Control!$B$12*1000 | H31: =Control!$B$12*1000
A32: GPU servers | B32: =ROUNDDOWN(B31/$C$6,0) | C32: =ROUNDDOWN(C31/$C$6,0) | D32: =ROUNDDOWN(D31/$C$6,0) | E32: =ROUNDDOWN(E31/$C$6,0) | F32: =ROUNDDOWN(F31/$C$6,0) | G32: =ROUNDDOWN(G31/$C$6,0) | H32: =ROUNDDOWN(H31/$C$6,0)
A33: GPUs | B33: =B32*$C$7 | C33: =C32*$C$7 | D33: =D32*$C$7 | E33: =E32*$C$7 | F33: =F32*$C$7 | G33: =G32*$C$7 | H33: =H32*$C$7
A34: GPU capex incl. network/storage, A$ | B34: =B32*$C$5*(1+$C$8)/Rates!$D$4 | C34: =C32*$C$5*(1+$C$8)/Rates!$D$4 | D34: =D32*$C$5*(1+$C$8)/Rates!$D$4 | E34: =E32*$C$5*(1+$C$8)/Rates!$D$4 | F34: =F32*$C$5*(1+$C$8)/Rates!$D$4 | G34: =G32*$C$5*(1+$C$8)/Rates!$D$4 | H34: =H32*$C$5*(1+$C$8)/Rates!$D$4
A35: Infrastructure capital (raise or hall), A$ | B35: ='Route-Compare'!$B$6+Connectivity!$C$5 | C35: ='Route-Compare'!$B$6+Connectivity!$C$5 | D35: ='Route-Compare'!$C$6+Connectivity!$C$7 | E35: ='Route-Compare'!$C$6+Connectivity!$C$7 | F35: ='Route-Compare'!$B$6+Connectivity!$C$5 | G35: =Connectivity!$C$5+('AU-Route'!$B$26+'AU-Route'!$B$27+'AU-Route'!$B$28)*(1+Control!$B$13)+Control!$B$14*Control!$B$15 | H35: =Connectivity!$C$5+('AU-Route'!$B$26+'AU-Route'!$B$27+'AU-Route'!$B$28)*(1+Control!$B$13)+Control!$B$14*Control!$B$15
A36: TOTAL CAPITAL incl. GPUs, A$ | B36: =B34+B35 | C36: =C34+C35 | D36: =D34+D35 | E36: =E34+E35 | F36: =F34+F35 | G36: =G34+G35 | H36: =H34+H35 | I36: ='Route-Compare'!$B$6
A37: Price, US$/GPU-h (year 1) | B37: =$C$15 | C37: =$C$15 | D37: =$C$15 | E37: =$C$15 | F37: =$C$15*(1-Rates!$D$83) | G37: =$C$15 | H37: =$C$15
A38: Utilisation | B38: =$C$19 | C38: =$C$19 | D38: =$C$19 | E38: =$C$19 | F38: =$C$18 | G38: =$C$19 | H38: =$C$19
A39: GPU-hours sold, yr 1 (capped by deliverable bandwidth, Connectivity C13/C14) | B39: =B33*8760*B38*Connectivity!$C$13 | C39: =C33*8760*C38*Connectivity!$C$13 | D39: =D33*8760*D38*Connectivity!$C$14 | E39: =E33*8760*E38*Connectivity!$C$14 | F39: =F33*8760*F38*Connectivity!$C$13 | G39: =G33*8760*G38*Connectivity!$C$13 | H39: =H33*8760*H38*Connectivity!$C$13
A40: REVENUE yr 1, A$ | B40: =B39*B37/Rates!$D$4 | C40: =C39*C37/Rates!$D$4 | D40: =D39*D37/Rates!$D$4 | E40: =E39*E37/Rates!$D$4 | F40: =F39*F37/Rates!$D$4 | G40: =G39*G37/Rates!$D$4 | H40: =H39*H37/Rates!$D$4 | I40: ='Compute-Revenue'!$B$10
A41: Power cost, A$/yr | B41: ='Compute-Revenue'!$B$23 | C41: ='Compute-Revenue'!$B$23 | D41: ='Compute-Revenue'!$B$24 | E41: ='Compute-Revenue'!$B$24 | F41: ='Compute-Revenue'!$B$23 | G41: ='Compute-Revenue'!$B$7*'Power-Economics'!$E$16 | H41: ='Compute-Revenue'!$B$7*'Power-Economics'!$E$16
A42: Hardware maintenance, A$/yr | B42: =$C$9*B34 | C42: =$C$9*C34 | D42: =$C$9*D34 | E42: =$C$9*E34 | F42: =$C$9*F34 | G42: =$C$9*G34 | H42: =$C$9*H34
A43: GPU ops staff, A$/yr | B43: =MAX($C$11,B33/512*$C$11)*$C$10/Rates!$D$4 | C43: =MAX($C$11,C33/512*$C$11)*$C$10/Rates!$D$4 | D43: =MAX($C$11,D33/512*$C$11)*$C$10/Rates!$D$4 | E43: =MAX($C$11,E33/512*$C$11)*$C$10/Rates!$D$4 | F43: =MAX($C$11,F33/512*$C$11)*$C$10/Rates!$D$4 | G43: =MAX($C$11,G33/512*$C$11)*$C$10/Rates!$D$4 | H43: =MAX($C$11,H33/512*$C$11)*$C$10/Rates!$D$4
A44: Team + overhead, A$/yr | B44: =Control!$B$15*12 | C44: =Control!$B$15*12 | D44: =Control!$B$15*12 | E44: =Control!$B$15*12 | F44: =Control!$B$15*12 | G44: =Control!$B$15*12 | H44: =Control!$B$15*12
A45: Connectivity opex (Connectivity tab); other data-centre non-energy opex RATE_MISSING, A$/yr | B45: =Connectivity!$C$6 | C45: =Connectivity!$C$6 | D45: =Connectivity!$C$8 | E45: =Connectivity!$C$8 | F45: =Connectivity!$C$6 | G45: =Connectivity!$C$6 | H45: =Connectivity!$C$6
A46: EBITDA yr 1, A$ | B46: =B40-SUM(B41:B45) | C46: =C40-SUM(C41:C45) | D46: =D40-SUM(D41:D45) | E46: =E40-SUM(E41:E45) | F46: =F40-SUM(F41:F45) | G46: =G40-SUM(G41:G45) | H46: =H40-SUM(H41:H45) | I46: ='Compute-Revenue'!$B$31
A47: EBITDA margin yr 1 | B47: =B46/B40 | C47: =C46/C40 | D47: =D46/D40 | E47: =E46/E40 | F47: =F46/F40 | G47: =G46/G40 | H47: =H46/H40
A48: EBITDA yr 1 / total capital | B48: =B46/B36 | C48: =C46/C36 | D48: =D46/D36 | E48: =E46/E36 | F48: =F46/F36 | G48: =G46/G36 | H48: =H46/H36 | I48: =I46/I36
A49: Simple payback of total capital at yr-1 EBITDA (yrs) | B49: =IF(B46>0,B36/B46,"never") | C49: =IF(C46>0,C36/C46,"never") | D49: =IF(D46>0,D36/D46,"never") | E49: =IF(E46>0,E36/E46,"never") | F49: =IF(F46>0,F36/F46,"never") | G49: =IF(G46>0,G36/G46,"never") | H49: =IF(H46>0,H36/H46,"never") | I49: =IF(I46>0,I36/I46,"never")
A50: Price change per year in cycle | B50: =$C$22 | C50: =$C$23 | D50: =$C$22 | E50: =$C$23 | F50: =$C$22 | G50: =$C$22 | H50: =$C$23
A51: 25-yr IRR (unlevered, pre-tax, no terminal value) | B51: =IFERROR(IRR(C57:AB57),IF(SUM(C57:AB57)<0,"never repays","no IRR")) | C51: =IFERROR(IRR(C58:AB58),IF(SUM(C58:AB58)<0,"never repays","no IRR")) | D51: =IFERROR(IRR(C59:AB59),IF(SUM(C59:AB59)<0,"never repays","no IRR")) | E51: =IFERROR(IRR(C60:AB60),IF(SUM(C60:AB60)<0,"never repays","no IRR")) | F51: =IFERROR(IRR(C61:AB61),IF(SUM(C61:AB61)<0,"never repays","no IRR")) | G51: =IFERROR(IRR(C62:AB62),IF(SUM(C62:AB62)<0,"never repays","no IRR")) | H51: =IFERROR(IRR(C63:AB63),IF(SUM(C63:AB63)<0,"never repays","no IRR")) | I51: =IFERROR(IRR(C64:AB64),IF(SUM(C64:AB64)<0,"never repays","no IRR"))
A52: 25-yr net cash, undiscounted, A$ | B52: =SUM(C57:AB57) | C52: =SUM(C58:AB58) | D52: =SUM(C59:AB59) | E52: =SUM(C60:AB60) | F52: =SUM(C61:AB61) | G52: =SUM(C62:AB62) | H52: =SUM(C63:AB63) | I52: =SUM(C64:AB64)
A55: 25-YEAR CASH FLOWS (year 0 in column C). GPU fleet replaced every life years at the same capex; price resets to year-1 level at each refresh, then changes per year. No terminal value, tax or financing.
A56: Year | C56: 0 | D56: 1 | E56: 2 | F56: 3 | G56: 4 | H56: 5 | I56: 6 | J56: 7 | K56: 8 | L56: 9 | M56: 10 | N56: 11 | O56: 12 | P56: 13 | Q56: 14 | R56: 15 | S56: 16 | T56: 17 | U56: 18 | V56: 19 | W56: 20 | X56: 21 | Y56: 22 | Z56: 23 | AA56: 24 | AB56: 25
A57: Cash flow: AU, prices decay | C57: =-B$36 | D57: =IF(D$56<=Rates!$D$71,(B$40*(1+B$50)^MOD(D$56-1,$C$21)-B$42-B$43)*D$65-B$41-B$44-B$45-IF(AND(MOD(D$56,$C$21)=0,D$56<Rates!$D$71),B$34*D$65,0),0) | E57: =IF(E$56<=Rates!$D$71,(B$40*(1+B$50)^MOD(E$56-1,$C$21)-B$42-B$43)*E$65-B$41-B$44-B$45-IF(AND(MOD(E$56,$C$21)=0,E$56<Rates!$D$71),B$34*E$65,0),0) | F57: =IF(F$56<=Rates!$D$71,(B$40*(1+B$50)^MOD(F$56-1,$C$21)-B$42-B$43)*F$65-B$41-B$44-B$45-IF(AND(MOD(F$56,$C$21)=0,F$56<Rates!$D$71),B$34*F$65,0),0) | G57: =IF(G$56<=Rates!$D$71,(B$40*(1+B$50)^MOD(G$56-1,$C$21)-B$42-B$43)*G$65-B$41-B$44-B$45-IF(AND(MOD(G$56,$C$21)=0,G$56<Rates!$D$71),B$34*G$65,0),0) | H57: =IF(H$56<=Rates!$D$71,(B$40*(1+B$50)^MOD(H$56-1,$C$21)-B$42-B$43)*H$65-B$41-B$44-B$45-IF(AND(MOD(H$56,$C$21)=0,H$56<Rates!$D$71),B$34*H$65,0),0) | I57: =IF(I$56<=Rates!$D$71,(B$40*(1+B$50)^MOD(I$56-1,$C$21)-B$42-B$43)*I$65-B$41-B$44-B$45-IF(AND(MOD(I$56,$C$21)=0,I$56<Rates!$D$71),B$34*I$65,0),0) | J57: =IF(J$56<=Rates!$D$71,(B$40*(1+B$50)^MOD(J$56-1,$C$21)-B$42-B$43)*J$65-B$41-B$44-B$45-IF(AND(MOD(J$56,$C$21)=0,J$56<Rates!$D$71),B$34*J$65,0),0) | K57: =IF(K$56<=Rates!$D$71,(B$40*(1+B$50)^MOD(K$56-1,$C$21)-B$42-B$43)*K$65-B$41-B$44-B$45-IF(AND(MOD(K$56,$C$21)=0,K$56<Rates!$D$71),B$34*K$65,0),0) | L57: =IF(L$56<=Rates!$D$71,(B$40*(1+B$50)^MOD(L$56-1,$C$21)-B$42-B$43)*L$65-B$41-B$44-B$45-IF(AND(MOD(L$56,$C$21)=0,L$56<Rates!$D$71),B$34*L$65,0),0) | M57: =IF(M$56<=Rates!$D$71,(B$40*(1+B$50)^MOD(M$56-1,$C$21)-B$42-B$43)*M$65-B$41-B$44-B$45-IF(AND(MOD(M$56,$C$21)=0,M$56<Rates!$D$71),B$34*M$65,0),0) | N57: =IF(N$56<=Rates!$D$71,(B$40*(1+B$50)^MOD(N$56-1,$C$21)-B$42-B$43)*N$65-B$41-B$44-B$45-IF(AND(MOD(N$56,$C$21)=0,N$56<Rates!$D$71),B$34*N$65,0),0) | O57: =IF(O$56<=Rates!$D$71,(B$40*(1+B$50)^MOD(O$56-1,$C$21)-B$42-B$43)*O$65-B$41-B$44-B$45-IF(AND(MOD(O$56,$C$21)=0,O$56<Rates!$D$71),B$34*O$65,0),0) | P57: =IF(P$56<=Rates!$D$71,(B$40*(1+B$50)^MOD(P$56-1,$C$21)-B$42-B$43)*P$65-B$41-B$44-B$45-IF(AND(MOD(P$56,$C$21)=0,P$56<Rates!$D$71),B$34*P$65,0),0) | Q57: =IF(Q$56<=Rates!$D$71,(B$40*(1+B$50)^MOD(Q$56-1,$C$21)-B$42-B$43)*Q$65-B$41-B$44-B$45-IF(AND(MOD(Q$56,$C$21)=0,Q$56<Rates!$D$71),B$34*Q$65,0),0) | R57: =IF(R$56<=Rates!$D$71,(B$40*(1+B$50)^MOD(R$56-1,$C$21)-B$42-B$43)*R$65-B$41-B$44-B$45-IF(AND(MOD(R$56,$C$21)=0,R$56<Rates!$D$71),B$34*R$65,0),0) | S57: =IF(S$56<=Rates!$D$71,(B$40*(1+B$50)^MOD(S$56-1,$C$21)-B$42-B$43)*S$65-B$41-B$44-B$45-IF(AND(MOD(S$56,$C$21)=0,S$56<Rates!$D$71),B$34*S$65,0),0) | T57: =IF(T$56<=Rates!$D$71,(B$40*(1+B$50)^MOD(T$56-1,$C$21)-B$42-B$43)*T$65-B$41-B$44-B$45-IF(AND(MOD(T$56,$C$21)=0,T$56<Rates!$D$71),B$34*T$65,0),0) | U57: =IF(U$56<=Rates!$D$71,(B$40*(1+B$50)^MOD(U$56-1,$C$21)-B$42-B$43)*U$65-B$41-B$44-B$45-IF(AND(MOD(U$56,$C$21)=0,U$56<Rates!$D$71),B$34*U$65,0),0) | V57: =IF(V$56<=Rates!$D$71,(B$40*(1+B$50)^MOD(V$56-1,$C$21)-B$42-B$43)*V$65-B$41-B$44-B$45-IF(AND(MOD(V$56,$C$21)=0,V$56<Rates!$D$71),B$34*V$65,0),0) | W57: =IF(W$56<=Rates!$D$71,(B$40*(1+B$50)^MOD(W$56-1,$C$21)-B$42-B$43)*W$65-B$41-B$44-B$45-IF(AND(MOD(W$56,$C$21)=0,W$56<Rates!$D$71),B$34*W$65,0),0) | X57: =IF(X$56<=Rates!$D$71,(B$40*(1+B$50)^MOD(X$56-1,$C$21)-B$42-B$43)*X$65-B$41-B$44-B$45-IF(AND(MOD(X$56,$C$21)=0,X$56<Rates!$D$71),B$34*X$65,0),0) | Y57: =IF(Y$56<=Rates!$D$71,(B$40*(1+B$50)^MOD(Y$56-1,$C$21)-B$42-B$43)*Y$65-B$41-B$44-B$45-IF(AND(MOD(Y$56,$C$21)=0,Y$56<Rates!$D$71),B$34*Y$65,0),0) | Z57: =IF(Z$56<=Rates!$D$71,(B$40*(1+B$50)^MOD(Z$56-1,$C$21)-B$42-B$43)*Z$65-B$41-B$44-B$45-IF(AND(MOD(Z$56,$C$21)=0,Z$56<Rates!$D$71),B$34*Z$65,0),0) | AA57: =IF(AA$56<=Rates!$D$71,(B$40*(1+B$50)^MOD(AA$56-1,$C$21)-B$42-B$43)*AA$65-B$41-B$44-B$45-IF(AND(MOD(AA$56,$C$21)=0,AA$56<Rates!$D$71),B$34*AA$65,0),0) | AB57: =IF(AB$56<=Rates!$D$71,(B$40*(1+B$50)^MOD(AB$56-1,$C$21)-B$42-B$43)*AB$65-B$41-B$44-B$45-IF(AND(MOD(AB$56,$C$21)=0,AB$56<Rates!$D$71),B$34*AB$65,0),0)
A58: Cash flow: AU, flat prices | C58: =-C$36 | D58: =IF(D$56<=Rates!$D$71,(C$40*(1+C$50)^MOD(D$56-1,$C$21)-C$42-C$43)*D$65-C$41-C$44-C$45-IF(AND(MOD(D$56,$C$21)=0,D$56<Rates!$D$71),C$34*D$65,0),0) | E58: =IF(E$56<=Rates!$D$71,(C$40*(1+C$50)^MOD(E$56-1,$C$21)-C$42-C$43)*E$65-C$41-C$44-C$45-IF(AND(MOD(E$56,$C$21)=0,E$56<Rates!$D$71),C$34*E$65,0),0) | F58: =IF(F$56<=Rates!$D$71,(C$40*(1+C$50)^MOD(F$56-1,$C$21)-C$42-C$43)*F$65-C$41-C$44-C$45-IF(AND(MOD(F$56,$C$21)=0,F$56<Rates!$D$71),C$34*F$65,0),0) | G58: =IF(G$56<=Rates!$D$71,(C$40*(1+C$50)^MOD(G$56-1,$C$21)-C$42-C$43)*G$65-C$41-C$44-C$45-IF(AND(MOD(G$56,$C$21)=0,G$56<Rates!$D$71),C$34*G$65,0),0) | H58: =IF(H$56<=Rates!$D$71,(C$40*(1+C$50)^MOD(H$56-1,$C$21)-C$42-C$43)*H$65-C$41-C$44-C$45-IF(AND(MOD(H$56,$C$21)=0,H$56<Rates!$D$71),C$34*H$65,0),0) | I58: =IF(I$56<=Rates!$D$71,(C$40*(1+C$50)^MOD(I$56-1,$C$21)-C$42-C$43)*I$65-C$41-C$44-C$45-IF(AND(MOD(I$56,$C$21)=0,I$56<Rates!$D$71),C$34*I$65,0),0) | J58: =IF(J$56<=Rates!$D$71,(C$40*(1+C$50)^MOD(J$56-1,$C$21)-C$42-C$43)*J$65-C$41-C$44-C$45-IF(AND(MOD(J$56,$C$21)=0,J$56<Rates!$D$71),C$34*J$65,0),0) | K58: =IF(K$56<=Rates!$D$71,(C$40*(1+C$50)^MOD(K$56-1,$C$21)-C$42-C$43)*K$65-C$41-C$44-C$45-IF(AND(MOD(K$56,$C$21)=0,K$56<Rates!$D$71),C$34*K$65,0),0) | L58: =IF(L$56<=Rates!$D$71,(C$40*(1+C$50)^MOD(L$56-1,$C$21)-C$42-C$43)*L$65-C$41-C$44-C$45-IF(AND(MOD(L$56,$C$21)=0,L$56<Rates!$D$71),C$34*L$65,0),0) | M58: =IF(M$56<=Rates!$D$71,(C$40*(1+C$50)^MOD(M$56-1,$C$21)-C$42-C$43)*M$65-C$41-C$44-C$45-IF(AND(MOD(M$56,$C$21)=0,M$56<Rates!$D$71),C$34*M$65,0),0) | N58: =IF(N$56<=Rates!$D$71,(C$40*(1+C$50)^MOD(N$56-1,$C$21)-C$42-C$43)*N$65-C$41-C$44-C$45-IF(AND(MOD(N$56,$C$21)=0,N$56<Rates!$D$71),C$34*N$65,0),0) | O58: =IF(O$56<=Rates!$D$71,(C$40*(1+C$50)^MOD(O$56-1,$C$21)-C$42-C$43)*O$65-C$41-C$44-C$45-IF(AND(MOD(O$56,$C$21)=0,O$56<Rates!$D$71),C$34*O$65,0),0) | P58: =IF(P$56<=Rates!$D$71,(C$40*(1+C$50)^MOD(P$56-1,$C$21)-C$42-C$43)*P$65-C$41-C$44-C$45-IF(AND(MOD(P$56,$C$21)=0,P$56<Rates!$D$71),C$34*P$65,0),0) | Q58: =IF(Q$56<=Rates!$D$71,(C$40*(1+C$50)^MOD(Q$56-1,$C$21)-C$42-C$43)*Q$65-C$41-C$44-C$45-IF(AND(MOD(Q$56,$C$21)=0,Q$56<Rates!$D$71),C$34*Q$65,0),0) | R58: =IF(R$56<=Rates!$D$71,(C$40*(1+C$50)^MOD(R$56-1,$C$21)-C$42-C$43)*R$65-C$41-C$44-C$45-IF(AND(MOD(R$56,$C$21)=0,R$56<Rates!$D$71),C$34*R$65,0),0) | S58: =IF(S$56<=Rates!$D$71,(C$40*(1+C$50)^MOD(S$56-1,$C$21)-C$42-C$43)*S$65-C$41-C$44-C$45-IF(AND(MOD(S$56,$C$21)=0,S$56<Rates!$D$71),C$34*S$65,0),0) | T58: =IF(T$56<=Rates!$D$71,(C$40*(1+C$50)^MOD(T$56-1,$C$21)-C$42-C$43)*T$65-C$41-C$44-C$45-IF(AND(MOD(T$56,$C$21)=0,T$56<Rates!$D$71),C$34*T$65,0),0) | U58: =IF(U$56<=Rates!$D$71,(C$40*(1+C$50)^MOD(U$56-1,$C$21)-C$42-C$43)*U$65-C$41-C$44-C$45-IF(AND(MOD(U$56,$C$21)=0,U$56<Rates!$D$71),C$34*U$65,0),0) | V58: =IF(V$56<=Rates!$D$71,(C$40*(1+C$50)^MOD(V$56-1,$C$21)-C$42-C$43)*V$65-C$41-C$44-C$45-IF(AND(MOD(V$56,$C$21)=0,V$56<Rates!$D$71),C$34*V$65,0),0) | W58: =IF(W$56<=Rates!$D$71,(C$40*(1+C$50)^MOD(W$56-1,$C$21)-C$42-C$43)*W$65-C$41-C$44-C$45-IF(AND(MOD(W$56,$C$21)=0,W$56<Rates!$D$71),C$34*W$65,0),0) | X58: =IF(X$56<=Rates!$D$71,(C$40*(1+C$50)^MOD(X$56-1,$C$21)-C$42-C$43)*X$65-C$41-C$44-C$45-IF(AND(MOD(X$56,$C$21)=0,X$56<Rates!$D$71),C$34*X$65,0),0) | Y58: =IF(Y$56<=Rates!$D$71,(C$40*(1+C$50)^MOD(Y$56-1,$C$21)-C$42-C$43)*Y$65-C$41-C$44-C$45-IF(AND(MOD(Y$56,$C$21)=0,Y$56<Rates!$D$71),C$34*Y$65,0),0) | Z58: =IF(Z$56<=Rates!$D$71,(C$40*(1+C$50)^MOD(Z$56-1,$C$21)-C$42-C$43)*Z$65-C$41-C$44-C$45-IF(AND(MOD(Z$56,$C$21)=0,Z$56<Rates!$D$71),C$34*Z$65,0),0) | AA58: =IF(AA$56<=Rates!$D$71,(C$40*(1+C$50)^MOD(AA$56-1,$C$21)-C$42-C$43)*AA$65-C$41-C$44-C$45-IF(AND(MOD(AA$56,$C$21)=0,AA$56<Rates!$D$71),C$34*AA$65,0),0) | AB58: =IF(AB$56<=Rates!$D$71,(C$40*(1+C$50)^MOD(AB$56-1,$C$21)-C$42-C$43)*AB$65-C$41-C$44-C$45-IF(AND(MOD(AB$56,$C$21)=0,AB$56<Rates!$D$71),C$34*AB$65,0),0)
A59: Cash flow: NZ, prices decay | C59: =-D$36 | D59: =IF(D$56<=Rates!$D$71,(D$40*(1+D$50)^MOD(D$56-1,$C$21)-D$42-D$43)-D$41-D$44-D$45-IF(AND(MOD(D$56,$C$21)=0,D$56<Rates!$D$71),D$34,0),0) | E59: =IF(E$56<=Rates!$D$71,(D$40*(1+D$50)^MOD(E$56-1,$C$21)-D$42-D$43)-D$41-D$44-D$45-IF(AND(MOD(E$56,$C$21)=0,E$56<Rates!$D$71),D$34,0),0) | F59: =IF(F$56<=Rates!$D$71,(D$40*(1+D$50)^MOD(F$56-1,$C$21)-D$42-D$43)-D$41-D$44-D$45-IF(AND(MOD(F$56,$C$21)=0,F$56<Rates!$D$71),D$34,0),0) | G59: =IF(G$56<=Rates!$D$71,(D$40*(1+D$50)^MOD(G$56-1,$C$21)-D$42-D$43)-D$41-D$44-D$45-IF(AND(MOD(G$56,$C$21)=0,G$56<Rates!$D$71),D$34,0),0) | H59: =IF(H$56<=Rates!$D$71,(D$40*(1+D$50)^MOD(H$56-1,$C$21)-D$42-D$43)-D$41-D$44-D$45-IF(AND(MOD(H$56,$C$21)=0,H$56<Rates!$D$71),D$34,0),0) | I59: =IF(I$56<=Rates!$D$71,(D$40*(1+D$50)^MOD(I$56-1,$C$21)-D$42-D$43)-D$41-D$44-D$45-IF(AND(MOD(I$56,$C$21)=0,I$56<Rates!$D$71),D$34,0),0) | J59: =IF(J$56<=Rates!$D$71,(D$40*(1+D$50)^MOD(J$56-1,$C$21)-D$42-D$43)-D$41-D$44-D$45-IF(AND(MOD(J$56,$C$21)=0,J$56<Rates!$D$71),D$34,0),0) | K59: =IF(K$56<=Rates!$D$71,(D$40*(1+D$50)^MOD(K$56-1,$C$21)-D$42-D$43)-D$41-D$44-D$45-IF(AND(MOD(K$56,$C$21)=0,K$56<Rates!$D$71),D$34,0),0) | L59: =IF(L$56<=Rates!$D$71,(D$40*(1+D$50)^MOD(L$56-1,$C$21)-D$42-D$43)-D$41-D$44-D$45-IF(AND(MOD(L$56,$C$21)=0,L$56<Rates!$D$71),D$34,0),0) | M59: =IF(M$56<=Rates!$D$71,(D$40*(1+D$50)^MOD(M$56-1,$C$21)-D$42-D$43)-D$41-D$44-D$45-IF(AND(MOD(M$56,$C$21)=0,M$56<Rates!$D$71),D$34,0),0) | N59: =IF(N$56<=Rates!$D$71,(D$40*(1+D$50)^MOD(N$56-1,$C$21)-D$42-D$43)-D$41-D$44-D$45-IF(AND(MOD(N$56,$C$21)=0,N$56<Rates!$D$71),D$34,0),0) | O59: =IF(O$56<=Rates!$D$71,(D$40*(1+D$50)^MOD(O$56-1,$C$21)-D$42-D$43)-D$41-D$44-D$45-IF(AND(MOD(O$56,$C$21)=0,O$56<Rates!$D$71),D$34,0),0) | P59: =IF(P$56<=Rates!$D$71,(D$40*(1+D$50)^MOD(P$56-1,$C$21)-D$42-D$43)-D$41-D$44-D$45-IF(AND(MOD(P$56,$C$21)=0,P$56<Rates!$D$71),D$34,0),0) | Q59: =IF(Q$56<=Rates!$D$71,(D$40*(1+D$50)^MOD(Q$56-1,$C$21)-D$42-D$43)-D$41-D$44-D$45-IF(AND(MOD(Q$56,$C$21)=0,Q$56<Rates!$D$71),D$34,0),0) | R59: =IF(R$56<=Rates!$D$71,(D$40*(1+D$50)^MOD(R$56-1,$C$21)-D$42-D$43)-D$41-D$44-D$45-IF(AND(MOD(R$56,$C$21)=0,R$56<Rates!$D$71),D$34,0),0) | S59: =IF(S$56<=Rates!$D$71,(D$40*(1+D$50)^MOD(S$56-1,$C$21)-D$42-D$43)-D$41-D$44-D$45-IF(AND(MOD(S$56,$C$21)=0,S$56<Rates!$D$71),D$34,0),0) | T59: =IF(T$56<=Rates!$D$71,(D$40*(1+D$50)^MOD(T$56-1,$C$21)-D$42-D$43)-D$41-D$44-D$45-IF(AND(MOD(T$56,$C$21)=0,T$56<Rates!$D$71),D$34,0),0) | U59: =IF(U$56<=Rates!$D$71,(D$40*(1+D$50)^MOD(U$56-1,$C$21)-D$42-D$43)-D$41-D$44-D$45-IF(AND(MOD(U$56,$C$21)=0,U$56<Rates!$D$71),D$34,0),0) | V59: =IF(V$56<=Rates!$D$71,(D$40*(1+D$50)^MOD(V$56-1,$C$21)-D$42-D$43)-D$41-D$44-D$45-IF(AND(MOD(V$56,$C$21)=0,V$56<Rates!$D$71),D$34,0),0) | W59: =IF(W$56<=Rates!$D$71,(D$40*(1+D$50)^MOD(W$56-1,$C$21)-D$42-D$43)-D$41-D$44-D$45-IF(AND(MOD(W$56,$C$21)=0,W$56<Rates!$D$71),D$34,0),0) | X59: =IF(X$56<=Rates!$D$71,(D$40*(1+D$50)^MOD(X$56-1,$C$21)-D$42-D$43)-D$41-D$44-D$45-IF(AND(MOD(X$56,$C$21)=0,X$56<Rates!$D$71),D$34,0),0) | Y59: =IF(Y$56<=Rates!$D$71,(D$40*(1+D$50)^MOD(Y$56-1,$C$21)-D$42-D$43)-D$41-D$44-D$45-IF(AND(MOD(Y$56,$C$21)=0,Y$56<Rates!$D$71),D$34,0),0) | Z59: =IF(Z$56<=Rates!$D$71,(D$40*(1+D$50)^MOD(Z$56-1,$C$21)-D$42-D$43)-D$41-D$44-D$45-IF(AND(MOD(Z$56,$C$21)=0,Z$56<Rates!$D$71),D$34,0),0) | AA59: =IF(AA$56<=Rates!$D$71,(D$40*(1+D$50)^MOD(AA$56-1,$C$21)-D$42-D$43)-D$41-D$44-D$45-IF(AND(MOD(AA$56,$C$21)=0,AA$56<Rates!$D$71),D$34,0),0) | AB59: =IF(AB$56<=Rates!$D$71,(D$40*(1+D$50)^MOD(AB$56-1,$C$21)-D$42-D$43)-D$41-D$44-D$45-IF(AND(MOD(AB$56,$C$21)=0,AB$56<Rates!$D$71),D$34,0),0)
A60: Cash flow: NZ, flat prices | C60: =-E$36 | D60: =IF(D$56<=Rates!$D$71,(E$40*(1+E$50)^MOD(D$56-1,$C$21)-E$42-E$43)-E$41-E$44-E$45-IF(AND(MOD(D$56,$C$21)=0,D$56<Rates!$D$71),E$34,0),0) | E60: =IF(E$56<=Rates!$D$71,(E$40*(1+E$50)^MOD(E$56-1,$C$21)-E$42-E$43)-E$41-E$44-E$45-IF(AND(MOD(E$56,$C$21)=0,E$56<Rates!$D$71),E$34,0),0) | F60: =IF(F$56<=Rates!$D$71,(E$40*(1+E$50)^MOD(F$56-1,$C$21)-E$42-E$43)-E$41-E$44-E$45-IF(AND(MOD(F$56,$C$21)=0,F$56<Rates!$D$71),E$34,0),0) | G60: =IF(G$56<=Rates!$D$71,(E$40*(1+E$50)^MOD(G$56-1,$C$21)-E$42-E$43)-E$41-E$44-E$45-IF(AND(MOD(G$56,$C$21)=0,G$56<Rates!$D$71),E$34,0),0) | H60: =IF(H$56<=Rates!$D$71,(E$40*(1+E$50)^MOD(H$56-1,$C$21)-E$42-E$43)-E$41-E$44-E$45-IF(AND(MOD(H$56,$C$21)=0,H$56<Rates!$D$71),E$34,0),0) | I60: =IF(I$56<=Rates!$D$71,(E$40*(1+E$50)^MOD(I$56-1,$C$21)-E$42-E$43)-E$41-E$44-E$45-IF(AND(MOD(I$56,$C$21)=0,I$56<Rates!$D$71),E$34,0),0) | J60: =IF(J$56<=Rates!$D$71,(E$40*(1+E$50)^MOD(J$56-1,$C$21)-E$42-E$43)-E$41-E$44-E$45-IF(AND(MOD(J$56,$C$21)=0,J$56<Rates!$D$71),E$34,0),0) | K60: =IF(K$56<=Rates!$D$71,(E$40*(1+E$50)^MOD(K$56-1,$C$21)-E$42-E$43)-E$41-E$44-E$45-IF(AND(MOD(K$56,$C$21)=0,K$56<Rates!$D$71),E$34,0),0) | L60: =IF(L$56<=Rates!$D$71,(E$40*(1+E$50)^MOD(L$56-1,$C$21)-E$42-E$43)-E$41-E$44-E$45-IF(AND(MOD(L$56,$C$21)=0,L$56<Rates!$D$71),E$34,0),0) | M60: =IF(M$56<=Rates!$D$71,(E$40*(1+E$50)^MOD(M$56-1,$C$21)-E$42-E$43)-E$41-E$44-E$45-IF(AND(MOD(M$56,$C$21)=0,M$56<Rates!$D$71),E$34,0),0) | N60: =IF(N$56<=Rates!$D$71,(E$40*(1+E$50)^MOD(N$56-1,$C$21)-E$42-E$43)-E$41-E$44-E$45-IF(AND(MOD(N$56,$C$21)=0,N$56<Rates!$D$71),E$34,0),0) | O60: =IF(O$56<=Rates!$D$71,(E$40*(1+E$50)^MOD(O$56-1,$C$21)-E$42-E$43)-E$41-E$44-E$45-IF(AND(MOD(O$56,$C$21)=0,O$56<Rates!$D$71),E$34,0),0) | P60: =IF(P$56<=Rates!$D$71,(E$40*(1+E$50)^MOD(P$56-1,$C$21)-E$42-E$43)-E$41-E$44-E$45-IF(AND(MOD(P$56,$C$21)=0,P$56<Rates!$D$71),E$34,0),0) | Q60: =IF(Q$56<=Rates!$D$71,(E$40*(1+E$50)^MOD(Q$56-1,$C$21)-E$42-E$43)-E$41-E$44-E$45-IF(AND(MOD(Q$56,$C$21)=0,Q$56<Rates!$D$71),E$34,0),0) | R60: =IF(R$56<=Rates!$D$71,(E$40*(1+E$50)^MOD(R$56-1,$C$21)-E$42-E$43)-E$41-E$44-E$45-IF(AND(MOD(R$56,$C$21)=0,R$56<Rates!$D$71),E$34,0),0) | S60: =IF(S$56<=Rates!$D$71,(E$40*(1+E$50)^MOD(S$56-1,$C$21)-E$42-E$43)-E$41-E$44-E$45-IF(AND(MOD(S$56,$C$21)=0,S$56<Rates!$D$71),E$34,0),0) | T60: =IF(T$56<=Rates!$D$71,(E$40*(1+E$50)^MOD(T$56-1,$C$21)-E$42-E$43)-E$41-E$44-E$45-IF(AND(MOD(T$56,$C$21)=0,T$56<Rates!$D$71),E$34,0),0) | U60: =IF(U$56<=Rates!$D$71,(E$40*(1+E$50)^MOD(U$56-1,$C$21)-E$42-E$43)-E$41-E$44-E$45-IF(AND(MOD(U$56,$C$21)=0,U$56<Rates!$D$71),E$34,0),0) | V60: =IF(V$56<=Rates!$D$71,(E$40*(1+E$50)^MOD(V$56-1,$C$21)-E$42-E$43)-E$41-E$44-E$45-IF(AND(MOD(V$56,$C$21)=0,V$56<Rates!$D$71),E$34,0),0) | W60: =IF(W$56<=Rates!$D$71,(E$40*(1+E$50)^MOD(W$56-1,$C$21)-E$42-E$43)-E$41-E$44-E$45-IF(AND(MOD(W$56,$C$21)=0,W$56<Rates!$D$71),E$34,0),0) | X60: =IF(X$56<=Rates!$D$71,(E$40*(1+E$50)^MOD(X$56-1,$C$21)-E$42-E$43)-E$41-E$44-E$45-IF(AND(MOD(X$56,$C$21)=0,X$56<Rates!$D$71),E$34,0),0) | Y60: =IF(Y$56<=Rates!$D$71,(E$40*(1+E$50)^MOD(Y$56-1,$C$21)-E$42-E$43)-E$41-E$44-E$45-IF(AND(MOD(Y$56,$C$21)=0,Y$56<Rates!$D$71),E$34,0),0) | Z60: =IF(Z$56<=Rates!$D$71,(E$40*(1+E$50)^MOD(Z$56-1,$C$21)-E$42-E$43)-E$41-E$44-E$45-IF(AND(MOD(Z$56,$C$21)=0,Z$56<Rates!$D$71),E$34,0),0) | AA60: =IF(AA$56<=Rates!$D$71,(E$40*(1+E$50)^MOD(AA$56-1,$C$21)-E$42-E$43)-E$41-E$44-E$45-IF(AND(MOD(AA$56,$C$21)=0,AA$56<Rates!$D$71),E$34,0),0) | AB60: =IF(AB$56<=Rates!$D$71,(E$40*(1+E$50)^MOD(AB$56-1,$C$21)-E$42-E$43)-E$41-E$44-E$45-IF(AND(MOD(AB$56,$C$21)=0,AB$56<Rates!$D$71),E$34,0),0)
A61: Cash flow: AU downside: 47% util, 20% remote discount, decay | C61: =-F$36 | D61: =IF(D$56<=Rates!$D$71,(F$40*(1+F$50)^MOD(D$56-1,$C$21)-F$42-F$43)*D$65-F$41-F$44-F$45-IF(AND(MOD(D$56,$C$21)=0,D$56<Rates!$D$71),F$34*D$65,0),0) | E61: =IF(E$56<=Rates!$D$71,(F$40*(1+F$50)^MOD(E$56-1,$C$21)-F$42-F$43)*E$65-F$41-F$44-F$45-IF(AND(MOD(E$56,$C$21)=0,E$56<Rates!$D$71),F$34*E$65,0),0) | F61: =IF(F$56<=Rates!$D$71,(F$40*(1+F$50)^MOD(F$56-1,$C$21)-F$42-F$43)*F$65-F$41-F$44-F$45-IF(AND(MOD(F$56,$C$21)=0,F$56<Rates!$D$71),F$34*F$65,0),0) | G61: =IF(G$56<=Rates!$D$71,(F$40*(1+F$50)^MOD(G$56-1,$C$21)-F$42-F$43)*G$65-F$41-F$44-F$45-IF(AND(MOD(G$56,$C$21)=0,G$56<Rates!$D$71),F$34*G$65,0),0) | H61: =IF(H$56<=Rates!$D$71,(F$40*(1+F$50)^MOD(H$56-1,$C$21)-F$42-F$43)*H$65-F$41-F$44-F$45-IF(AND(MOD(H$56,$C$21)=0,H$56<Rates!$D$71),F$34*H$65,0),0) | I61: =IF(I$56<=Rates!$D$71,(F$40*(1+F$50)^MOD(I$56-1,$C$21)-F$42-F$43)*I$65-F$41-F$44-F$45-IF(AND(MOD(I$56,$C$21)=0,I$56<Rates!$D$71),F$34*I$65,0),0) | J61: =IF(J$56<=Rates!$D$71,(F$40*(1+F$50)^MOD(J$56-1,$C$21)-F$42-F$43)*J$65-F$41-F$44-F$45-IF(AND(MOD(J$56,$C$21)=0,J$56<Rates!$D$71),F$34*J$65,0),0) | K61: =IF(K$56<=Rates!$D$71,(F$40*(1+F$50)^MOD(K$56-1,$C$21)-F$42-F$43)*K$65-F$41-F$44-F$45-IF(AND(MOD(K$56,$C$21)=0,K$56<Rates!$D$71),F$34*K$65,0),0) | L61: =IF(L$56<=Rates!$D$71,(F$40*(1+F$50)^MOD(L$56-1,$C$21)-F$42-F$43)*L$65-F$41-F$44-F$45-IF(AND(MOD(L$56,$C$21)=0,L$56<Rates!$D$71),F$34*L$65,0),0) | M61: =IF(M$56<=Rates!$D$71,(F$40*(1+F$50)^MOD(M$56-1,$C$21)-F$42-F$43)*M$65-F$41-F$44-F$45-IF(AND(MOD(M$56,$C$21)=0,M$56<Rates!$D$71),F$34*M$65,0),0) | N61: =IF(N$56<=Rates!$D$71,(F$40*(1+F$50)^MOD(N$56-1,$C$21)-F$42-F$43)*N$65-F$41-F$44-F$45-IF(AND(MOD(N$56,$C$21)=0,N$56<Rates!$D$71),F$34*N$65,0),0) | O61: =IF(O$56<=Rates!$D$71,(F$40*(1+F$50)^MOD(O$56-1,$C$21)-F$42-F$43)*O$65-F$41-F$44-F$45-IF(AND(MOD(O$56,$C$21)=0,O$56<Rates!$D$71),F$34*O$65,0),0) | P61: =IF(P$56<=Rates!$D$71,(F$40*(1+F$50)^MOD(P$56-1,$C$21)-F$42-F$43)*P$65-F$41-F$44-F$45-IF(AND(MOD(P$56,$C$21)=0,P$56<Rates!$D$71),F$34*P$65,0),0) | Q61: =IF(Q$56<=Rates!$D$71,(F$40*(1+F$50)^MOD(Q$56-1,$C$21)-F$42-F$43)*Q$65-F$41-F$44-F$45-IF(AND(MOD(Q$56,$C$21)=0,Q$56<Rates!$D$71),F$34*Q$65,0),0) | R61: =IF(R$56<=Rates!$D$71,(F$40*(1+F$50)^MOD(R$56-1,$C$21)-F$42-F$43)*R$65-F$41-F$44-F$45-IF(AND(MOD(R$56,$C$21)=0,R$56<Rates!$D$71),F$34*R$65,0),0) | S61: =IF(S$56<=Rates!$D$71,(F$40*(1+F$50)^MOD(S$56-1,$C$21)-F$42-F$43)*S$65-F$41-F$44-F$45-IF(AND(MOD(S$56,$C$21)=0,S$56<Rates!$D$71),F$34*S$65,0),0) | T61: =IF(T$56<=Rates!$D$71,(F$40*(1+F$50)^MOD(T$56-1,$C$21)-F$42-F$43)*T$65-F$41-F$44-F$45-IF(AND(MOD(T$56,$C$21)=0,T$56<Rates!$D$71),F$34*T$65,0),0) | U61: =IF(U$56<=Rates!$D$71,(F$40*(1+F$50)^MOD(U$56-1,$C$21)-F$42-F$43)*U$65-F$41-F$44-F$45-IF(AND(MOD(U$56,$C$21)=0,U$56<Rates!$D$71),F$34*U$65,0),0) | V61: =IF(V$56<=Rates!$D$71,(F$40*(1+F$50)^MOD(V$56-1,$C$21)-F$42-F$43)*V$65-F$41-F$44-F$45-IF(AND(MOD(V$56,$C$21)=0,V$56<Rates!$D$71),F$34*V$65,0),0) | W61: =IF(W$56<=Rates!$D$71,(F$40*(1+F$50)^MOD(W$56-1,$C$21)-F$42-F$43)*W$65-F$41-F$44-F$45-IF(AND(MOD(W$56,$C$21)=0,W$56<Rates!$D$71),F$34*W$65,0),0) | X61: =IF(X$56<=Rates!$D$71,(F$40*(1+F$50)^MOD(X$56-1,$C$21)-F$42-F$43)*X$65-F$41-F$44-F$45-IF(AND(MOD(X$56,$C$21)=0,X$56<Rates!$D$71),F$34*X$65,0),0) | Y61: =IF(Y$56<=Rates!$D$71,(F$40*(1+F$50)^MOD(Y$56-1,$C$21)-F$42-F$43)*Y$65-F$41-F$44-F$45-IF(AND(MOD(Y$56,$C$21)=0,Y$56<Rates!$D$71),F$34*Y$65,0),0) | Z61: =IF(Z$56<=Rates!$D$71,(F$40*(1+F$50)^MOD(Z$56-1,$C$21)-F$42-F$43)*Z$65-F$41-F$44-F$45-IF(AND(MOD(Z$56,$C$21)=0,Z$56<Rates!$D$71),F$34*Z$65,0),0) | AA61: =IF(AA$56<=Rates!$D$71,(F$40*(1+F$50)^MOD(AA$56-1,$C$21)-F$42-F$43)*AA$65-F$41-F$44-F$45-IF(AND(MOD(AA$56,$C$21)=0,AA$56<Rates!$D$71),F$34*AA$65,0),0) | AB61: =IF(AB$56<=Rates!$D$71,(F$40*(1+F$50)^MOD(AB$56-1,$C$21)-F$42-F$43)*AB$65-F$41-F$44-F$45-IF(AND(MOD(AB$56,$C$21)=0,AB$56<Rates!$D$71),F$34*AB$65,0),0)
A62: Cash flow: AU ComputeCo (transfer price), decay | C62: =-G$36 | D62: =IF(D$56<=Rates!$D$71,(G$40*(1+G$50)^MOD(D$56-1,$C$21)-G$42-G$43)*D$65-G$41-G$44-G$45-IF(AND(MOD(D$56,$C$21)=0,D$56<Rates!$D$71),G$34*D$65,0),0) | E62: =IF(E$56<=Rates!$D$71,(G$40*(1+G$50)^MOD(E$56-1,$C$21)-G$42-G$43)*E$65-G$41-G$44-G$45-IF(AND(MOD(E$56,$C$21)=0,E$56<Rates!$D$71),G$34*E$65,0),0) | F62: =IF(F$56<=Rates!$D$71,(G$40*(1+G$50)^MOD(F$56-1,$C$21)-G$42-G$43)*F$65-G$41-G$44-G$45-IF(AND(MOD(F$56,$C$21)=0,F$56<Rates!$D$71),G$34*F$65,0),0) | G62: =IF(G$56<=Rates!$D$71,(G$40*(1+G$50)^MOD(G$56-1,$C$21)-G$42-G$43)*G$65-G$41-G$44-G$45-IF(AND(MOD(G$56,$C$21)=0,G$56<Rates!$D$71),G$34*G$65,0),0) | H62: =IF(H$56<=Rates!$D$71,(G$40*(1+G$50)^MOD(H$56-1,$C$21)-G$42-G$43)*H$65-G$41-G$44-G$45-IF(AND(MOD(H$56,$C$21)=0,H$56<Rates!$D$71),G$34*H$65,0),0) | I62: =IF(I$56<=Rates!$D$71,(G$40*(1+G$50)^MOD(I$56-1,$C$21)-G$42-G$43)*I$65-G$41-G$44-G$45-IF(AND(MOD(I$56,$C$21)=0,I$56<Rates!$D$71),G$34*I$65,0),0) | J62: =IF(J$56<=Rates!$D$71,(G$40*(1+G$50)^MOD(J$56-1,$C$21)-G$42-G$43)*J$65-G$41-G$44-G$45-IF(AND(MOD(J$56,$C$21)=0,J$56<Rates!$D$71),G$34*J$65,0),0) | K62: =IF(K$56<=Rates!$D$71,(G$40*(1+G$50)^MOD(K$56-1,$C$21)-G$42-G$43)*K$65-G$41-G$44-G$45-IF(AND(MOD(K$56,$C$21)=0,K$56<Rates!$D$71),G$34*K$65,0),0) | L62: =IF(L$56<=Rates!$D$71,(G$40*(1+G$50)^MOD(L$56-1,$C$21)-G$42-G$43)*L$65-G$41-G$44-G$45-IF(AND(MOD(L$56,$C$21)=0,L$56<Rates!$D$71),G$34*L$65,0),0) | M62: =IF(M$56<=Rates!$D$71,(G$40*(1+G$50)^MOD(M$56-1,$C$21)-G$42-G$43)*M$65-G$41-G$44-G$45-IF(AND(MOD(M$56,$C$21)=0,M$56<Rates!$D$71),G$34*M$65,0),0) | N62: =IF(N$56<=Rates!$D$71,(G$40*(1+G$50)^MOD(N$56-1,$C$21)-G$42-G$43)*N$65-G$41-G$44-G$45-IF(AND(MOD(N$56,$C$21)=0,N$56<Rates!$D$71),G$34*N$65,0),0) | O62: =IF(O$56<=Rates!$D$71,(G$40*(1+G$50)^MOD(O$56-1,$C$21)-G$42-G$43)*O$65-G$41-G$44-G$45-IF(AND(MOD(O$56,$C$21)=0,O$56<Rates!$D$71),G$34*O$65,0),0) | P62: =IF(P$56<=Rates!$D$71,(G$40*(1+G$50)^MOD(P$56-1,$C$21)-G$42-G$43)*P$65-G$41-G$44-G$45-IF(AND(MOD(P$56,$C$21)=0,P$56<Rates!$D$71),G$34*P$65,0),0) | Q62: =IF(Q$56<=Rates!$D$71,(G$40*(1+G$50)^MOD(Q$56-1,$C$21)-G$42-G$43)*Q$65-G$41-G$44-G$45-IF(AND(MOD(Q$56,$C$21)=0,Q$56<Rates!$D$71),G$34*Q$65,0),0) | R62: =IF(R$56<=Rates!$D$71,(G$40*(1+G$50)^MOD(R$56-1,$C$21)-G$42-G$43)*R$65-G$41-G$44-G$45-IF(AND(MOD(R$56,$C$21)=0,R$56<Rates!$D$71),G$34*R$65,0),0) | S62: =IF(S$56<=Rates!$D$71,(G$40*(1+G$50)^MOD(S$56-1,$C$21)-G$42-G$43)*S$65-G$41-G$44-G$45-IF(AND(MOD(S$56,$C$21)=0,S$56<Rates!$D$71),G$34*S$65,0),0) | T62: =IF(T$56<=Rates!$D$71,(G$40*(1+G$50)^MOD(T$56-1,$C$21)-G$42-G$43)*T$65-G$41-G$44-G$45-IF(AND(MOD(T$56,$C$21)=0,T$56<Rates!$D$71),G$34*T$65,0),0) | U62: =IF(U$56<=Rates!$D$71,(G$40*(1+G$50)^MOD(U$56-1,$C$21)-G$42-G$43)*U$65-G$41-G$44-G$45-IF(AND(MOD(U$56,$C$21)=0,U$56<Rates!$D$71),G$34*U$65,0),0) | V62: =IF(V$56<=Rates!$D$71,(G$40*(1+G$50)^MOD(V$56-1,$C$21)-G$42-G$43)*V$65-G$41-G$44-G$45-IF(AND(MOD(V$56,$C$21)=0,V$56<Rates!$D$71),G$34*V$65,0),0) | W62: =IF(W$56<=Rates!$D$71,(G$40*(1+G$50)^MOD(W$56-1,$C$21)-G$42-G$43)*W$65-G$41-G$44-G$45-IF(AND(MOD(W$56,$C$21)=0,W$56<Rates!$D$71),G$34*W$65,0),0) | X62: =IF(X$56<=Rates!$D$71,(G$40*(1+G$50)^MOD(X$56-1,$C$21)-G$42-G$43)*X$65-G$41-G$44-G$45-IF(AND(MOD(X$56,$C$21)=0,X$56<Rates!$D$71),G$34*X$65,0),0) | Y62: =IF(Y$56<=Rates!$D$71,(G$40*(1+G$50)^MOD(Y$56-1,$C$21)-G$42-G$43)*Y$65-G$41-G$44-G$45-IF(AND(MOD(Y$56,$C$21)=0,Y$56<Rates!$D$71),G$34*Y$65,0),0) | Z62: =IF(Z$56<=Rates!$D$71,(G$40*(1+G$50)^MOD(Z$56-1,$C$21)-G$42-G$43)*Z$65-G$41-G$44-G$45-IF(AND(MOD(Z$56,$C$21)=0,Z$56<Rates!$D$71),G$34*Z$65,0),0) | AA62: =IF(AA$56<=Rates!$D$71,(G$40*(1+G$50)^MOD(AA$56-1,$C$21)-G$42-G$43)*AA$65-G$41-G$44-G$45-IF(AND(MOD(AA$56,$C$21)=0,AA$56<Rates!$D$71),G$34*AA$65,0),0) | AB62: =IF(AB$56<=Rates!$D$71,(G$40*(1+G$50)^MOD(AB$56-1,$C$21)-G$42-G$43)*AB$65-G$41-G$44-G$45-IF(AND(MOD(AB$56,$C$21)=0,AB$56<Rates!$D$71),G$34*AB$65,0),0)
A63: Cash flow: AU ComputeCo (transfer price), flat | C63: =-H$36 | D63: =IF(D$56<=Rates!$D$71,(H$40*(1+H$50)^MOD(D$56-1,$C$21)-H$42-H$43)*D$65-H$41-H$44-H$45-IF(AND(MOD(D$56,$C$21)=0,D$56<Rates!$D$71),H$34*D$65,0),0) | E63: =IF(E$56<=Rates!$D$71,(H$40*(1+H$50)^MOD(E$56-1,$C$21)-H$42-H$43)*E$65-H$41-H$44-H$45-IF(AND(MOD(E$56,$C$21)=0,E$56<Rates!$D$71),H$34*E$65,0),0) | F63: =IF(F$56<=Rates!$D$71,(H$40*(1+H$50)^MOD(F$56-1,$C$21)-H$42-H$43)*F$65-H$41-H$44-H$45-IF(AND(MOD(F$56,$C$21)=0,F$56<Rates!$D$71),H$34*F$65,0),0) | G63: =IF(G$56<=Rates!$D$71,(H$40*(1+H$50)^MOD(G$56-1,$C$21)-H$42-H$43)*G$65-H$41-H$44-H$45-IF(AND(MOD(G$56,$C$21)=0,G$56<Rates!$D$71),H$34*G$65,0),0) | H63: =IF(H$56<=Rates!$D$71,(H$40*(1+H$50)^MOD(H$56-1,$C$21)-H$42-H$43)*H$65-H$41-H$44-H$45-IF(AND(MOD(H$56,$C$21)=0,H$56<Rates!$D$71),H$34*H$65,0),0) | I63: =IF(I$56<=Rates!$D$71,(H$40*(1+H$50)^MOD(I$56-1,$C$21)-H$42-H$43)*I$65-H$41-H$44-H$45-IF(AND(MOD(I$56,$C$21)=0,I$56<Rates!$D$71),H$34*I$65,0),0) | J63: =IF(J$56<=Rates!$D$71,(H$40*(1+H$50)^MOD(J$56-1,$C$21)-H$42-H$43)*J$65-H$41-H$44-H$45-IF(AND(MOD(J$56,$C$21)=0,J$56<Rates!$D$71),H$34*J$65,0),0) | K63: =IF(K$56<=Rates!$D$71,(H$40*(1+H$50)^MOD(K$56-1,$C$21)-H$42-H$43)*K$65-H$41-H$44-H$45-IF(AND(MOD(K$56,$C$21)=0,K$56<Rates!$D$71),H$34*K$65,0),0) | L63: =IF(L$56<=Rates!$D$71,(H$40*(1+H$50)^MOD(L$56-1,$C$21)-H$42-H$43)*L$65-H$41-H$44-H$45-IF(AND(MOD(L$56,$C$21)=0,L$56<Rates!$D$71),H$34*L$65,0),0) | M63: =IF(M$56<=Rates!$D$71,(H$40*(1+H$50)^MOD(M$56-1,$C$21)-H$42-H$43)*M$65-H$41-H$44-H$45-IF(AND(MOD(M$56,$C$21)=0,M$56<Rates!$D$71),H$34*M$65,0),0) | N63: =IF(N$56<=Rates!$D$71,(H$40*(1+H$50)^MOD(N$56-1,$C$21)-H$42-H$43)*N$65-H$41-H$44-H$45-IF(AND(MOD(N$56,$C$21)=0,N$56<Rates!$D$71),H$34*N$65,0),0) | O63: =IF(O$56<=Rates!$D$71,(H$40*(1+H$50)^MOD(O$56-1,$C$21)-H$42-H$43)*O$65-H$41-H$44-H$45-IF(AND(MOD(O$56,$C$21)=0,O$56<Rates!$D$71),H$34*O$65,0),0) | P63: =IF(P$56<=Rates!$D$71,(H$40*(1+H$50)^MOD(P$56-1,$C$21)-H$42-H$43)*P$65-H$41-H$44-H$45-IF(AND(MOD(P$56,$C$21)=0,P$56<Rates!$D$71),H$34*P$65,0),0) | Q63: =IF(Q$56<=Rates!$D$71,(H$40*(1+H$50)^MOD(Q$56-1,$C$21)-H$42-H$43)*Q$65-H$41-H$44-H$45-IF(AND(MOD(Q$56,$C$21)=0,Q$56<Rates!$D$71),H$34*Q$65,0),0) | R63: =IF(R$56<=Rates!$D$71,(H$40*(1+H$50)^MOD(R$56-1,$C$21)-H$42-H$43)*R$65-H$41-H$44-H$45-IF(AND(MOD(R$56,$C$21)=0,R$56<Rates!$D$71),H$34*R$65,0),0) | S63: =IF(S$56<=Rates!$D$71,(H$40*(1+H$50)^MOD(S$56-1,$C$21)-H$42-H$43)*S$65-H$41-H$44-H$45-IF(AND(MOD(S$56,$C$21)=0,S$56<Rates!$D$71),H$34*S$65,0),0) | T63: =IF(T$56<=Rates!$D$71,(H$40*(1+H$50)^MOD(T$56-1,$C$21)-H$42-H$43)*T$65-H$41-H$44-H$45-IF(AND(MOD(T$56,$C$21)=0,T$56<Rates!$D$71),H$34*T$65,0),0) | U63: =IF(U$56<=Rates!$D$71,(H$40*(1+H$50)^MOD(U$56-1,$C$21)-H$42-H$43)*U$65-H$41-H$44-H$45-IF(AND(MOD(U$56,$C$21)=0,U$56<Rates!$D$71),H$34*U$65,0),0) | V63: =IF(V$56<=Rates!$D$71,(H$40*(1+H$50)^MOD(V$56-1,$C$21)-H$42-H$43)*V$65-H$41-H$44-H$45-IF(AND(MOD(V$56,$C$21)=0,V$56<Rates!$D$71),H$34*V$65,0),0) | W63: =IF(W$56<=Rates!$D$71,(H$40*(1+H$50)^MOD(W$56-1,$C$21)-H$42-H$43)*W$65-H$41-H$44-H$45-IF(AND(MOD(W$56,$C$21)=0,W$56<Rates!$D$71),H$34*W$65,0),0) | X63: =IF(X$56<=Rates!$D$71,(H$40*(1+H$50)^MOD(X$56-1,$C$21)-H$42-H$43)*X$65-H$41-H$44-H$45-IF(AND(MOD(X$56,$C$21)=0,X$56<Rates!$D$71),H$34*X$65,0),0) | Y63: =IF(Y$56<=Rates!$D$71,(H$40*(1+H$50)^MOD(Y$56-1,$C$21)-H$42-H$43)*Y$65-H$41-H$44-H$45-IF(AND(MOD(Y$56,$C$21)=0,Y$56<Rates!$D$71),H$34*Y$65,0),0) | Z63: =IF(Z$56<=Rates!$D$71,(H$40*(1+H$50)^MOD(Z$56-1,$C$21)-H$42-H$43)*Z$65-H$41-H$44-H$45-IF(AND(MOD(Z$56,$C$21)=0,Z$56<Rates!$D$71),H$34*Z$65,0),0) | AA63: =IF(AA$56<=Rates!$D$71,(H$40*(1+H$50)^MOD(AA$56-1,$C$21)-H$42-H$43)*AA$65-H$41-H$44-H$45-IF(AND(MOD(AA$56,$C$21)=0,AA$56<Rates!$D$71),H$34*AA$65,0),0) | AB63: =IF(AB$56<=Rates!$D$71,(H$40*(1+H$50)^MOD(AB$56-1,$C$21)-H$42-H$43)*AB$65-H$41-H$44-H$45-IF(AND(MOD(AB$56,$C$21)=0,AB$56<Rates!$D$71),H$34*AB$65,0),0)
A64: Cash flow: AU colocation (rental), for comparison | C64: =-I$36 | D64: =IF(D$56<=Rates!$D$71,I$46-I$40*(1-D$65),0) | E64: =IF(E$56<=Rates!$D$71,I$46-I$40*(1-E$65),0) | F64: =IF(F$56<=Rates!$D$71,I$46-I$40*(1-F$65),0) | G64: =IF(G$56<=Rates!$D$71,I$46-I$40*(1-G$65),0) | H64: =IF(H$56<=Rates!$D$71,I$46-I$40*(1-H$65),0) | I64: =IF(I$56<=Rates!$D$71,I$46-I$40*(1-I$65),0) | J64: =IF(J$56<=Rates!$D$71,I$46-I$40*(1-J$65),0) | K64: =IF(K$56<=Rates!$D$71,I$46-I$40*(1-K$65),0) | L64: =IF(L$56<=Rates!$D$71,I$46-I$40*(1-L$65),0) | M64: =IF(M$56<=Rates!$D$71,I$46-I$40*(1-M$65),0) | N64: =IF(N$56<=Rates!$D$71,I$46-I$40*(1-N$65),0) | O64: =IF(O$56<=Rates!$D$71,I$46-I$40*(1-O$65),0) | P64: =IF(P$56<=Rates!$D$71,I$46-I$40*(1-P$65),0) | Q64: =IF(Q$56<=Rates!$D$71,I$46-I$40*(1-Q$65),0) | R64: =IF(R$56<=Rates!$D$71,I$46-I$40*(1-R$65),0) | S64: =IF(S$56<=Rates!$D$71,I$46-I$40*(1-S$65),0) | T64: =IF(T$56<=Rates!$D$71,I$46-I$40*(1-T$65),0) | U64: =IF(U$56<=Rates!$D$71,I$46-I$40*(1-U$65),0) | V64: =IF(V$56<=Rates!$D$71,I$46-I$40*(1-V$65),0) | W64: =IF(W$56<=Rates!$D$71,I$46-I$40*(1-W$65),0) | X64: =IF(X$56<=Rates!$D$71,I$46-I$40*(1-X$65),0) | Y64: =IF(Y$56<=Rates!$D$71,I$46-I$40*(1-Y$65),0) | Z64: =IF(Z$56<=Rates!$D$71,I$46-I$40*(1-Z$65),0) | AA64: =IF(AA$56<=Rates!$D$71,I$46-I$40*(1-AA$65),0) | AB64: =IF(AB$56<=Rates!$D$71,I$46-I$40*(1-AB$65),0)
A65: Lit-module share, AU (Decline tab, selected degC/yr on well capability; NZ buys grid power so is not affected) | D65: =Decline!D44/4 | E65: =Decline!E44/4 | F65: =Decline!F44/4 | G65: =Decline!G44/4 | H65: =Decline!H44/4 | I65: =Decline!I44/4 | J65: =Decline!J44/4 | K65: =Decline!K44/4 | ... AB65: =Decline!AB44/4
A67: SENSITIVITY: AU consolidated 25-yr IRR, price x utilisation, PRICES DECAY ~25%/yr within each 5-yr cycle
A68: US$/GPU-h \ utilisation | B68: =$C$18 | C68: =$C$19 | D68: =$C$20
A69: =$C$14 | B69: =IFERROR(IRR(C75:AB75),IF(SUM(C75:AB75)<0,"never repays","no IRR")) | C69: =IFERROR(IRR(C76:AB76),IF(SUM(C76:AB76)<0,"never repays","no IRR")) | D69: =IFERROR(IRR(C77:AB77),IF(SUM(C77:AB77)<0,"never repays","no IRR"))
A70: =$C$15 | B70: =IFERROR(IRR(C78:AB78),IF(SUM(C78:AB78)<0,"never repays","no IRR")) | C70: =IFERROR(IRR(C79:AB79),IF(SUM(C79:AB79)<0,"never repays","no IRR")) | D70: =IFERROR(IRR(C80:AB80),IF(SUM(C80:AB80)<0,"never repays","no IRR"))
A71: =$C$16 | B71: =IFERROR(IRR(C81:AB81),IF(SUM(C81:AB81)<0,"never repays","no IRR")) | C71: =IFERROR(IRR(C82:AB82),IF(SUM(C82:AB82)<0,"never repays","no IRR")) | D71: =IFERROR(IRR(C83:AB83),IF(SUM(C83:AB83)<0,"never repays","no IRR"))
A72: =$C$17 | B72: =IFERROR(IRR(C84:AB84),IF(SUM(C84:AB84)<0,"never repays","no IRR")) | C72: =IFERROR(IRR(C85:AB85),IF(SUM(C85:AB85)<0,"never repays","no IRR")) | D72: =IFERROR(IRR(C86:AB86),IF(SUM(C86:AB86)<0,"never repays","no IRR"))
A75: helper: p_low x u_low | C75: =-B$36 | D75: =IF(D$56<=Rates!$D$71,B$33*8760*$C$18*$C$14*Connectivity!$C$13/Rates!$D$4*(1+$C$22)^MOD(D$56-1,$C$21)*D$65-('Compute-Revenue'!$B$23+$C$9*B$34+B$43+B$44+B$45)-IF(AND(MOD(D$56,$C$21)=0,D$56<Rates!$D$71),B$34,0),0) | E75: =IF(E$56<=Rates!$D$71,B$33*8760*$C$18*$C$14*Connectivity!$C$13/Rates!$D$4*(1+$C$22)^MOD(E$56-1,$C$21)*E$65-('Compute-Revenue'!$B$23+$C$9*B$34+B$43+B$44+B$45)-IF(AND(MOD(E$56,$C$21)=0,E$56<Rates!$D$71),B$34,0),0) | F75: =IF(F$56<=Rates!$D$71,B$33*8760*$C$18*$C$14*Connectivity!$C$13/Rates!$D$4*(1+$C$22)^MOD(F$56-1,$C$21)*F$65-('Compute-Revenue'!$B$23+$C$9*B$34+B$43+B$44+B$45)-IF(AND(MOD(F$56,$C$21)=0,F$56<Rates!$D$71),B$34,0),0) | G75: =IF(G$56<=Rates!$D$71,B$33*8760*$C$18*$C$14*Connectivity!$C$13/Rates!$D$4*(1+$C$22)^MOD(G$56-1,$C$21)*G$65-('Compute-Revenue'!$B$23+$C$9*B$34+B$43+B$44+B$45)-IF(AND(MOD(G$56,$C$21)=0,G$56<Rates!$D$71),B$34,0),0) | H75: =IF(H$56<=Rates!$D$71,B$33*8760*$C$18*$C$14*Connectivity!$C$13/Rates!$D$4*(1+$C$22)^MOD(H$56-1,$C$21)*H$65-('Compute-Revenue'!$B$23+$C$9*B$34+B$43+B$44+B$45)-IF(AND(MOD(H$56,$C$21)=0,H$56<Rates!$D$71),B$34,0),0) | I75: =IF(I$56<=Rates!$D$71,B$33*8760*$C$18*$C$14*Connectivity!$C$13/Rates!$D$4*(1+$C$22)^MOD(I$56-1,$C$21)*I$65-('Compute-Revenue'!$B$23+$C$9*B$34+B$43+B$44+B$45)-IF(AND(MOD(I$56,$C$21)=0,I$56<Rates!$D$71),B$34,0),0) | J75: =IF(J$56<=Rates!$D$71,B$33*8760*$C$18*$C$14*Connectivity!$C$13/Rates!$D$4*(1+$C$22)^MOD(J$56-1,$C$21)*J$65-('Compute-Revenue'!$B$23+$C$9*B$34+B$43+B$44+B$45)-IF(AND(MOD(J$56,$C$21)=0,J$56<Rates!$D$71),B$34,0),0) | K75: =IF(K$56<=Rates!$D$71,B$33*8760*$C$18*$C$14*Connectivity!$C$13/Rates!$D$4*(1+$C$22)^MOD(K$56-1,$C$21)*K$65-('Compute-Revenue'!$B$23+$C$9*B$34+B$43+B$44+B$45)-IF(AND(MOD(K$56,$C$21)=0,K$56<Rates!$D$71),B$34,0),0) | L75: =IF(L$56<=Rates!$D$71,B$33*8760*$C$18*$C$14*Connectivity!$C$13/Rates!$D$4*(1+$C$22)^MOD(L$56-1,$C$21)*L$65-('Compute-Revenue'!$B$23+$C$9*B$34+B$43+B$44+B$45)-IF(AND(MOD(L$56,$C$21)=0,L$56<Rates!$D$71),B$34,0),0) | M75: =IF(M$56<=Rates!$D$71,B$33*8760*$C$18*$C$14*Connectivity!$C$13/Rates!$D$4*(1+$C$22)^MOD(M$56-1,$C$21)*M$65-('Compute-Revenue'!$B$23+$C$9*B$34+B$43+B$44+B$45)-IF(AND(MOD(M$56,$C$21)=0,M$56<Rates!$D$71),B$34,0),0) | N75: =IF(N$56<=Rates!$D$71,B$33*8760*$C$18*$C$14*Connectivity!$C$13/Rates!$D$4*(1+$C$22)^MOD(N$56-1,$C$21)*N$65-('Compute-Revenue'!$B$23+$C$9*B$34+B$43+B$44+B$45)-IF(AND(MOD(N$56,$C$21)=0,N$56<Rates!$D$71),B$34,0),0) | O75: =IF(O$56<=Rates!$D$71,B$33*8760*$C$18*$C$14*Connectivity!$C$13/Rates!$D$4*(1+$C$22)^MOD(O$56-1,$C$21)*O$65-('Compute-Revenue'!$B$23+$C$9*B$34+B$43+B$44+B$45)-IF(AND(MOD(O$56,$C$21)=0,O$56<Rates!$D$71),B$34,0),0) | P75: =IF(P$56<=Rates!$D$71,B$33*8760*$C$18*$C$14*Connectivity!$C$13/Rates!$D$4*(1+$C$22)^MOD(P$56-1,$C$21)*P$65-('Compute-Revenue'!$B$23+$C$9*B$34+B$43+B$44+B$45)-IF(AND(MOD(P$56,$C$21)=0,P$56<Rates!$D$71),B$34,0),0) | Q75: =IF(Q$56<=Rates!$D$71,B$33*8760*$C$18*$C$14*Connectivity!$C$13/Rates!$D$4*(1+$C$22)^MOD(Q$56-1,$C$21)*Q$65-('Compute-Revenue'!$B$23+$C$9*B$34+B$43+B$44+B$45)-IF(AND(MOD(Q$56,$C$21)=0,Q$56<Rates!$D$71),B$34,0),0) | R75: =IF(R$56<=Rates!$D$71,B$33*8760*$C$18*$C$14*Connectivity!$C$13/Rates!$D$4*(1+$C$22)^MOD(R$56-1,$C$21)*R$65-('Compute-Revenue'!$B$23+$C$9*B$34+B$43+B$44+B$45)-IF(AND(MOD(R$56,$C$21)=0,R$56<Rates!$D$71),B$34,0),0) | S75: =IF(S$56<=Rates!$D$71,B$33*8760*$C$18*$C$14*Connectivity!$C$13/Rates!$D$4*(1+$C$22)^MOD(S$56-1,$C$21)*S$65-('Compute-Revenue'!$B$23+$C$9*B$34+B$43+B$44+B$45)-IF(AND(MOD(S$56,$C$21)=0,S$56<Rates!$D$71),B$34,0),0) | T75: =IF(T$56<=Rates!$D$71,B$33*8760*$C$18*$C$14*Connectivity!$C$13/Rates!$D$4*(1+$C$22)^MOD(T$56-1,$C$21)*T$65-('Compute-Revenue'!$B$23+$C$9*B$34+B$43+B$44+B$45)-IF(AND(MOD(T$56,$C$21)=0,T$56<Rates!$D$71),B$34,0),0) | U75: =IF(U$56<=Rates!$D$71,B$33*8760*$C$18*$C$14*Connectivity!$C$13/Rates!$D$4*(1+$C$22)^MOD(U$56-1,$C$21)*U$65-('Compute-Revenue'!$B$23+$C$9*B$34+B$43+B$44+B$45)-IF(AND(MOD(U$56,$C$21)=0,U$56<Rates!$D$71),B$34,0),0) | V75: =IF(V$56<=Rates!$D$71,B$33*8760*$C$18*$C$14*Connectivity!$C$13/Rates!$D$4*(1+$C$22)^MOD(V$56-1,$C$21)*V$65-('Compute-Revenue'!$B$23+$C$9*B$34+B$43+B$44+B$45)-IF(AND(MOD(V$56,$C$21)=0,V$56<Rates!$D$71),B$34,0),0) | W75: =IF(W$56<=Rates!$D$71,B$33*8760*$C$18*$C$14*Connectivity!$C$13/Rates!$D$4*(1+$C$22)^MOD(W$56-1,$C$21)*W$65-('Compute-Revenue'!$B$23+$C$9*B$34+B$43+B$44+B$45)-IF(AND(MOD(W$56,$C$21)=0,W$56<Rates!$D$71),B$34,0),0) | X75: =IF(X$56<=Rates!$D$71,B$33*8760*$C$18*$C$14*Connectivity!$C$13/Rates!$D$4*(1+$C$22)^MOD(X$56-1,$C$21)*X$65-('Compute-Revenue'!$B$23+$C$9*B$34+B$43+B$44+B$45)-IF(AND(MOD(X$56,$C$21)=0,X$56<Rates!$D$71),B$34,0),0) | Y75: =IF(Y$56<=Rates!$D$71,B$33*8760*$C$18*$C$14*Connectivity!$C$13/Rates!$D$4*(1+$C$22)^MOD(Y$56-1,$C$21)*Y$65-('Compute-Revenue'!$B$23+$C$9*B$34+B$43+B$44+B$45)-IF(AND(MOD(Y$56,$C$21)=0,Y$56<Rates!$D$71),B$34,0),0) | Z75: =IF(Z$56<=Rates!$D$71,B$33*8760*$C$18*$C$14*Connectivity!$C$13/Rates!$D$4*(1+$C$22)^MOD(Z$56-1,$C$21)*Z$65-('Compute-Revenue'!$B$23+$C$9*B$34+B$43+B$44+B$45)-IF(AND(MOD(Z$56,$C$21)=0,Z$56<Rates!$D$71),B$34,0),0) | AA75: =IF(AA$56<=Rates!$D$71,B$33*8760*$C$18*$C$14*Connectivity!$C$13/Rates!$D$4*(1+$C$22)^MOD(AA$56-1,$C$21)*AA$65-('Compute-Revenue'!$B$23+$C$9*B$34+B$43+B$44+B$45)-IF(AND(MOD(AA$56,$C$21)=0,AA$56<Rates!$D$71),B$34,0),0) | AB75: =IF(AB$56<=Rates!$D$71,B$33*8760*$C$18*$C$14*Connectivity!$C$13/Rates!$D$4*(1+$C$22)^MOD(AB$56-1,$C$21)*AB$65-('Compute-Revenue'!$B$23+$C$9*B$34+B$43+B$44+B$45)-IF(AND(MOD(AB$56,$C$21)=0,AB$56<Rates!$D$71),B$34,0),0)
A76: helper: p_low x u_base | C76: =-B$36 | D76: =IF(D$56<=Rates!$D$71,B$33*8760*$C$19*$C$14*Connectivity!$C$13/Rates!$D$4*(1+$C$22)^MOD(D$56-1,$C$21)*D$65-('Compute-Revenue'!$B$23+$C$9*B$34+B$43+B$44+B$45)-IF(AND(MOD(D$56,$C$21)=0,D$56<Rates!$D$71),B$34,0),0) | E76: =IF(E$56<=Rates!$D$71,B$33*8760*$C$19*$C$14*Connectivity!$C$13/Rates!$D$4*(1+$C$22)^MOD(E$56-1,$C$21)*E$65-('Compute-Revenue'!$B$23+$C$9*B$34+B$43+B$44+B$45)-IF(AND(MOD(E$56,$C$21)=0,E$56<Rates!$D$71),B$34,0),0) | F76: =IF(F$56<=Rates!$D$71,B$33*8760*$C$19*$C$14*Connectivity!$C$13/Rates!$D$4*(1+$C$22)^MOD(F$56-1,$C$21)*F$65-('Compute-Revenue'!$B$23+$C$9*B$34+B$43+B$44+B$45)-IF(AND(MOD(F$56,$C$21)=0,F$56<Rates!$D$71),B$34,0),0) | G76: =IF(G$56<=Rates!$D$71,B$33*8760*$C$19*$C$14*Connectivity!$C$13/Rates!$D$4*(1+$C$22)^MOD(G$56-1,$C$21)*G$65-('Compute-Revenue'!$B$23+$C$9*B$34+B$43+B$44+B$45)-IF(AND(MOD(G$56,$C$21)=0,G$56<Rates!$D$71),B$34,0),0) | H76: =IF(H$56<=Rates!$D$71,B$33*8760*$C$19*$C$14*Connectivity!$C$13/Rates!$D$4*(1+$C$22)^MOD(H$56-1,$C$21)*H$65-('Compute-Revenue'!$B$23+$C$9*B$34+B$43+B$44+B$45)-IF(AND(MOD(H$56,$C$21)=0,H$56<Rates!$D$71),B$34,0),0) | I76: =IF(I$56<=Rates!$D$71,B$33*8760*$C$19*$C$14*Connectivity!$C$13/Rates!$D$4*(1+$C$22)^MOD(I$56-1,$C$21)*I$65-('Compute-Revenue'!$B$23+$C$9*B$34+B$43+B$44+B$45)-IF(AND(MOD(I$56,$C$21)=0,I$56<Rates!$D$71),B$34,0),0) | J76: =IF(J$56<=Rates!$D$71,B$33*8760*$C$19*$C$14*Connectivity!$C$13/Rates!$D$4*(1+$C$22)^MOD(J$56-1,$C$21)*J$65-('Compute-Revenue'!$B$23+$C$9*B$34+B$43+B$44+B$45)-IF(AND(MOD(J$56,$C$21)=0,J$56<Rates!$D$71),B$34,0),0) | K76: =IF(K$56<=Rates!$D$71,B$33*8760*$C$19*$C$14*Connectivity!$C$13/Rates!$D$4*(1+$C$22)^MOD(K$56-1,$C$21)*K$65-('Compute-Revenue'!$B$23+$C$9*B$34+B$43+B$44+B$45)-IF(AND(MOD(K$56,$C$21)=0,K$56<Rates!$D$71),B$34,0),0) | L76: =IF(L$56<=Rates!$D$71,B$33*8760*$C$19*$C$14*Connectivity!$C$13/Rates!$D$4*(1+$C$22)^MOD(L$56-1,$C$21)*L$65-('Compute-Revenue'!$B$23+$C$9*B$34+B$43+B$44+B$45)-IF(AND(MOD(L$56,$C$21)=0,L$56<Rates!$D$71),B$34,0),0) | M76: =IF(M$56<=Rates!$D$71,B$33*8760*$C$19*$C$14*Connectivity!$C$13/Rates!$D$4*(1+$C$22)^MOD(M$56-1,$C$21)*M$65-('Compute-Revenue'!$B$23+$C$9*B$34+B$43+B$44+B$45)-IF(AND(MOD(M$56,$C$21)=0,M$56<Rates!$D$71),B$34,0),0) | N76: =IF(N$56<=Rates!$D$71,B$33*8760*$C$19*$C$14*Connectivity!$C$13/Rates!$D$4*(1+$C$22)^MOD(N$56-1,$C$21)*N$65-('Compute-Revenue'!$B$23+$C$9*B$34+B$43+B$44+B$45)-IF(AND(MOD(N$56,$C$21)=0,N$56<Rates!$D$71),B$34,0),0) | O76: =IF(O$56<=Rates!$D$71,B$33*8760*$C$19*$C$14*Connectivity!$C$13/Rates!$D$4*(1+$C$22)^MOD(O$56-1,$C$21)*O$65-('Compute-Revenue'!$B$23+$C$9*B$34+B$43+B$44+B$45)-IF(AND(MOD(O$56,$C$21)=0,O$56<Rates!$D$71),B$34,0),0) | P76: =IF(P$56<=Rates!$D$71,B$33*8760*$C$19*$C$14*Connectivity!$C$13/Rates!$D$4*(1+$C$22)^MOD(P$56-1,$C$21)*P$65-('Compute-Revenue'!$B$23+$C$9*B$34+B$43+B$44+B$45)-IF(AND(MOD(P$56,$C$21)=0,P$56<Rates!$D$71),B$34,0),0) | Q76: =IF(Q$56<=Rates!$D$71,B$33*8760*$C$19*$C$14*Connectivity!$C$13/Rates!$D$4*(1+$C$22)^MOD(Q$56-1,$C$21)*Q$65-('Compute-Revenue'!$B$23+$C$9*B$34+B$43+B$44+B$45)-IF(AND(MOD(Q$56,$C$21)=0,Q$56<Rates!$D$71),B$34,0),0) | R76: =IF(R$56<=Rates!$D$71,B$33*8760*$C$19*$C$14*Connectivity!$C$13/Rates!$D$4*(1+$C$22)^MOD(R$56-1,$C$21)*R$65-('Compute-Revenue'!$B$23+$C$9*B$34+B$43+B$44+B$45)-IF(AND(MOD(R$56,$C$21)=0,R$56<Rates!$D$71),B$34,0),0) | S76: =IF(S$56<=Rates!$D$71,B$33*8760*$C$19*$C$14*Connectivity!$C$13/Rates!$D$4*(1+$C$22)^MOD(S$56-1,$C$21)*S$65-('Compute-Revenue'!$B$23+$C$9*B$34+B$43+B$44+B$45)-IF(AND(MOD(S$56,$C$21)=0,S$56<Rates!$D$71),B$34,0),0) | T76: =IF(T$56<=Rates!$D$71,B$33*8760*$C$19*$C$14*Connectivity!$C$13/Rates!$D$4*(1+$C$22)^MOD(T$56-1,$C$21)*T$65-('Compute-Revenue'!$B$23+$C$9*B$34+B$43+B$44+B$45)-IF(AND(MOD(T$56,$C$21)=0,T$56<Rates!$D$71),B$34,0),0) | U76: =IF(U$56<=Rates!$D$71,B$33*8760*$C$19*$C$14*Connectivity!$C$13/Rates!$D$4*(1+$C$22)^MOD(U$56-1,$C$21)*U$65-('Compute-Revenue'!$B$23+$C$9*B$34+B$43+B$44+B$45)-IF(AND(MOD(U$56,$C$21)=0,U$56<Rates!$D$71),B$34,0),0) | V76: =IF(V$56<=Rates!$D$71,B$33*8760*$C$19*$C$14*Connectivity!$C$13/Rates!$D$4*(1+$C$22)^MOD(V$56-1,$C$21)*V$65-('Compute-Revenue'!$B$23+$C$9*B$34+B$43+B$44+B$45)-IF(AND(MOD(V$56,$C$21)=0,V$56<Rates!$D$71),B$34,0),0) | W76: =IF(W$56<=Rates!$D$71,B$33*8760*$C$19*$C$14*Connectivity!$C$13/Rates!$D$4*(1+$C$22)^MOD(W$56-1,$C$21)*W$65-('Compute-Revenue'!$B$23+$C$9*B$34+B$43+B$44+B$45)-IF(AND(MOD(W$56,$C$21)=0,W$56<Rates!$D$71),B$34,0),0) | X76: =IF(X$56<=Rates!$D$71,B$33*8760*$C$19*$C$14*Connectivity!$C$13/Rates!$D$4*(1+$C$22)^MOD(X$56-1,$C$21)*X$65-('Compute-Revenue'!$B$23+$C$9*B$34+B$43+B$44+B$45)-IF(AND(MOD(X$56,$C$21)=0,X$56<Rates!$D$71),B$34,0),0) | Y76: =IF(Y$56<=Rates!$D$71,B$33*8760*$C$19*$C$14*Connectivity!$C$13/Rates!$D$4*(1+$C$22)^MOD(Y$56-1,$C$21)*Y$65-('Compute-Revenue'!$B$23+$C$9*B$34+B$43+B$44+B$45)-IF(AND(MOD(Y$56,$C$21)=0,Y$56<Rates!$D$71),B$34,0),0) | Z76: =IF(Z$56<=Rates!$D$71,B$33*8760*$C$19*$C$14*Connectivity!$C$13/Rates!$D$4*(1+$C$22)^MOD(Z$56-1,$C$21)*Z$65-('Compute-Revenue'!$B$23+$C$9*B$34+B$43+B$44+B$45)-IF(AND(MOD(Z$56,$C$21)=0,Z$56<Rates!$D$71),B$34,0),0) | AA76: =IF(AA$56<=Rates!$D$71,B$33*8760*$C$19*$C$14*Connectivity!$C$13/Rates!$D$4*(1+$C$22)^MOD(AA$56-1,$C$21)*AA$65-('Compute-Revenue'!$B$23+$C$9*B$34+B$43+B$44+B$45)-IF(AND(MOD(AA$56,$C$21)=0,AA$56<Rates!$D$71),B$34,0),0) | AB76: =IF(AB$56<=Rates!$D$71,B$33*8760*$C$19*$C$14*Connectivity!$C$13/Rates!$D$4*(1+$C$22)^MOD(AB$56-1,$C$21)*AB$65-('Compute-Revenue'!$B$23+$C$9*B$34+B$43+B$44+B$45)-IF(AND(MOD(AB$56,$C$21)=0,AB$56<Rates!$D$71),B$34,0),0)
A77: helper: p_low x u_high | C77: =-B$36 | D77: =IF(D$56<=Rates!$D$71,B$33*8760*$C$20*$C$14*Connectivity!$C$13/Rates!$D$4*(1+$C$22)^MOD(D$56-1,$C$21)*D$65-('Compute-Revenue'!$B$23+$C$9*B$34+B$43+B$44+B$45)-IF(AND(MOD(D$56,$C$21)=0,D$56<Rates!$D$71),B$34,0),0) | E77: =IF(E$56<=Rates!$D$71,B$33*8760*$C$20*$C$14*Connectivity!$C$13/Rates!$D$4*(1+$C$22)^MOD(E$56-1,$C$21)*E$65-('Compute-Revenue'!$B$23+$C$9*B$34+B$43+B$44+B$45)-IF(AND(MOD(E$56,$C$21)=0,E$56<Rates!$D$71),B$34,0),0) | F77: =IF(F$56<=Rates!$D$71,B$33*8760*$C$20*$C$14*Connectivity!$C$13/Rates!$D$4*(1+$C$22)^MOD(F$56-1,$C$21)*F$65-('Compute-Revenue'!$B$23+$C$9*B$34+B$43+B$44+B$45)-IF(AND(MOD(F$56,$C$21)=0,F$56<Rates!$D$71),B$34,0),0) | G77: =IF(G$56<=Rates!$D$71,B$33*8760*$C$20*$C$14*Connectivity!$C$13/Rates!$D$4*(1+$C$22)^MOD(G$56-1,$C$21)*G$65-('Compute-Revenue'!$B$23+$C$9*B$34+B$43+B$44+B$45)-IF(AND(MOD(G$56,$C$21)=0,G$56<Rates!$D$71),B$34,0),0) | H77: =IF(H$56<=Rates!$D$71,B$33*8760*$C$20*$C$14*Connectivity!$C$13/Rates!$D$4*(1+$C$22)^MOD(H$56-1,$C$21)*H$65-('Compute-Revenue'!$B$23+$C$9*B$34+B$43+B$44+B$45)-IF(AND(MOD(H$56,$C$21)=0,H$56<Rates!$D$71),B$34,0),0) | I77: =IF(I$56<=Rates!$D$71,B$33*8760*$C$20*$C$14*Connectivity!$C$13/Rates!$D$4*(1+$C$22)^MOD(I$56-1,$C$21)*I$65-('Compute-Revenue'!$B$23+$C$9*B$34+B$43+B$44+B$45)-IF(AND(MOD(I$56,$C$21)=0,I$56<Rates!$D$71),B$34,0),0) | J77: =IF(J$56<=Rates!$D$71,B$33*8760*$C$20*$C$14*Connectivity!$C$13/Rates!$D$4*(1+$C$22)^MOD(J$56-1,$C$21)*J$65-('Compute-Revenue'!$B$23+$C$9*B$34+B$43+B$44+B$45)-IF(AND(MOD(J$56,$C$21)=0,J$56<Rates!$D$71),B$34,0),0) | K77: =IF(K$56<=Rates!$D$71,B$33*8760*$C$20*$C$14*Connectivity!$C$13/Rates!$D$4*(1+$C$22)^MOD(K$56-1,$C$21)*K$65-('Compute-Revenue'!$B$23+$C$9*B$34+B$43+B$44+B$45)-IF(AND(MOD(K$56,$C$21)=0,K$56<Rates!$D$71),B$34,0),0) | L77: =IF(L$56<=Rates!$D$71,B$33*8760*$C$20*$C$14*Connectivity!$C$13/Rates!$D$4*(1+$C$22)^MOD(L$56-1,$C$21)*L$65-('Compute-Revenue'!$B$23+$C$9*B$34+B$43+B$44+B$45)-IF(AND(MOD(L$56,$C$21)=0,L$56<Rates!$D$71),B$34,0),0) | M77: =IF(M$56<=Rates!$D$71,B$33*8760*$C$20*$C$14*Connectivity!$C$13/Rates!$D$4*(1+$C$22)^MOD(M$56-1,$C$21)*M$65-('Compute-Revenue'!$B$23+$C$9*B$34+B$43+B$44+B$45)-IF(AND(MOD(M$56,$C$21)=0,M$56<Rates!$D$71),B$34,0),0) | N77: =IF(N$56<=Rates!$D$71,B$33*8760*$C$20*$C$14*Connectivity!$C$13/Rates!$D$4*(1+$C$22)^MOD(N$56-1,$C$21)*N$65-('Compute-Revenue'!$B$23+$C$9*B$34+B$43+B$44+B$45)-IF(AND(MOD(N$56,$C$21)=0,N$56<Rates!$D$71),B$34,0),0) | O77: =IF(O$56<=Rates!$D$71,B$33*8760*$C$20*$C$14*Connectivity!$C$13/Rates!$D$4*(1+$C$22)^MOD(O$56-1,$C$21)*O$65-('Compute-Revenue'!$B$23+$C$9*B$34+B$43+B$44+B$45)-IF(AND(MOD(O$56,$C$21)=0,O$56<Rates!$D$71),B$34,0),0) | P77: =IF(P$56<=Rates!$D$71,B$33*8760*$C$20*$C$14*Connectivity!$C$13/Rates!$D$4*(1+$C$22)^MOD(P$56-1,$C$21)*P$65-('Compute-Revenue'!$B$23+$C$9*B$34+B$43+B$44+B$45)-IF(AND(MOD(P$56,$C$21)=0,P$56<Rates!$D$71),B$34,0),0) | Q77: =IF(Q$56<=Rates!$D$71,B$33*8760*$C$20*$C$14*Connectivity!$C$13/Rates!$D$4*(1+$C$22)^MOD(Q$56-1,$C$21)*Q$65-('Compute-Revenue'!$B$23+$C$9*B$34+B$43+B$44+B$45)-IF(AND(MOD(Q$56,$C$21)=0,Q$56<Rates!$D$71),B$34,0),0) | R77: =IF(R$56<=Rates!$D$71,B$33*8760*$C$20*$C$14*Connectivity!$C$13/Rates!$D$4*(1+$C$22)^MOD(R$56-1,$C$21)*R$65-('Compute-Revenue'!$B$23+$C$9*B$34+B$43+B$44+B$45)-IF(AND(MOD(R$56,$C$21)=0,R$56<Rates!$D$71),B$34,0),0) | S77: =IF(S$56<=Rates!$D$71,B$33*8760*$C$20*$C$14*Connectivity!$C$13/Rates!$D$4*(1+$C$22)^MOD(S$56-1,$C$21)*S$65-('Compute-Revenue'!$B$23+$C$9*B$34+B$43+B$44+B$45)-IF(AND(MOD(S$56,$C$21)=0,S$56<Rates!$D$71),B$34,0),0) | T77: =IF(T$56<=Rates!$D$71,B$33*8760*$C$20*$C$14*Connectivity!$C$13/Rates!$D$4*(1+$C$22)^MOD(T$56-1,$C$21)*T$65-('Compute-Revenue'!$B$23+$C$9*B$34+B$43+B$44+B$45)-IF(AND(MOD(T$56,$C$21)=0,T$56<Rates!$D$71),B$34,0),0) | U77: =IF(U$56<=Rates!$D$71,B$33*8760*$C$20*$C$14*Connectivity!$C$13/Rates!$D$4*(1+$C$22)^MOD(U$56-1,$C$21)*U$65-('Compute-Revenue'!$B$23+$C$9*B$34+B$43+B$44+B$45)-IF(AND(MOD(U$56,$C$21)=0,U$56<Rates!$D$71),B$34,0),0) | V77: =IF(V$56<=Rates!$D$71,B$33*8760*$C$20*$C$14*Connectivity!$C$13/Rates!$D$4*(1+$C$22)^MOD(V$56-1,$C$21)*V$65-('Compute-Revenue'!$B$23+$C$9*B$34+B$43+B$44+B$45)-IF(AND(MOD(V$56,$C$21)=0,V$56<Rates!$D$71),B$34,0),0) | W77: =IF(W$56<=Rates!$D$71,B$33*8760*$C$20*$C$14*Connectivity!$C$13/Rates!$D$4*(1+$C$22)^MOD(W$56-1,$C$21)*W$65-('Compute-Revenue'!$B$23+$C$9*B$34+B$43+B$44+B$45)-IF(AND(MOD(W$56,$C$21)=0,W$56<Rates!$D$71),B$34,0),0) | X77: =IF(X$56<=Rates!$D$71,B$33*8760*$C$20*$C$14*Connectivity!$C$13/Rates!$D$4*(1+$C$22)^MOD(X$56-1,$C$21)*X$65-('Compute-Revenue'!$B$23+$C$9*B$34+B$43+B$44+B$45)-IF(AND(MOD(X$56,$C$21)=0,X$56<Rates!$D$71),B$34,0),0) | Y77: =IF(Y$56<=Rates!$D$71,B$33*8760*$C$20*$C$14*Connectivity!$C$13/Rates!$D$4*(1+$C$22)^MOD(Y$56-1,$C$21)*Y$65-('Compute-Revenue'!$B$23+$C$9*B$34+B$43+B$44+B$45)-IF(AND(MOD(Y$56,$C$21)=0,Y$56<Rates!$D$71),B$34,0),0) | Z77: =IF(Z$56<=Rates!$D$71,B$33*8760*$C$20*$C$14*Connectivity!$C$13/Rates!$D$4*(1+$C$22)^MOD(Z$56-1,$C$21)*Z$65-('Compute-Revenue'!$B$23+$C$9*B$34+B$43+B$44+B$45)-IF(AND(MOD(Z$56,$C$21)=0,Z$56<Rates!$D$71),B$34,0),0) | AA77: =IF(AA$56<=Rates!$D$71,B$33*8760*$C$20*$C$14*Connectivity!$C$13/Rates!$D$4*(1+$C$22)^MOD(AA$56-1,$C$21)*AA$65-('Compute-Revenue'!$B$23+$C$9*B$34+B$43+B$44+B$45)-IF(AND(MOD(AA$56,$C$21)=0,AA$56<Rates!$D$71),B$34,0),0) | AB77: =IF(AB$56<=Rates!$D$71,B$33*8760*$C$20*$C$14*Connectivity!$C$13/Rates!$D$4*(1+$C$22)^MOD(AB$56-1,$C$21)*AB$65-('Compute-Revenue'!$B$23+$C$9*B$34+B$43+B$44+B$45)-IF(AND(MOD(AB$56,$C$21)=0,AB$56<Rates!$D$71),B$34,0),0)
A78: helper: p_base x u_low | C78: =-B$36 | D78: =IF(D$56<=Rates!$D$71,B$33*8760*$C$18*$C$15*Connectivity!$C$13/Rates!$D$4*(1+$C$22)^MOD(D$56-1,$C$21)*D$65-('Compute-Revenue'!$B$23+$C$9*B$34+B$43+B$44+B$45)-IF(AND(MOD(D$56,$C$21)=0,D$56<Rates!$D$71),B$34,0),0) | E78: =IF(E$56<=Rates!$D$71,B$33*8760*$C$18*$C$15*Connectivity!$C$13/Rates!$D$4*(1+$C$22)^MOD(E$56-1,$C$21)*E$65-('Compute-Revenue'!$B$23+$C$9*B$34+B$43+B$44+B$45)-IF(AND(MOD(E$56,$C$21)=0,E$56<Rates!$D$71),B$34,0),0) | F78: =IF(F$56<=Rates!$D$71,B$33*8760*$C$18*$C$15*Connectivity!$C$13/Rates!$D$4*(1+$C$22)^MOD(F$56-1,$C$21)*F$65-('Compute-Revenue'!$B$23+$C$9*B$34+B$43+B$44+B$45)-IF(AND(MOD(F$56,$C$21)=0,F$56<Rates!$D$71),B$34,0),0) | G78: =IF(G$56<=Rates!$D$71,B$33*8760*$C$18*$C$15*Connectivity!$C$13/Rates!$D$4*(1+$C$22)^MOD(G$56-1,$C$21)*G$65-('Compute-Revenue'!$B$23+$C$9*B$34+B$43+B$44+B$45)-IF(AND(MOD(G$56,$C$21)=0,G$56<Rates!$D$71),B$34,0),0) | H78: =IF(H$56<=Rates!$D$71,B$33*8760*$C$18*$C$15*Connectivity!$C$13/Rates!$D$4*(1+$C$22)^MOD(H$56-1,$C$21)*H$65-('Compute-Revenue'!$B$23+$C$9*B$34+B$43+B$44+B$45)-IF(AND(MOD(H$56,$C$21)=0,H$56<Rates!$D$71),B$34,0),0) | I78: =IF(I$56<=Rates!$D$71,B$33*8760*$C$18*$C$15*Connectivity!$C$13/Rates!$D$4*(1+$C$22)^MOD(I$56-1,$C$21)*I$65-('Compute-Revenue'!$B$23+$C$9*B$34+B$43+B$44+B$45)-IF(AND(MOD(I$56,$C$21)=0,I$56<Rates!$D$71),B$34,0),0) | J78: =IF(J$56<=Rates!$D$71,B$33*8760*$C$18*$C$15*Connectivity!$C$13/Rates!$D$4*(1+$C$22)^MOD(J$56-1,$C$21)*J$65-('Compute-Revenue'!$B$23+$C$9*B$34+B$43+B$44+B$45)-IF(AND(MOD(J$56,$C$21)=0,J$56<Rates!$D$71),B$34,0),0) | K78: =IF(K$56<=Rates!$D$71,B$33*8760*$C$18*$C$15*Connectivity!$C$13/Rates!$D$4*(1+$C$22)^MOD(K$56-1,$C$21)*K$65-('Compute-Revenue'!$B$23+$C$9*B$34+B$43+B$44+B$45)-IF(AND(MOD(K$56,$C$21)=0,K$56<Rates!$D$71),B$34,0),0) | L78: =IF(L$56<=Rates!$D$71,B$33*8760*$C$18*$C$15*Connectivity!$C$13/Rates!$D$4*(1+$C$22)^MOD(L$56-1,$C$21)*L$65-('Compute-Revenue'!$B$23+$C$9*B$34+B$43+B$44+B$45)-IF(AND(MOD(L$56,$C$21)=0,L$56<Rates!$D$71),B$34,0),0) | M78: =IF(M$56<=Rates!$D$71,B$33*8760*$C$18*$C$15*Connectivity!$C$13/Rates!$D$4*(1+$C$22)^MOD(M$56-1,$C$21)*M$65-('Compute-Revenue'!$B$23+$C$9*B$34+B$43+B$44+B$45)-IF(AND(MOD(M$56,$C$21)=0,M$56<Rates!$D$71),B$34,0),0) | N78: =IF(N$56<=Rates!$D$71,B$33*8760*$C$18*$C$15*Connectivity!$C$13/Rates!$D$4*(1+$C$22)^MOD(N$56-1,$C$21)*N$65-('Compute-Revenue'!$B$23+$C$9*B$34+B$43+B$44+B$45)-IF(AND(MOD(N$56,$C$21)=0,N$56<Rates!$D$71),B$34,0),0) | O78: =IF(O$56<=Rates!$D$71,B$33*8760*$C$18*$C$15*Connectivity!$C$13/Rates!$D$4*(1+$C$22)^MOD(O$56-1,$C$21)*O$65-('Compute-Revenue'!$B$23+$C$9*B$34+B$43+B$44+B$45)-IF(AND(MOD(O$56,$C$21)=0,O$56<Rates!$D$71),B$34,0),0) | P78: =IF(P$56<=Rates!$D$71,B$33*8760*$C$18*$C$15*Connectivity!$C$13/Rates!$D$4*(1+$C$22)^MOD(P$56-1,$C$21)*P$65-('Compute-Revenue'!$B$23+$C$9*B$34+B$43+B$44+B$45)-IF(AND(MOD(P$56,$C$21)=0,P$56<Rates!$D$71),B$34,0),0) | Q78: =IF(Q$56<=Rates!$D$71,B$33*8760*$C$18*$C$15*Connectivity!$C$13/Rates!$D$4*(1+$C$22)^MOD(Q$56-1,$C$21)*Q$65-('Compute-Revenue'!$B$23+$C$9*B$34+B$43+B$44+B$45)-IF(AND(MOD(Q$56,$C$21)=0,Q$56<Rates!$D$71),B$34,0),0) | R78: =IF(R$56<=Rates!$D$71,B$33*8760*$C$18*$C$15*Connectivity!$C$13/Rates!$D$4*(1+$C$22)^MOD(R$56-1,$C$21)*R$65-('Compute-Revenue'!$B$23+$C$9*B$34+B$43+B$44+B$45)-IF(AND(MOD(R$56,$C$21)=0,R$56<Rates!$D$71),B$34,0),0) | S78: =IF(S$56<=Rates!$D$71,B$33*8760*$C$18*$C$15*Connectivity!$C$13/Rates!$D$4*(1+$C$22)^MOD(S$56-1,$C$21)*S$65-('Compute-Revenue'!$B$23+$C$9*B$34+B$43+B$44+B$45)-IF(AND(MOD(S$56,$C$21)=0,S$56<Rates!$D$71),B$34,0),0) | T78: =IF(T$56<=Rates!$D$71,B$33*8760*$C$18*$C$15*Connectivity!$C$13/Rates!$D$4*(1+$C$22)^MOD(T$56-1,$C$21)*T$65-('Compute-Revenue'!$B$23+$C$9*B$34+B$43+B$44+B$45)-IF(AND(MOD(T$56,$C$21)=0,T$56<Rates!$D$71),B$34,0),0) | U78: =IF(U$56<=Rates!$D$71,B$33*8760*$C$18*$C$15*Connectivity!$C$13/Rates!$D$4*(1+$C$22)^MOD(U$56-1,$C$21)*U$65-('Compute-Revenue'!$B$23+$C$9*B$34+B$43+B$44+B$45)-IF(AND(MOD(U$56,$C$21)=0,U$56<Rates!$D$71),B$34,0),0) | V78: =IF(V$56<=Rates!$D$71,B$33*8760*$C$18*$C$15*Connectivity!$C$13/Rates!$D$4*(1+$C$22)^MOD(V$56-1,$C$21)*V$65-('Compute-Revenue'!$B$23+$C$9*B$34+B$43+B$44+B$45)-IF(AND(MOD(V$56,$C$21)=0,V$56<Rates!$D$71),B$34,0),0) | W78: =IF(W$56<=Rates!$D$71,B$33*8760*$C$18*$C$15*Connectivity!$C$13/Rates!$D$4*(1+$C$22)^MOD(W$56-1,$C$21)*W$65-('Compute-Revenue'!$B$23+$C$9*B$34+B$43+B$44+B$45)-IF(AND(MOD(W$56,$C$21)=0,W$56<Rates!$D$71),B$34,0),0) | X78: =IF(X$56<=Rates!$D$71,B$33*8760*$C$18*$C$15*Connectivity!$C$13/Rates!$D$4*(1+$C$22)^MOD(X$56-1,$C$21)*X$65-('Compute-Revenue'!$B$23+$C$9*B$34+B$43+B$44+B$45)-IF(AND(MOD(X$56,$C$21)=0,X$56<Rates!$D$71),B$34,0),0) | Y78: =IF(Y$56<=Rates!$D$71,B$33*8760*$C$18*$C$15*Connectivity!$C$13/Rates!$D$4*(1+$C$22)^MOD(Y$56-1,$C$21)*Y$65-('Compute-Revenue'!$B$23+$C$9*B$34+B$43+B$44+B$45)-IF(AND(MOD(Y$56,$C$21)=0,Y$56<Rates!$D$71),B$34,0),0) | Z78: =IF(Z$56<=Rates!$D$71,B$33*8760*$C$18*$C$15*Connectivity!$C$13/Rates!$D$4*(1+$C$22)^MOD(Z$56-1,$C$21)*Z$65-('Compute-Revenue'!$B$23+$C$9*B$34+B$43+B$44+B$45)-IF(AND(MOD(Z$56,$C$21)=0,Z$56<Rates!$D$71),B$34,0),0) | AA78: =IF(AA$56<=Rates!$D$71,B$33*8760*$C$18*$C$15*Connectivity!$C$13/Rates!$D$4*(1+$C$22)^MOD(AA$56-1,$C$21)*AA$65-('Compute-Revenue'!$B$23+$C$9*B$34+B$43+B$44+B$45)-IF(AND(MOD(AA$56,$C$21)=0,AA$56<Rates!$D$71),B$34,0),0) | AB78: =IF(AB$56<=Rates!$D$71,B$33*8760*$C$18*$C$15*Connectivity!$C$13/Rates!$D$4*(1+$C$22)^MOD(AB$56-1,$C$21)*AB$65-('Compute-Revenue'!$B$23+$C$9*B$34+B$43+B$44+B$45)-IF(AND(MOD(AB$56,$C$21)=0,AB$56<Rates!$D$71),B$34,0),0)
